Workbook
Name UPDATE: 'Data Sheet'!$E$1

Sheet Financials>

Sheet One Page Profile 
B2: ='Data Sheet'!B1& " - One Page Profile" -> HINDUSTAN UNILEVER LTD - One Page Profile
C4: Hindustan Unilever Limited is India's largest Fast-Moving Consumer Goods (FMCG) company, with a legacy of over 90 years in the Indian market. The company is a subsidiary of Unilever and operates across Home Care, Beauty & Personal Care, and Foods & Refreshment segments. HUL owns several trusted brands that are used by millions of consumers every day. With a strong distribution network and focus on innovation, the company reaches a vast majority of Indian households. HUL is committed to sustainable business practices and aims to make sustainable living commonplace while delivering high-quality products to consumers.
B5: INR(Crs)
B6: Key Financial Metrics | C6: ='Data Sheet'!G16 -> 44286 | D6: ='Data Sheet'!H16 -> 44651 | E6: ='Data Sheet'!I16 -> 45016 | F6: ='Data Sheet'!J16 -> 45382 | G6: ='Data Sheet'!K16 -> 45747 | I6: Share Price - 5Y
B8: Total Sales | C8: ='Data Sheet'!G17 -> 47028 | D8: ='Data Sheet'!H17 -> 52446 | E8: ='Data Sheet'!I17 -> 60580 | F8: ='Data Sheet'!J17 -> 61896 | G8: ='Data Sheet'!K17 -> 63121
B9: Sales Growth (y-o-y) | C9: =HistoricalFS!H13 -> 0.18211296 | D9: =HistoricalFS!I13 -> 0.11520796 | E9: =HistoricalFS!J13 -> 0.15509286 | F9: =HistoricalFS!K13 -> 0.021723341 | G9: =HistoricalFS!L13 -> 0.019791263
B10: Gross Profit Margin(%) | C10: =HistoricalFS!H19 -> 0.46200136 | D10: =HistoricalFS!I19 -> 0.44579186 | E10: =HistoricalFS!J19 -> 0.41596236 | F10: =HistoricalFS!K19 -> 0.45632997 | G10: =HistoricalFS!L19 -> 0.45297128
B11: EBITDA Margins(%) | C11: =HistoricalFS!H25 -> 0.24721443 | D11: =HistoricalFS!I25 -> 0.24514739 | E11: =HistoricalFS!J25 -> 0.23352592 | F11: =HistoricalFS!K25 -> 0.23683275 | G11: =HistoricalFS!L25 -> 0.23515153
B12: EBIT Margins(%) | C12: =(HistoricalFS!H24-HistoricalFS!H30)/HistoricalFS!H12 -> 0.22437697 | D12: =(HistoricalFS!I24-HistoricalFS!I30)/HistoricalFS!I12 -> 0.22434504 | E12: =(HistoricalFS!J24-HistoricalFS!J30)/HistoricalFS!J12 -> 0.21475735 | F12: =(HistoricalFS!K24-HistoricalFS!K30)/HistoricalFS!K12 -> 0.21718689 | G12: =(HistoricalFS!L24-HistoricalFS!L30)/HistoricalFS!L12 -> 0.21368483
B13: Net Profit Margins(%) | C13: =HistoricalFS!H39/HistoricalFS!H12 -> 0.16647529 | D13: =HistoricalFS!I39/HistoricalFS!I12 -> 0.16537009 | E13: =HistoricalFS!J39/HistoricalFS!J12 -> 0.16003632 | F13: =HistoricalFS!K39/HistoricalFS!K12 -> 0.1529178 | G13: =HistoricalFS!L39/HistoricalFS!L12 -> 0.14811236
B14: Earnings Per Share (in Rs.) | C14: =HistoricalFS!H44 -> 33.320565 | D14: =HistoricalFS!I44 -> 36.912666 | E14: =HistoricalFS!J44 -> 41.262343 | F14: =HistoricalFS!K44 -> 40.283453 | G14: =HistoricalFS!L44 -> 39.789751
B15: EPS Growth y-o-y (%) | C15: =HistoricalFS!H45 -> 0.13917182 | D15: =HistoricalFS!I45 -> 0.10780432 | E15: =HistoricalFS!J45 -> 0.11783697 | F15: =HistoricalFS!K45 -> -0.023723569 | G15: =HistoricalFS!L45 -> -0.012255679
B16: Dividend Per Share | C16: =HistoricalFS!H47 -> 40.506895 | D16: =HistoricalFS!I47 -> 34.005788 | E16: =HistoricalFS!J47 -> 39.006639 | F16: =HistoricalFS!K47 -> 42.00715 | G16: =HistoricalFS!L47 -> 53.009023
B17: Dividend Growth y-o-y (%) | C17: =HistoricalFS!H47/HistoricalFS!G47-1 -> 0.6238764 | D17: =HistoricalFS!I47/HistoricalFS!H47-1 -> -0.16049383 | E17: =HistoricalFS!J47/HistoricalFS!I47-1 -> 0.14705882 | F17: =HistoricalFS!K47/HistoricalFS!J47-1 -> 0.076923077 | G17: =HistoricalFS!L47/HistoricalFS!K47-1 -> 0.26190476
B19: Key Financial Ratios | C19: =C6 -> 44286 | D19: =D6 -> 44651 | E19: =E6 -> 45016 | F19: =F6 -> 45382 | G19: =G6 -> 45747 | I19: Volume - 5Y
B21: Price to Earnings | C21: ='Data Sheet'!G90/HistoricalFS!H44 -> 69.840352 | D21: ='Data Sheet'!H90/HistoricalFS!I44 -> 53.117269 | E21: ='Data Sheet'!I90/HistoricalFS!J44 -> 59.386837 | F21: ='Data Sheet'!J90/HistoricalFS!K44 -> 53.797276 | G21: ='Data Sheet'!K90/HistoricalFS!L44 -> 54.332584
B22: EV/EBITDA | C22: =(('Data Sheet'!G93*'Data Sheet'!G90)+(SUM('Data Sheet'!G59:G60))-('Data Sheet'!G69))/'Data Sheet'!G33 -> 47.776044 | D22: =(('Data Sheet'!H93*'Data Sheet'!H90)+(SUM('Data Sheet'!H59:H60))-('Data Sheet'!H69))/'Data Sheet'!H33 -> 36.613724 | E22: =(('Data Sheet'!I93*'Data Sheet'!I90)+(SUM('Data Sheet'!I59:I60))-('Data Sheet'!I69))/'Data Sheet'!I33 -> 40.75284 | F22: =(('Data Sheet'!J93*'Data Sheet'!J90)+(SUM('Data Sheet'!J59:J60))-('Data Sheet'!J69))/'Data Sheet'!J33 -> 34.18675 | G22: =(('Data Sheet'!K93*'Data Sheet'!K90)+(SUM('Data Sheet'!K59:K60))-('Data Sheet'!K69))/'Data Sheet'!K33 -> 32.884986
B23: EV/Sales | C23: =(('Data Sheet'!G93*'Data Sheet'!G90)+(SUM('Data Sheet'!G59:G60))-('Data Sheet'!G69))/'Data Sheet'!G17 -> 11.979568 | D23: =(('Data Sheet'!H93*'Data Sheet'!H90)+(SUM('Data Sheet'!H59:H60))-('Data Sheet'!H69))/'Data Sheet'!H17 -> 9.119572 | E23: =(('Data Sheet'!I93*'Data Sheet'!I90)+(SUM('Data Sheet'!I59:I60))-('Data Sheet'!I69))/'Data Sheet'!I17 -> 9.8027465 | F23: =(('Data Sheet'!J93*'Data Sheet'!J90)+(SUM('Data Sheet'!J59:J60))-('Data Sheet'!J69))/'Data Sheet'!J17 -> 8.5450306 | G23: =(('Data Sheet'!K93*'Data Sheet'!K90)+(SUM('Data Sheet'!K59:K60))-('Data Sheet'!K69))/'Data Sheet'!K17 -> 8.4102331
B24: Price to Book Value | C24: =(('Data Sheet'!G93*'Data Sheet'!G90)/(SUM('Data Sheet'!G57:G58))) -> 11.469147 | D24: =(('Data Sheet'!H93*'Data Sheet'!H90)/(SUM('Data Sheet'!H57:H58))) -> 9.3900669 | E24: =(('Data Sheet'!I93*'Data Sheet'!I90)/(SUM('Data Sheet'!I57:I58))) -> 11.445519 | F24: =(('Data Sheet'!J93*'Data Sheet'!J90)/(SUM('Data Sheet'!J57:J58))) -> 9.9416458 | G24: =(('Data Sheet'!K93*'Data Sheet'!K90)/(SUM('Data Sheet'!K57:K58))) -> 10.28208
B25: Return on Equity (%) | C25: ='Ratio Analysis'!H29 -> 0.16421949 | D25: ='Ratio Analysis'!I29 -> 0.17677993 | E25: ='Ratio Analysis'!J29 -> 0.19272821 | F25: ='Ratio Analysis'!K29 -> 0.18479831 | G25: ='Ratio Analysis'!L29 -> 0.18924335 | H25: ='Ratio Analysis'!M29 -> 0
B26: Return on Capital Employed (%) | C26: ='Ratio Analysis'!H27 -> 0.22133658 | D26: ='Ratio Analysis'!I27 -> 0.23483155 | E26: ='Ratio Analysis'!J27 -> 0.25250859 | F26: ='Ratio Analysis'!K27 -> 0.25507571 | G26: ='Ratio Analysis'!L27 -> 0.26421156
B28: Top 10 Shareholders | C28: ='Hind. Uni Share Price Daily 5y'!C1239 -> N. Shares (In Crs.) | E28: ='Hind. Uni Share Price Daily 5y'!D1239 -> % Holding | F28: ='Hind. Uni Share Price Daily 5y'!E1239 -> Market Value (In Crs.) | I28: Shareholding Pattern
B29: ='Hind. Uni Share Price Daily 5y'!B1240 -> UNILEVER PLC | C29: ='Hind. Uni Share Price Daily 5y'!C1240 -> 111.43701 | E29: ='Hind. Uni Share Price Daily 5y'!D1240 -> 0.4743 | F29: ='Hind. Uni Share Price Daily 5y'!E1240 -> 248727.42
B30: ='Hind. Uni Share Price Daily 5y'!B1241 -> LIFE INSURANCE CORPORATION OF INDIA | C30: ='Hind. Uni Share Price Daily 5y'!C1241 -> 15.743276 | E30: ='Hind. Uni Share Price Daily 5y'!D1241 -> 0.067 | F30: ='Hind. Uni Share Price Daily 5y'!E1241 -> 35138.992
B31: ='Hind. Uni Share Price Daily 5y'!B1242 -> UNILEVER GROUP LIMITED | C31: ='Hind. Uni Share Price Daily 5y'!C1242 -> 10.673946 | E31: ='Hind. Uni Share Price Daily 5y'!D1242 -> 0.0454 | F31: ='Hind. Uni Share Price Daily 5y'!E1242 -> 23824.247
B32: ='Hind. Uni Share Price Daily 5y'!B1243 -> UNILEVER OVERSEAS HOLDINGS AG | C32: ='Hind. Uni Share Price Daily 5y'!C1243 -> 6.878432 | E32: ='Hind. Uni Share Price Daily 5y'!D1243 -> 0.0293 | F32: ='Hind. Uni Share Price Daily 5y'!E1243 -> 15352.66
B33: ='Hind. Uni Share Price Daily 5y'!B1244 -> UNILEVER UK&CN HOLDINGS LIMITED | C33: ='Hind. Uni Share Price Daily 5y'!C1244 -> 6.008625 | E33: ='Hind. Uni Share Price Daily 5y'!D1244 -> 0.0256 | F33: ='Hind. Uni Share Price Daily 5y'!E1244 -> 13411.251
B34: ='Hind. Uni Share Price Daily 5y'!B1245 -> UNILEVER SOUTH INDIA ESTATES LIMITED | C34: ='Hind. Uni Share Price Daily 5y'!C1245 -> 5.27472 | E34: ='Hind. Uni Share Price Daily 5y'!D1245 -> 0.0224 | F34: ='Hind. Uni Share Price Daily 5y'!E1245 -> 11773.175
B35: ='Hind. Uni Share Price Daily 5y'!B1246 -> SBI ESG EXCLUSIONARY STRATEGY FUND | C35: ='Hind. Uni Share Price Daily 5y'!C1246 -> 3.8897573 | E35: ='Hind. Uni Share Price Daily 5y'!D1246 -> 0.0166 | F35: ='Hind. Uni Share Price Daily 5y'!E1246 -> 8681.9383
B36: ='Hind. Uni Share Price Daily 5y'!B1247 -> ICICI PRUDENTIAL SENSEX ETF | C36: ='Hind. Uni Share Price Daily 5y'!C1247 -> 3.4496318 | E36: ='Hind. Uni Share Price Daily 5y'!D1247 -> 0.0147 | F36: ='Hind. Uni Share Price Daily 5y'!E1247 -> 7699.5782
B37: ='Hind. Uni Share Price Daily 5y'!B1248 -> UNILEVER ASSAM ESTATES LIMITED | C37: ='Hind. Uni Share Price Daily 5y'!C1248 -> 3.282048 | E37: ='Hind. Uni Share Price Daily 5y'!D1248 -> 0.014 | F37: ='Hind. Uni Share Price Daily 5y'!E1248 -> 7325.5311
B38: ='Hind. Uni Share Price Daily 5y'!B1249 -> UNILEVER OVERSEAS HOLDINGS B V | C38: ='Hind. Uni Share Price Daily 5y'!C1249 -> 1.8865 | E38: ='Hind. Uni Share Price Daily 5y'!D1249 -> 0.008 | F38: ='Hind. Uni Share Price Daily 5y'!E1249 -> 4210.668
B40: Managerial Remuneration | C40: Deisgnation | E40: Remunertaion (in Crs.) | I40: Capital Structure
B42: Rohit Jawa | C42: CEO & MD | E42: =223923213/10000000 -> 22.392321 | I42: Share Price as on April 2026 | K42: ='Data Sheet'!B8 -> 2082.5
B43: Madhusudhan Rao Rupanagudi | C43: Executive Director (Beauty) | E43: =129413118/10000000 -> 12.941312 | I43: Number of Shares o/s | K43: ='Data Sheet'!B6 -> 234.95918
B44: Ritesh Tiwari | C44: Executive Director (Finance & IT) | E44: =85560788/10000000 -> 8.5560788 | I44: Market Capitalisation | K44: =K42*K43 -> 489302.49
B45: Anuradha Razdan | C45: Executive Director (HR) | E45: =83181617/10000000 -> 8.3181617 | I45: Less : Cash & Equivalents | K45: =-'Data Sheet'!K69 -> -7554
B46: Kedar Lele | C46: Executive Director (Customer Dev.) | E46: =79572021/10000000 -> 7.9572021 | I46: Add : Total Debt | K46: ='Data Sheet'!K59 -> 1648
B47: Deepak Subramanian | C47: Executive Director (Home Care) | E47: =68250477/10000000 -> 6.8250477 | I47: Add : Minority Interest | K47: 22
I48: Enterprise Value | K48: =SUM(K44:K47) -> 483418.49
B50: Recent Updates

Sheet HistoricalFS
B3: ='Dupont Analysis'!B3 -> HINDUSTAN UNILEVER LTD
B4: ='Dupont Analysis'!B4 -> (HINDUNILVR | BSE Code: 500696)
B6: Historical Financial Statement
B8: ="Historical Financial Statement -"&'Data Sheet'!B1 -> Historical Financial Statement -HINDUSTAN UNILEVER LTD
B9: Years | C9: ='Data Sheet'!B16 -> 42460 | D9: ='Data Sheet'!C16 -> 42825 | E9: ='Data Sheet'!D16 -> 43190 | F9: ='Data Sheet'!E16 -> 43555 | G9: ='Data Sheet'!F16 -> 43921 | H9: ='Data Sheet'!G16 -> 44286 | I9: ='Data Sheet'!H16 -> 44651 | J9: ='Data Sheet'!I16 -> 45016 | ... L9: ='Data Sheet'!K16 -> 45747 | M9: LTM
A11: # | B11: Income Statement
B12: Sales | C12: =IFERROR('Data Sheet'!B17,0) -> 32186 | D12: =IFERROR('Data Sheet'!C17,0) -> 33162 | E12: =IFERROR('Data Sheet'!D17,0) -> 35545 | F12: =IFERROR('Data Sheet'!E17,0) -> 39310 | G12: =IFERROR('Data Sheet'!F17,0) -> 39783 | H12: =IFERROR('Data Sheet'!G17,0) -> 47028 | I12: =IFERROR('Data Sheet'!H17,0) -> 52446 | J12: =IFERROR('Data Sheet'!I17,0) -> 60580 | ... L12: =IFERROR('Data Sheet'!K17,0) -> 63121 | M12: =IFERROR(SUM('Data Sheet'!H42:K42),0) -> 64544
B13: Sales Growth | C13: - | D13: =(D12/C12)-1 -> 0.030323743 | E13: =(E12/D12)-1 -> 0.071859357 | F13: =(F12/E12)-1 -> 0.10592207 | G13: =(G12/F12)-1 -> 0.012032562 | H13: =(H12/G12)-1 -> 0.18211296 | I13: =(I12/H12)-1 -> 0.11520796 | J13: =(J12/I12)-1 -> 0.15509286 | K13: =(K12/J12)-1 -> 0.021723341 | ... M13: =(M12/L12)-1 -> 0.022544003
B15: COGS | C15: =IFERROR(SUM('Data Sheet'!B18,'Data Sheet'!B20:B22)-1*'Data Sheet'!B19,0) -> 18222 | D15: =IFERROR(SUM('Data Sheet'!C18,'Data Sheet'!C20:C22)-1*'Data Sheet'!C19,0) -> 18675 | E15: =IFERROR(SUM('Data Sheet'!D18,'Data Sheet'!D20:D22)-1*'Data Sheet'!D19,0) -> 19314 | F15: =IFERROR(SUM('Data Sheet'!E18,'Data Sheet'!E20:E22)-1*'Data Sheet'!E19,0) -> 21081 | G15: =IFERROR(SUM('Data Sheet'!F18,'Data Sheet'!F20:F22)-1*'Data Sheet'!F19,0) -> 20614 | H15: =IFERROR(SUM('Data Sheet'!G18,'Data Sheet'!G20:G22)-1*'Data Sheet'!G19,0) -> 25301 | I15: =IFERROR(SUM('Data Sheet'!H18,'Data Sheet'!H20:H22)-1*'Data Sheet'!H19,0) -> 29066 | J15: =IFERROR(SUM('Data Sheet'!I18,'Data Sheet'!I20:I22)-1*'Data Sheet'!I19,0) -> 35381 | ... L15: =IFERROR(SUM('Data Sheet'!K18,'Data Sheet'!K20:K22)-1*'Data Sheet'!K19,0) -> 34529 | M15: =IFERROR(SUM('Data Sheet'!H43:K43),0) -> 49646
B16: COGS % Sales | C16: =C15/C12 -> 0.56614677 | D16: =D15/D12 -> 0.56314456 | E16: =E15/E12 -> 0.54336756 | F16: =F15/F12 -> 0.53627576 | G16: =G15/G12 -> 0.51816102 | H16: =H15/H12 -> 0.53799864 | I16: =I15/I12 -> 0.55420814 | J16: =J15/J12 -> 0.58403764 | ... M16: =M15/M12 -> 0.76918071
B18: Gross Profit | C18: =C12-C15 -> 13964 | D18: =D12-D15 -> 14487 | E18: =E12-E15 -> 16231 | F18: =F12-F15 -> 18229 | G18: =G12-G15 -> 19169 | H18: =H12-H15 -> 21727 | I18: =I12-I15 -> 23380 | J18: =J12-J15 -> 25199 | ... M18: =M12-M15 -> 14898
B19: Gross Margin | C19: =IFERROR(C18/C12,0) -> 0.43385323 | D19: =IFERROR(D18/D12,0) -> 0.43685544 | E19: =IFERROR(E18/E12,0) -> 0.45663244 | F19: =IFERROR(F18/F12,0) -> 0.46372424 | G19: =IFERROR(G18/G12,0) -> 0.48183898 | H19: =IFERROR(H18/H12,0) -> 0.46200136 | I19: =IFERROR(I18/I12,0) -> 0.44579186 | J19: =IFERROR(J18/J12,0) -> 0.41596236 | ... M19: =IFERROR(M18/M12,0) -> 0.23081929
B21: Selling & General expenses | C21: =IFERROR(SUM('Data Sheet'!B23:B24),0) -> 8054 | D21: =IFERROR(SUM('Data Sheet'!C23:C24),0) -> 8159 | E21: =IFERROR(SUM('Data Sheet'!D23:D24),0) -> 8732 | F21: =IFERROR(SUM('Data Sheet'!E23:E24),0) -> 9349 | G21: =IFERROR(SUM('Data Sheet'!F23:F24),0) -> 9308 | H21: =IFERROR(SUM('Data Sheet'!G23:G24),0) -> 10101 | I21: =IFERROR(SUM('Data Sheet'!H23:H24),0) -> 10523 | J21: =IFERROR(SUM('Data Sheet'!I23:I24),0) -> 11052 | ... M21: =IFERROR(SUM('Data Sheet'!L23:L24),0) -> 0
B22: S&G Expense % Sales | C22: =C21/C12 -> 0.25023302 | D22: =D21/D12 -> 0.24603462 | E22: =E21/E12 -> 0.24566043 | F22: =F21/F12 -> 0.23782752 | G22: =G21/G12 -> 0.23396928 | H22: =H21/H12 -> 0.21478694 | I22: =I21/I12 -> 0.20064447 | J22: =J21/J12 -> 0.18243645 | ... L22: =L21/L12 -> 0.21781974
B24: EBIDTA | C24: =C18-C21 -> 5910 | D24: =D18-D21 -> 6328 | E24: =E18-E21 -> 7499 | F24: =F18-F21 -> 8880 | G24: =G18-G21 -> 9861 | H24: =H18-H21 -> 11626 | I24: =I18-I21 -> 12857 | J24: =J18-J21 -> 14147 | ... L24: =L18-L21 -> 14843 | M24: =IFERROR(SUM('Data Sheet'!H45:K47),0) -> 19460
B25: EBITDA Margins | C25: =C24/C12 -> 0.18362021 | D25: =D24/D12 -> 0.19082082 | E25: =E24/E12 -> 0.21097201 | F25: =F24/F12 -> 0.22589672 | G25: =G24/G12 -> 0.24786969 | H25: =H24/H12 -> 0.24721443 | I25: =I24/I12 -> 0.24514739 | J25: =J24/J12 -> 0.23352592 | ... M25: =M24/M12 -> 0.30149975
B27: Interest | C27: =IFERROR('Data Sheet'!B27,0) -> 17 | D27: =IFERROR('Data Sheet'!C27,0) -> 35 | E27: =IFERROR('Data Sheet'!D27,0) -> 26 | F27: =IFERROR('Data Sheet'!E27,0) -> 33 | G27: =IFERROR('Data Sheet'!F27,0) -> 118 | H27: =IFERROR('Data Sheet'!G27,0) -> 117 | I27: =IFERROR('Data Sheet'!H27,0) -> 106 | J27: =IFERROR('Data Sheet'!I27,0) -> 114 | ... L27: =IFERROR('Data Sheet'!K27,0) -> 395 | M27: =IFERROR(SUM('Data Sheet'!H46:K46),0) -> 419
B28: Interest % Sales | C28: =C27/C12 -> 0.00052817995 | D28: =D27/D12 -> 0.0010554249 | E28: =E27/E12 -> 0.00073146715 | F28: =F27/F12 -> 0.00083948105 | G28: =G27/G12 -> 0.002966091 | H28: =H27/H12 -> 0.0024878796 | I28: =I27/I12 -> 0.0020211265 | J28: =J27/J12 -> 0.0018818092 | ... M28: =M27/M12 -> 0.0064916956
B30: Depriciation | C30: =IFERROR('Data Sheet'!B26,0) -> 353 | D30: =IFERROR('Data Sheet'!C26,0) -> 432 | E30: =IFERROR('Data Sheet'!D26,0) -> 520 | F30: =IFERROR('Data Sheet'!E26,0) -> 565 | G30: =IFERROR('Data Sheet'!F26,0) -> 1002 | H30: =IFERROR('Data Sheet'!G26,0) -> 1074 | I30: =IFERROR('Data Sheet'!H26,0) -> 1091 | J30: =IFERROR('Data Sheet'!I26,0) -> 1137 | ... L30: =IFERROR('Data Sheet'!K26,0) -> 1355 | M30: =IFERROR(SUM('Data Sheet'!H45:K45),0) -> 1367
B31: Depriciation % Sales | C31: =C30/C12 -> 0.010967501 | D31: =D30/D12 -> 0.013026959 | E31: =E30/E12 -> 0.014629343 | F31: =F30/F12 -> 0.014372933 | G31: =G30/G12 -> 0.025186638 | H31: =H30/H12 -> 0.022837459 | I31: =I30/I12 -> 0.020802349 | J31: =J30/J12 -> 0.01876857 | ... M31: =M30/M12 -> 0.021179351
B33: Earnings Before Tax | C33: =IFERROR(C24-SUM(C27,C30),0) -> 5540 | D33: =IFERROR(D24-SUM(D27,D30),0) -> 5861 | E33: =IFERROR(E24-SUM(E27,E30),0) -> 6953 | F33: =IFERROR(F24-SUM(F27,F30),0) -> 8282 | G33: =IFERROR(G24-SUM(G27,G30),0) -> 8741 | H33: =IFERROR(H24-SUM(H27,H30),0) -> 10435 | I33: =IFERROR(I24-SUM(I27,I30),0) -> 11660 | J33: =IFERROR(J24-SUM(J27,J30),0) -> 12896 | ... M33: =IFERROR(M24-SUM(M27,M30),0) -> 17674
B34: EBT % Sales | C34: =C33/C12 -> 0.17212453 | D34: =D33/D12 -> 0.17673844 | E34: =E33/E12 -> 0.1956112 | F34: =F33/F12 -> 0.2106843 | G34: =G33/G12 -> 0.21971696 | H34: =H33/H12 -> 0.22188909 | I34: =I33/I12 -> 0.22232391 | J34: =J33/J12 -> 0.21287554 | ... M34: =M33/M12 -> 0.27382871
B36: Tax | C36: =IFERROR('Data Sheet'!B29,0) -> 1875 | D36: =IFERROR('Data Sheet'!C29,0) -> 1977 | E36: =IFERROR('Data Sheet'!D29,0) -> 2079 | F36: =IFERROR('Data Sheet'!E29,0) -> 2544 | G36: =IFERROR('Data Sheet'!F29,0) -> 2409 | H36: =IFERROR('Data Sheet'!G29,0) -> 2606 | I36: =IFERROR('Data Sheet'!H29,0) -> 2987 | J36: =IFERROR('Data Sheet'!I29,0) -> 3201 | ... L36: =IFERROR('Data Sheet'!K29,0) -> 3744 | M36: =IFERROR(SUM('Data Sheet'!H48:K48),0) -> 3134
B37: Effective Tax rate | C37: =C36/C33 -> 0.33844765 | D37: =D36/D33 -> 0.33731445 | E37: =E36/E33 -> 0.29900762 | F37: =F36/F33 -> 0.30717218 | G37: =G36/G33 -> 0.27559776 | H37: =H36/H33 -> 0.24973646 | I37: =I36/I33 -> 0.25617496 | J37: =J36/J33 -> 0.2482165 | ... M37: =M36/M33 -> 0.17732262
B39: Net Profit | C39: =IFERROR(C33-C36,0) -> 3665 | D39: =IFERROR(D33-D36,0) -> 3884 | E39: =IFERROR(E33-E36,0) -> 4874 | F39: =IFERROR(F33-F36,0) -> 5738 | G39: =IFERROR(G33-G36,0) -> 6332 | H39: =IFERROR(H33-H36,0) -> 7829 | I39: =IFERROR(I33-I36,0) -> 8673 | J39: =IFERROR(J33-J36,0) -> 9695 | ... M39: =IFERROR(M33-M36,0) -> 14540
B40: Net Margins | C40: =IFERROR(C39/C12,0) -> 0.11386938 | D40: =IFERROR(D39/D12,0) -> 0.11712201 | E40: =IFERROR(E39/E12,0) -> 0.13712196 | F40: =IFERROR(F39/F12,0) -> 0.14596795 | G40: =IFERROR(G39/G12,0) -> 0.15916346 | H40: =IFERROR(H39/H12,0) -> 0.16647529 | I40: =IFERROR(I39/I12,0) -> 0.16537009 | J40: =IFERROR(J39/J12,0) -> 0.16003632 | ... M40: =IFERROR(M39/M12,0) -> 0.22527268
B42: No. of Equity Shares | C42: =IFERROR('Data Sheet'!B93,0) -> 216.39 | D42: =IFERROR('Data Sheet'!C93,0) -> 216.43 | E42: =IFERROR('Data Sheet'!D93,0) -> 216.45 | F42: =IFERROR('Data Sheet'!E93,0) -> 216.47 | G42: =IFERROR('Data Sheet'!F93,0) -> 216.48 | H42: =IFERROR('Data Sheet'!G93,0) -> 234.96 | I42: =IFERROR('Data Sheet'!H93,0) -> 234.96 | J42: =IFERROR('Data Sheet'!I93,0) -> 234.96 | ... L42: =IFERROR('Data Sheet'!K93,0) -> 234.96
B44: Earnings Per Share | C44: =IFERROR(C39/C42,0) -> 16.937012 | D44: =IFERROR(D39/D42,0) -> 17.945756 | E44: =IFERROR(E39/E42,0) -> 22.517903 | F44: =IFERROR(F39/F42,0) -> 26.507137 | G44: =IFERROR(G39/G42,0) -> 29.249815 | H44: =IFERROR(H39/H42,0) -> 33.320565 | I44: =IFERROR(I39/I42,0) -> 36.912666 | J44: =IFERROR(J39/J42,0) -> 41.262343 | ... L44: =IFERROR(L39/L42,0) -> 39.789751
B45: EPS Growth % | D45: =IFERROR((D44/C44)-1,0) -> 0.059558573 | E45: =IFERROR((E44/D44)-1,0) -> 0.25477591 | F45: =IFERROR((F44/E44)-1,0) -> 0.17715836 | G45: =IFERROR((G44/F44)-1,0) -> 0.10346941 | H45: =IFERROR((H44/G44)-1,0) -> 0.13917182 | I45: =IFERROR((I44/H44)-1,0) -> 0.10780432 | J45: =IFERROR((J44/I44)-1,0) -> 0.11783697 | K45: =IFERROR((K44/J44)-1,0) -> -0.023723569 | L45: =IFERROR((L44/K44)-1,0) -> -0.012255679
B47: Dividend Per Share | C47: =IFERROR('Data Sheet'!B31/HistoricalFS!C42,0) -> 15.971163 | D47: =IFERROR('Data Sheet'!C31/HistoricalFS!D42,0) -> 16.966225 | E47: =IFERROR('Data Sheet'!D31/HistoricalFS!E42,0) -> 19.95842 | F47: =IFERROR('Data Sheet'!E31/HistoricalFS!F42,0) -> 21.952234 | G47: =IFERROR('Data Sheet'!F31/HistoricalFS!G42,0) -> 24.944568 | H47: =IFERROR('Data Sheet'!G31/HistoricalFS!H42,0) -> 40.506895 | I47: =IFERROR('Data Sheet'!H31/HistoricalFS!I42,0) -> 34.005788 | J47: =IFERROR('Data Sheet'!I31/HistoricalFS!J42,0) -> 39.006639 | ... L47: =IFERROR('Data Sheet'!K31/HistoricalFS!L42,0) -> 53.009023
B48: Dividend Payout Ratio | C48: =IFERROR(C47/C44,0) -> 0.94297408 | D48: =IFERROR(D47/D44,0) -> 0.9454171 | E48: =IFERROR(E47/E44,0) -> 0.88633566 | F48: =IFERROR(F47/F44,0) -> 0.82816312 | G48: =IFERROR(G47/G44,0) -> 0.85281112 | H48: =IFERROR(H47/H44,0) -> 1.2156725 | I48: =IFERROR(I47/I44,0) -> 0.92124986 | J48: =IFERROR(J47/J44,0) -> 0.94533265 | ... L48: =IFERROR(L47/L44,0) -> 1.332228
B50: Retained Earnings | C50: =IFERROR(1-C48,0) -> 0.057025921 | D50: =IFERROR(1-D48,0) -> 0.054582904 | E50: =IFERROR(1-E48,0) -> 0.11366434 | F50: =IFERROR(1-F48,0) -> 0.17183688 | G50: =IFERROR(1-G48,0) -> 0.14718888 | H50: =IFERROR(1-H48,0) -> -0.2156725 | I50: =IFERROR(1-I48,0) -> 0.078750144 | J50: =IFERROR(1-J48,0) -> 0.054667354 | ... L50: =IFERROR(1-L48,0) -> -0.33222805
A52: # | B52: Balance Sheet
B53: Equity Share Capital | C53: =IFERROR('Data Sheet'!B57,0) -> 216 | D53: =IFERROR('Data Sheet'!C57,0) -> 216 | E53: =IFERROR('Data Sheet'!D57,0) -> 216 | F53: =IFERROR('Data Sheet'!E57,0) -> 216 | G53: =IFERROR('Data Sheet'!F57,0) -> 216 | H53: =IFERROR('Data Sheet'!G57,0) -> 235 | I53: =IFERROR('Data Sheet'!H57,0) -> 235 | J53: =IFERROR('Data Sheet'!I57,0) -> 235 | ... L53: =IFERROR('Data Sheet'!K57,0) -> 235
B54: Reserves | C54: =IFERROR('Data Sheet'!B58,0) -> 6357 | D54: =IFERROR('Data Sheet'!C58,0) -> 6528 | E54: =IFERROR('Data Sheet'!D58,0) -> 7065 | F54: =IFERROR('Data Sheet'!E58,0) -> 7651 | G54: =IFERROR('Data Sheet'!F58,0) -> 8013 | H54: =IFERROR('Data Sheet'!G58,0) -> 47439 | I54: =IFERROR('Data Sheet'!H58,0) -> 48826 | J54: =IFERROR('Data Sheet'!I58,0) -> 50069 | ... L54: =IFERROR('Data Sheet'!K58,0) -> 49167
B55: Borrowings | C55: =IFERROR('Data Sheet'!B59,0) -> 177 | D55: =IFERROR('Data Sheet'!C59,0) -> 277 | E55: =IFERROR('Data Sheet'!D59,0) -> 0 | F55: =IFERROR('Data Sheet'!E59,0) -> 99 | G55: =IFERROR('Data Sheet'!F59,0) -> 0 | H55: =IFERROR('Data Sheet'!G59,0) -> 0 | I55: =IFERROR('Data Sheet'!H59,0) -> 1043 | J55: =IFERROR('Data Sheet'!I59,0) -> 1219 | ... L55: =IFERROR('Data Sheet'!K59,0) -> 1648
B56: Other Liabilities | C56: =IFERROR('Data Sheet'!B60,0) -> 8043 | D56: =IFERROR('Data Sheet'!C60,0) -> 8685 | E56: =IFERROR('Data Sheet'!D60,0) -> 10581 | F56: =IFERROR('Data Sheet'!E60,0) -> 10663 | G56: =IFERROR('Data Sheet'!F60,0) -> 11924 | H56: =IFERROR('Data Sheet'!G60,0) -> 21066 | I56: =IFERROR('Data Sheet'!H60,0) -> 20402 | J56: =IFERROR('Data Sheet'!I60,0) -> 21554 | ... L56: =IFERROR('Data Sheet'!K60,0) -> 28813
B57: Total Liabilities | C57: =IFERROR('Data Sheet'!B61,0) -> 14793 | D57: =IFERROR('Data Sheet'!C61,0) -> 15706 | E57: =IFERROR('Data Sheet'!D61,0) -> 17862 | F57: =IFERROR('Data Sheet'!E61,0) -> 18629 | G57: =IFERROR('Data Sheet'!F61,0) -> 20153 | H57: =IFERROR('Data Sheet'!G61,0) -> 68740 | I57: =IFERROR('Data Sheet'!H61,0) -> 70506 | J57: =IFERROR('Data Sheet'!I61,0) -> 73077 | ... L57: =IFERROR('Data Sheet'!K61,0) -> 79863
B59: Fixed Assets Net Block | C59: =IFERROR('Data Sheet'!B62,0) -> 3258 | D59: =IFERROR('Data Sheet'!C62,0) -> 4419 | E59: =IFERROR('Data Sheet'!D62,0) -> 4528 | F59: =IFERROR('Data Sheet'!E62,0) -> 4715 | G59: =IFERROR('Data Sheet'!F62,0) -> 5479 | H59: =IFERROR('Data Sheet'!G62,0) -> 51443 | I59: =IFERROR('Data Sheet'!H62,0) -> 51473 | J59: =IFERROR('Data Sheet'!I62,0) -> 52678 | ... L59: =IFERROR('Data Sheet'!K62,0) -> 54335
B60: Capital Work in Progress | C60: =IFERROR('Data Sheet'!B63,0) -> 408 | D60: =IFERROR('Data Sheet'!C63,0) -> 229 | E60: =IFERROR('Data Sheet'!D63,0) -> 461 | F60: =IFERROR('Data Sheet'!E63,0) -> 406 | G60: =IFERROR('Data Sheet'!F63,0) -> 597 | H60: =IFERROR('Data Sheet'!G63,0) -> 745 | I60: =IFERROR('Data Sheet'!H63,0) -> 1313 | J60: =IFERROR('Data Sheet'!I63,0) -> 1132 | ... L60: =IFERROR('Data Sheet'!K63,0) -> 1009
B61: Investments | C61: =IFERROR('Data Sheet'!B64,0) -> 2592 | D61: =IFERROR('Data Sheet'!C64,0) -> 3794 | E61: =IFERROR('Data Sheet'!D64,0) -> 2873 | F61: =IFERROR('Data Sheet'!E64,0) -> 2716 | G61: =IFERROR('Data Sheet'!F64,0) -> 1255 | H61: =IFERROR('Data Sheet'!G64,0) -> 2709 | I61: =IFERROR('Data Sheet'!H64,0) -> 3521 | J61: =IFERROR('Data Sheet'!I64,0) -> 2882 | ... L61: =IFERROR('Data Sheet'!K64,0) -> 3810
B62: Other Assets | C62: =IFERROR('Data Sheet'!B65-SUM('Data Sheet'!B67:B69),0) -> 1536 | D62: =IFERROR('Data Sheet'!C65-SUM('Data Sheet'!C67:C69),0) -> 1810 | E62: =IFERROR('Data Sheet'!D65-SUM('Data Sheet'!D67:D69),0) -> 2692 | F62: =IFERROR('Data Sheet'!E65-SUM('Data Sheet'!E67:E69),0) -> 2645 | G62: =IFERROR('Data Sheet'!F65-SUM('Data Sheet'!F67:F69),0) -> 3793 | H62: =IFERROR('Data Sheet'!G65-SUM('Data Sheet'!G67:G69),0) -> 4035 | I62: =IFERROR('Data Sheet'!H65-SUM('Data Sheet'!H67:H69),0) -> 4021 | J62: =IFERROR('Data Sheet'!I65-SUM('Data Sheet'!I67:I69),0) -> 4377 | ... L62: =IFERROR('Data Sheet'!K65-SUM('Data Sheet'!K67:K69),0) -> 4921
B63: Total Non-Current Assets | C63: =SUM(C59:C62) -> 7794 | D63: =SUM(D59:D62) -> 10252 | E63: =SUM(E59:E62) -> 10554 | F63: =SUM(F59:F62) -> 10482 | G63: =SUM(G59:G62) -> 11124 | H63: =SUM(H59:H62) -> 58932 | I63: =SUM(I59:I62) -> 60328 | J63: =SUM(J59:J62) -> 61069 | ... L63: =SUM(L59:L62) -> 64075
B65: Receivables | C65: =IFERROR('Data Sheet'!B67,0) -> 1264 | D65: =IFERROR('Data Sheet'!C67,0) -> 1085 | E65: =IFERROR('Data Sheet'!D67,0) -> 1310 | F65: =IFERROR('Data Sheet'!E67,0) -> 1816 | G65: =IFERROR('Data Sheet'!F67,0) -> 1149 | H65: =IFERROR('Data Sheet'!G67,0) -> 1758 | I65: =IFERROR('Data Sheet'!H67,0) -> 2236 | J65: =IFERROR('Data Sheet'!I67,0) -> 3079 | ... L65: =IFERROR('Data Sheet'!K67,0) -> 3819
B66: Inventory | C66: =IFERROR('Data Sheet'!B68,0) -> 2726 | D66: =IFERROR('Data Sheet'!C68,0) -> 2541 | E66: =IFERROR('Data Sheet'!D68,0) -> 2513 | F66: =IFERROR('Data Sheet'!E68,0) -> 2574 | G66: =IFERROR('Data Sheet'!F68,0) -> 2767 | H66: =IFERROR('Data Sheet'!G68,0) -> 3579 | I66: =IFERROR('Data Sheet'!H68,0) -> 4096 | J66: =IFERROR('Data Sheet'!I68,0) -> 4251 | ... L66: =IFERROR('Data Sheet'!K68,0) -> 4415
B67: Cash & Bank | C67: =IFERROR('Data Sheet'!B69,0) -> 3009 | D67: =IFERROR('Data Sheet'!C69,0) -> 1828 | E67: =IFERROR('Data Sheet'!D69,0) -> 3485 | F67: =IFERROR('Data Sheet'!E69,0) -> 3757 | G67: =IFERROR('Data Sheet'!F69,0) -> 5113 | H67: =IFERROR('Data Sheet'!G69,0) -> 4471 | I67: =IFERROR('Data Sheet'!H69,0) -> 3846 | J67: =IFERROR('Data Sheet'!I69,0) -> 4678 | ... L67: =IFERROR('Data Sheet'!K69,0) -> 7554
B68: Total Current Assets | C68: =IFERROR(SUM(C65:C67),0) -> 6999 | D68: =IFERROR(SUM(D65:D67),0) -> 5454 | E68: =IFERROR(SUM(E65:E67),0) -> 7308 | F68: =IFERROR(SUM(F65:F67),0) -> 8147 | G68: =IFERROR(SUM(G65:G67),0) -> 9029 | H68: =IFERROR(SUM(H65:H67),0) -> 9808 | I68: =IFERROR(SUM(I65:I67),0) -> 10178 | J68: =IFERROR(SUM(J65:J67),0) -> 12008 | ... L68: =IFERROR(SUM(L65:L67),0) -> 15788
B70: Total Assets | C70: =SUM(C68,C63) -> 14793 | D70: =SUM(D68,D63) -> 15706 | E70: =SUM(E68,E63) -> 17862 | F70: =SUM(F68,F63) -> 18629 | G70: =SUM(G68,G63) -> 20153 | H70: =SUM(H68,H63) -> 68740 | I70: =SUM(I68,I63) -> 70506 | J70: =SUM(J68,J63) -> 73077 | ... L70: =SUM(L68,L63) -> 79863
A72: # | B72: Cash Flow Statements
B73: Operating Activities
B74: Profit from operations | C74: =IFERROR('Cash Flow Data'!H4,0) -> 6025 | D74: =IFERROR('Cash Flow Data'!I4,0) -> 6512 | E74: =IFERROR('Cash Flow Data'!J4,0) -> 7485 | F74: =IFERROR('Cash Flow Data'!K4,0) -> 8909 | G74: =IFERROR('Cash Flow Data'!L4,0) -> 9723 | H74: =IFERROR('Cash Flow Data'!M4,0) -> 11672 | I74: =IFERROR('Cash Flow Data'!N4,0) -> 12829 | J74: =IFERROR('Cash Flow Data'!O4,0) -> 14089 | ... L74: =IFERROR('Cash Flow Data'!Q4,0) -> 14942
B75: Receivables | C75: =IFERROR('Cash Flow Data'!H5,0) -> -257 | D75: =IFERROR('Cash Flow Data'!I5,0) -> 173 | E75: =IFERROR('Cash Flow Data'!J5,0) -> 0 | F75: =IFERROR('Cash Flow Data'!K5,0) -> 0 | G75: =IFERROR('Cash Flow Data'!L5,0) -> 0 | H75: =IFERROR('Cash Flow Data'!M5,0) -> 0 | I75: =IFERROR('Cash Flow Data'!N5,0) -> 0 | J75: =IFERROR('Cash Flow Data'!O5,0) -> 0 | ... L75: =IFERROR('Cash Flow Data'!Q5,0) -> 0
B76: Inventory | C76: =IFERROR('Cash Flow Data'!H6,0) -> 89 | D76: =IFERROR('Cash Flow Data'!I6,0) -> 37 | E76: =IFERROR('Cash Flow Data'!J6,0) -> -146 | F76: =IFERROR('Cash Flow Data'!K6,0) -> -195 | G76: =IFERROR('Cash Flow Data'!L6,0) -> -331 | H76: =IFERROR('Cash Flow Data'!M6,0) -> -543 | I76: =IFERROR('Cash Flow Data'!N6,0) -> -758 | J76: =IFERROR('Cash Flow Data'!O6,0) -> -339 | ... L76: =IFERROR('Cash Flow Data'!Q6,0) -> -584
B77: Payables | C77: =IFERROR('Cash Flow Data'!H7,0) -> 164 | D77: =IFERROR('Cash Flow Data'!I7,0) -> 501 | E77: =IFERROR('Cash Flow Data'!J7,0) -> 0 | F77: =IFERROR('Cash Flow Data'!K7,0) -> 0 | G77: =IFERROR('Cash Flow Data'!L7,0) -> 0 | H77: =IFERROR('Cash Flow Data'!M7,0) -> 0 | I77: =IFERROR('Cash Flow Data'!N7,0) -> 0 | J77: =IFERROR('Cash Flow Data'!O7,0) -> 0 | ... L77: =IFERROR('Cash Flow Data'!Q7,0) -> 0
B78: Loans Advances | C78: =IFERROR('Cash Flow Data'!H8,0) -> 0 | D78: =IFERROR('Cash Flow Data'!I8,0) -> 0 | E78: =IFERROR('Cash Flow Data'!J8,0) -> 0 | F78: =IFERROR('Cash Flow Data'!K8,0) -> 0 | G78: =IFERROR('Cash Flow Data'!L8,0) -> 0 | H78: =IFERROR('Cash Flow Data'!M8,0) -> 0 | I78: =IFERROR('Cash Flow Data'!N8,0) -> 0 | J78: =IFERROR('Cash Flow Data'!O8,0) -> 0 | ... L78: =IFERROR('Cash Flow Data'!Q8,0) -> 0
B79: Operating Deposits | C79: =IFERROR('Cash Flow Data'!H9,0) -> 0 | D79: =IFERROR('Cash Flow Data'!I9,0) -> -46 | E79: =IFERROR('Cash Flow Data'!J9,0) -> 0 | F79: =IFERROR('Cash Flow Data'!K9,0) -> 0 | G79: =IFERROR('Cash Flow Data'!L9,0) -> 0 | H79: =IFERROR('Cash Flow Data'!M9,0) -> 0 | I79: =IFERROR('Cash Flow Data'!N9,0) -> 0 | J79: =IFERROR('Cash Flow Data'!O9,0) -> 0 | ... L79: =IFERROR('Cash Flow Data'!Q9,0) -> 0
B80: Other WC items | C80: =IFERROR('Cash Flow Data'!H10,0) -> -77 | D80: =IFERROR('Cash Flow Data'!I10,0) -> -99 | E80: =IFERROR('Cash Flow Data'!J10,0) -> 982 | F80: =IFERROR('Cash Flow Data'!K10,0) -> -147 | G80: =IFERROR('Cash Flow Data'!L10,0) -> 742 | H80: =IFERROR('Cash Flow Data'!M10,0) -> 442 | I80: =IFERROR('Cash Flow Data'!N10,0) -> -242 | J80: =IFERROR('Cash Flow Data'!O10,0) -> -621 | ... L80: =IFERROR('Cash Flow Data'!Q10,0) -> -204
B81: Direct Taxes | C81: =IFERROR('Cash Flow Data'!H11,0) -> -1765 | D81: =IFERROR('Cash Flow Data'!I11,0) -> -1859 | E81: =IFERROR('Cash Flow Data'!J11,0) -> -2264 | F81: =IFERROR('Cash Flow Data'!K11,0) -> -2767 | G81: =IFERROR('Cash Flow Data'!L11,0) -> -2505 | H81: =IFERROR('Cash Flow Data'!M11,0) -> -2407 | I81: =IFERROR('Cash Flow Data'!N11,0) -> -2784 | J81: =IFERROR('Cash Flow Data'!O11,0) -> -3138 | ... L81: =IFERROR('Cash Flow Data'!Q11,0) -> -2268
B82: Other Opertaing Items | C82: =IFERROR('Cash Flow Data'!H12,0) -> -8 | D82: =IFERROR('Cash Flow Data'!I12,0) -> -21 | E82: =IFERROR('Cash Flow Data'!J12,0) -> 0 | F82: =IFERROR('Cash Flow Data'!K12,0) -> 0 | G82: =IFERROR('Cash Flow Data'!L12,0) -> 0 | H82: =IFERROR('Cash Flow Data'!M12,0) -> 0 | I82: =IFERROR('Cash Flow Data'!N12,0) -> 0 | J82: =IFERROR('Cash Flow Data'!O12,0) -> 0 | ... L82: =IFERROR('Cash Flow Data'!Q12,0) -> 0
B83: Exceptional CF Items | C83: =IFERROR('Cash Flow Data'!H13,0) -> 0 | D83: =IFERROR('Cash Flow Data'!I13,0) -> -13 | E83: =IFERROR('Cash Flow Data'!J13,0) -> 2 | F83: =IFERROR('Cash Flow Data'!K13,0) -> 0 | G83: =IFERROR('Cash Flow Data'!L13,0) -> -6 | H83: =IFERROR('Cash Flow Data'!M13,0) -> -1 | I83: =IFERROR('Cash Flow Data'!N13,0) -> 3 | J83: =IFERROR('Cash Flow Data'!O13,0) -> 0 | ... L83: =IFERROR('Cash Flow Data'!Q13,0) -> 0
B84: Cash From Operating Activities | C84: =SUM(C74:C83) -> 4171 | D84: =SUM(D74:D83) -> 5185 | E84: =SUM(E74:E83) -> 6059 | F84: =SUM(F74:F83) -> 5800 | G84: =SUM(G74:G83) -> 7623 | H84: =SUM(H74:H83) -> 9163 | I84: =SUM(I74:I83) -> 9048 | J84: =SUM(J74:J83) -> 9991 | ... L84: =SUM(L74:L83) -> 11886
B86: Investing Activities
B87: Fixed assets purchased | C87: =IFERROR('Cash Flow Data'!H15,0) -> -810 | D87: =IFERROR('Cash Flow Data'!I15,0) -> -1113 | E87: =IFERROR('Cash Flow Data'!J15,0) -> -895 | F87: =IFERROR('Cash Flow Data'!K15,0) -> -767 | G87: =IFERROR('Cash Flow Data'!L15,0) -> -862 | H87: =IFERROR('Cash Flow Data'!M15,0) -> -4163 | I87: =IFERROR('Cash Flow Data'!N15,0) -> -1228 | J87: =IFERROR('Cash Flow Data'!O15,0) -> -1192 | ... L87: =IFERROR('Cash Flow Data'!Q15,0) -> -1275
B88: Fixed assets sold | C88: =IFERROR('Cash Flow Data'!H16,0) -> 99 | D88: =IFERROR('Cash Flow Data'!I16,0) -> 176 | E88: =IFERROR('Cash Flow Data'!J16,0) -> 32 | F88: =IFERROR('Cash Flow Data'!K16,0) -> 13 | G88: =IFERROR('Cash Flow Data'!L16,0) -> 52 | H88: =IFERROR('Cash Flow Data'!M16,0) -> 97 | I88: =IFERROR('Cash Flow Data'!N16,0) -> 175 | J88: =IFERROR('Cash Flow Data'!O16,0) -> 181 | ... L88: =IFERROR('Cash Flow Data'!Q16,0) -> 13
B89: Investments purchased | C89: =IFERROR('Cash Flow Data'!H17,0) -> -20666 | D89: =IFERROR('Cash Flow Data'!I17,0) -> -31214 | E89: =IFERROR('Cash Flow Data'!J17,0) -> -51855 | F89: =IFERROR('Cash Flow Data'!K17,0) -> -74365 | G89: =IFERROR('Cash Flow Data'!L17,0) -> -36090 | H89: =IFERROR('Cash Flow Data'!M17,0) -> -39920 | I89: =IFERROR('Cash Flow Data'!N17,0) -> -48522 | J89: =IFERROR('Cash Flow Data'!O17,0) -> -22649 | ... L89: =IFERROR('Cash Flow Data'!Q17,0) -> -22957
B90: Investments sold | C90: =IFERROR('Cash Flow Data'!H18,0) -> 20937 | D90: =IFERROR('Cash Flow Data'!I18,0) -> 30083 | E90: =IFERROR('Cash Flow Data'!J18,0) -> 52897 | F90: =IFERROR('Cash Flow Data'!K18,0) -> 74691 | G90: =IFERROR('Cash Flow Data'!L18,0) -> 37690 | H90: =IFERROR('Cash Flow Data'!M18,0) -> 38486 | I90: =IFERROR('Cash Flow Data'!N18,0) -> 47786 | J90: =IFERROR('Cash Flow Data'!O18,0) -> 23462 | ... L90: =IFERROR('Cash Flow Data'!Q18,0) -> 23987
B91: Interest received | C91: =IFERROR('Cash Flow Data'!H19,0) -> 315 | D91: =IFERROR('Cash Flow Data'!I19,0) -> 264 | E91: =IFERROR('Cash Flow Data'!J19,0) -> 297 | F91: =IFERROR('Cash Flow Data'!K19,0) -> 289 | G91: =IFERROR('Cash Flow Data'!L19,0) -> 351 | H91: =IFERROR('Cash Flow Data'!M19,0) -> 277 | I91: =IFERROR('Cash Flow Data'!N19,0) -> 161 | J91: =IFERROR('Cash Flow Data'!O19,0) -> 259 | ... L91: =IFERROR('Cash Flow Data'!Q19,0) -> 835
B92: Dividends received | C92: =IFERROR('Cash Flow Data'!H20,0) -> 33 | D92: =IFERROR('Cash Flow Data'!I20,0) -> 14 | E92: =IFERROR('Cash Flow Data'!J20,0) -> 0 | F92: =IFERROR('Cash Flow Data'!K20,0) -> 1 | G92: =IFERROR('Cash Flow Data'!L20,0) -> 1 | H92: =IFERROR('Cash Flow Data'!M20,0) -> 1 | I92: =IFERROR('Cash Flow Data'!N20,0) -> 1 | J92: =IFERROR('Cash Flow Data'!O20,0) -> 2 | ... L92: =IFERROR('Cash Flow Data'!Q20,0) -> 0
B93: Invest in Susidiaries | C93: =IFERROR('Cash Flow Data'!H21,0) -> 0 | D93: =IFERROR('Cash Flow Data'!I21,0) -> 0 | E93: =IFERROR('Cash Flow Data'!J21,0) -> 0 | F93: =IFERROR('Cash Flow Data'!K21,0) -> 0 | G93: =IFERROR('Cash Flow Data'!L21,0) -> 0 | H93: =IFERROR('Cash Flow Data'!M21,0) -> 0 | I93: =IFERROR('Cash Flow Data'!N21,0) -> 0 | J93: =IFERROR('Cash Flow Data'!O21,0) -> 0 | ... L93: =IFERROR('Cash Flow Data'!Q21,0) -> 0
B94: Loans to Subsidiaries | C94: =IFERROR('Cash Flow Data'!H22,0) -> 0 | D94: =IFERROR('Cash Flow Data'!I22,0) -> 0 | E94: =IFERROR('Cash Flow Data'!J22,0) -> 0 | F94: =IFERROR('Cash Flow Data'!K22,0) -> 0 | G94: =IFERROR('Cash Flow Data'!L22,0) -> 0 | H94: =IFERROR('Cash Flow Data'!M22,0) -> 0 | I94: =IFERROR('Cash Flow Data'!N22,0) -> 0 | J94: =IFERROR('Cash Flow Data'!O22,0) -> 0 | ... L94: =IFERROR('Cash Flow Data'!Q22,0) -> 0
B95: Redemp n Canc of Shares | C95: =IFERROR('Cash Flow Data'!H23,0) -> 161 | D95: =IFERROR('Cash Flow Data'!I23,0) -> 20 | E95: =IFERROR('Cash Flow Data'!J23,0) -> 73 | F95: =IFERROR('Cash Flow Data'!K23,0) -> 0 | G95: =IFERROR('Cash Flow Data'!L23,0) -> 0 | H95: =IFERROR('Cash Flow Data'!M23,0) -> 0 | I95: =IFERROR('Cash Flow Data'!N23,0) -> 0 | J95: =IFERROR('Cash Flow Data'!O23,0) -> 0 | ... L95: =IFERROR('Cash Flow Data'!Q23,0) -> 0
B96: Acquisition of companies | C96: =IFERROR('Cash Flow Data'!H24,0) -> 0 | D96: =IFERROR('Cash Flow Data'!I24,0) -> 0 | E96: =IFERROR('Cash Flow Data'!J24,0) -> 0 | F96: =IFERROR('Cash Flow Data'!K24,0) -> 0 | G96: =IFERROR('Cash Flow Data'!L24,0) -> 0 | H96: =IFERROR('Cash Flow Data'!M24,0) -> 0 | I96: =IFERROR('Cash Flow Data'!N24,0) -> 0 | J96: =IFERROR('Cash Flow Data'!O24,0) -> -334 | ... L96: =IFERROR('Cash Flow Data'!Q24,0) -> 0
B97: Other investing items | C97: =IFERROR('Cash Flow Data'!H25,0) -> -351 | D97: =IFERROR('Cash Flow Data'!I25,0) -> 597 | E97: =IFERROR('Cash Flow Data'!J25,0) -> -1612 | F97: =IFERROR('Cash Flow Data'!K25,0) -> -300 | G97: =IFERROR('Cash Flow Data'!L25,0) -> 649 | H97: =IFERROR('Cash Flow Data'!M25,0) -> 3994 | I97: =IFERROR('Cash Flow Data'!N25,0) -> -101 | J97: =IFERROR('Cash Flow Data'!O25,0) -> -1213 | ... L97: =IFERROR('Cash Flow Data'!Q25,0) -> 5870
B98: Cash From Investing Activities | C98: =SUM(C87:C97) -> -282 | D98: =SUM(D87:D97) -> -1173 | E98: =SUM(E87:E97) -> -1063 | F98: =SUM(F87:F97) -> -438 | G98: =SUM(G87:G97) -> 1791 | H98: =SUM(H87:H97) -> -1228 | I98: =SUM(I87:I97) -> -1728 | J98: =SUM(J87:J97) -> -1484 | ... L98: =SUM(L87:L97) -> 6473
B100: Financing Activities
B101: Proceeds from shares | C101: =IFERROR('Cash Flow Data'!H27,0) -> 0 | D101: =IFERROR('Cash Flow Data'!I27,0) -> 0 | E101: =IFERROR('Cash Flow Data'!J27,0) -> 0 | F101: =IFERROR('Cash Flow Data'!K27,0) -> 0 | G101: =IFERROR('Cash Flow Data'!L27,0) -> 0 | H101: =IFERROR('Cash Flow Data'!M27,0) -> 0 | I101: =IFERROR('Cash Flow Data'!N27,0) -> 0 | J101: =IFERROR('Cash Flow Data'!O27,0) -> 0 | ... L101: =IFERROR('Cash Flow Data'!Q27,0) -> 0
B102: Proceeds from borrowings | C102: =IFERROR('Cash Flow Data'!H28,0) -> 177 | D102: =IFERROR('Cash Flow Data'!I28,0) -> 460 | E102: =IFERROR('Cash Flow Data'!J28,0) -> 0 | F102: =IFERROR('Cash Flow Data'!K28,0) -> 99 | G102: =IFERROR('Cash Flow Data'!L28,0) -> 0 | H102: =IFERROR('Cash Flow Data'!M28,0) -> 188 | I102: =IFERROR('Cash Flow Data'!N28,0) -> 55 | J102: =IFERROR('Cash Flow Data'!O28,0) -> 286 | ... L102: =IFERROR('Cash Flow Data'!Q28,0) -> 0
B103: Repayment of borrowings | C103: =IFERROR('Cash Flow Data'!H29,0) -> 0 | D103: =IFERROR('Cash Flow Data'!I29,0) -> -360 | E103: =IFERROR('Cash Flow Data'!J29,0) -> -277 | F103: =IFERROR('Cash Flow Data'!K29,0) -> 0 | G103: =IFERROR('Cash Flow Data'!L29,0) -> -99 | H103: =IFERROR('Cash Flow Data'!M29,0) -> -188 | I103: =IFERROR('Cash Flow Data'!N29,0) -> -55 | J103: =IFERROR('Cash Flow Data'!O29,0) -> -208 | ... L103: =IFERROR('Cash Flow Data'!Q29,0) -> 0
B104: Interest paid fin | C104: =IFERROR('Cash Flow Data'!H30,0) -> -2 | D104: =IFERROR('Cash Flow Data'!I30,0) -> -14 | E104: =IFERROR('Cash Flow Data'!J30,0) -> -6 | F104: =IFERROR('Cash Flow Data'!K30,0) -> -7 | G104: =IFERROR('Cash Flow Data'!L30,0) -> -90 | H104: =IFERROR('Cash Flow Data'!M30,0) -> -92 | I104: =IFERROR('Cash Flow Data'!N30,0) -> -82 | J104: =IFERROR('Cash Flow Data'!O30,0) -> -88 | ... L104: =IFERROR('Cash Flow Data'!Q30,0) -> -130
B105: Dividends paid | C105: =IFERROR('Cash Flow Data'!H31,0) -> -3354 | D105: =IFERROR('Cash Flow Data'!I31,0) -> -3572 | E105: =IFERROR('Cash Flow Data'!J31,0) -> -3911 | F105: =IFERROR('Cash Flow Data'!K31,0) -> -4554 | G105: =IFERROR('Cash Flow Data'!L31,0) -> -5196 | H105: =IFERROR('Cash Flow Data'!M31,0) -> -8811 | I105: =IFERROR('Cash Flow Data'!N31,0) -> -7526 | J105: =IFERROR('Cash Flow Data'!O31,0) -> -8474 | ... L105: =IFERROR('Cash Flow Data'!Q31,0) -> -12473
B106: Financial liabilities | C106: =IFERROR('Cash Flow Data'!H32,0) -> 0 | D106: =IFERROR('Cash Flow Data'!I32,0) -> 0 | E106: =IFERROR('Cash Flow Data'!J32,0) -> 0 | F106: =IFERROR('Cash Flow Data'!K32,0) -> 0 | G106: =IFERROR('Cash Flow Data'!L32,0) -> -373 | H106: =IFERROR('Cash Flow Data'!M32,0) -> -406 | I106: =IFERROR('Cash Flow Data'!N32,0) -> -407 | J106: =IFERROR('Cash Flow Data'!O32,0) -> -467 | ... L106: =IFERROR('Cash Flow Data'!Q32,0) -> -498
B107: Other financing items | C107: =IFERROR('Cash Flow Data'!H33,0) -> -685 | D107: =IFERROR('Cash Flow Data'!I33,0) -> -728 | E107: =IFERROR('Cash Flow Data'!J33,0) -> -781 | F107: =IFERROR('Cash Flow Data'!K33,0) -> -928 | G107: =IFERROR('Cash Flow Data'!L33,0) -> -1061 | H107: =IFERROR('Cash Flow Data'!M33,0) -> 0 | I107: =IFERROR('Cash Flow Data'!N33,0) -> 0 | J107: =IFERROR('Cash Flow Data'!O33,0) -> -2 | ... L107: =IFERROR('Cash Flow Data'!Q33,0) -> 0
B108: Cash From Financing Activities | C108: =SUM(C101:C107) -> -3864 | D108: =SUM(D101:D107) -> -4214 | E108: =SUM(E101:E107) -> -4975 | F108: =SUM(F101:F107) -> -5390 | G108: =SUM(G101:G107) -> -6819 | H108: =SUM(H101:H107) -> -9309 | I108: =SUM(I101:I107) -> -8015 | J108: =SUM(J101:J107) -> -8953 | ... L108: =SUM(L101:L107) -> -13101
B110: Net Cash Flow | C110: =C108+C98+C84 -> 25 | D110: =D108+D98+D84 -> -202 | E110: =E108+E98+E84 -> 21 | F110: =F108+F98+F84 -> -28 | G110: =G108+G98+G84 -> 2595 | H110: =H108+H98+H84 -> -1374 | I110: =I108+I98+I84 -> -695 | J110: =J108+J98+J84 -> -446 | ... L110: =L108+L98+L84 -> 5258
A112: # | B112: Cash Flow Statements (Consolidated)
B114: Cash from Operating Activity | C114: =IFERROR('Data Sheet'!B82,0) -> 4171 | D114: =IFERROR('Data Sheet'!C82,0) -> 5185 | E114: =IFERROR('Data Sheet'!D82,0) -> 6059 | F114: =IFERROR('Data Sheet'!E82,0) -> 5800 | G114: =IFERROR('Data Sheet'!F82,0) -> 7623 | H114: =IFERROR('Data Sheet'!G82,0) -> 9163 | I114: =IFERROR('Data Sheet'!H82,0) -> 9048 | J114: =IFERROR('Data Sheet'!I82,0) -> 9991 | ... L114: =IFERROR('Data Sheet'!K82,0) -> 11886
B116: Cash from Investing Activity | C116: =IFERROR('Data Sheet'!B83,0) -> -282 | D116: =IFERROR('Data Sheet'!C83,0) -> -1173 | E116: =IFERROR('Data Sheet'!D83,0) -> -1063 | F116: =IFERROR('Data Sheet'!E83,0) -> -438 | G116: =IFERROR('Data Sheet'!F83,0) -> 1791 | H116: =IFERROR('Data Sheet'!G83,0) -> -1228 | I116: =IFERROR('Data Sheet'!H83,0) -> -1728 | J116: =IFERROR('Data Sheet'!I83,0) -> -1484 | ... L116: =IFERROR('Data Sheet'!K83,0) -> 6473
B118: Cash from Financing Activity | C118: =IFERROR('Data Sheet'!B84,0) -> -3864 | D118: =IFERROR('Data Sheet'!C84,0) -> -4214 | E118: =IFERROR('Data Sheet'!D84,0) -> -4975 | F118: =IFERROR('Data Sheet'!E84,0) -> -5390 | G118: =IFERROR('Data Sheet'!F84,0) -> -6819 | H118: =IFERROR('Data Sheet'!G84,0) -> -9309 | I118: =IFERROR('Data Sheet'!H84,0) -> -8015 | J118: =IFERROR('Data Sheet'!I84,0) -> -8953 | ... L118: =IFERROR('Data Sheet'!K84,0) -> -13101
B120: Net Cash Flow | C120: =IFERROR('Data Sheet'!B85,0) -> 25 | D120: =IFERROR('Data Sheet'!C85,0) -> -202 | E120: =IFERROR('Data Sheet'!D85,0) -> 21 | F120: =IFERROR('Data Sheet'!E85,0) -> -28 | G120: =IFERROR('Data Sheet'!F85,0) -> 2595 | H120: =IFERROR('Data Sheet'!G85,0) -> -1374 | I120: =IFERROR('Data Sheet'!H85,0) -> -695 | J120: =IFERROR('Data Sheet'!I85,0) -> -446 | ... L120: =IFERROR('Data Sheet'!K85,0) -> 5258

Sheet Forecast
B3: {=HistoricalFS!B3:B4} -> HINDUSTAN UNILEVER LTD
B4: (HINDUNILVR | BSE Code: 500696)
B6: Forecasting
B8: ='Data Sheet'!B1& " - "&'Data Sheet'!A17 &" " & "Forecasting" -> HINDUSTAN UNILEVER LTD - Sales Forecasting | G8: ='Data Sheet'!B1& " - "& HistoricalFS!B24 &" " & "Forecasting" -> HINDUSTAN UNILEVER LTD - EBIDTA Forecasting | L8: ='Data Sheet'!B1& " - "& HistoricalFS!B44 &"Forecasting" -> HINDUSTAN UNILEVER LTD - Earnings Per Share Forecasting
B9: Year Weight | C9: Year | D9: Sales | E9: Sales as Growth | G9: Year Weight | H9: Year | I9: =HistoricalFS!B24 -> EBIDTA | J9: EBIDTA as Growth | L9: Year Weight | M9: Year | N9: =HistoricalFS!B44 -> Earnings Per Share | O9: EPS as Growth
B10: 1 | C10: ='Data Sheet'!$B$16 -> 42460 | D10: {=TRANSPOSE('Data Sheet'!B17:K17)} -> 32186 | G10: 1 | H10: ='Data Sheet'!$B$16 -> 42460 | I10: {=TRANSPOSE(HistoricalFS!C24:L24)} -> 5910 | L10: 1 | M10: ='Data Sheet'!$B$16 -> 42460 | N10: {=TRANSPOSE(HistoricalFS!C44:L44)} -> 16.937012
B11: =B10+1 -> 2 | C11: =C10+365 -> 42825 | D11: 33162 | E11: =(D11/D10)-1 -> 0.030323743 | G11: =G10+1 -> 2 | H11: =H10+365 -> 42825 | I11: 6328 | J11: =(I11/I10)-1 -> 0.07072758 | L11: =L10+1 -> 2 | M11: =M10+365 -> 42825 | N11: 17.945756 | O11: =(N11/N10)-1 -> 0.059558573
B12: =B11+1 -> 3 | C12: =C11+365 -> 43190 | D12: 35545 | E12: =(D12/D11)-1 -> 0.071859357 | G12: =G11+1 -> 3 | H12: =H11+365 -> 43190 | I12: 7499 | J12: =(I12/I11)-1 -> 0.18505057 | L12: =L11+1 -> 3 | M12: =M11+365 -> 43190 | N12: 22.517903 | O12: =(N12/N11)-1 -> 0.25477591
B13: =B12+1 -> 4 | C13: =C12+365 -> 43555 | D13: 39310 | E13: =(D13/D12)-1 -> 0.10592207 | G13: =G12+1 -> 4 | H13: =H12+365 -> 43555 | I13: 8880 | J13: =(I13/I12)-1 -> 0.18415789 | L13: =L12+1 -> 4 | M13: =M12+365 -> 43555 | N13: 26.507137 | O13: =(N13/N12)-1 -> 0.17715836
B14: =B13+1 -> 5 | C14: =C13+365 -> 43920 | D14: 39783 | E14: =(D14/D13)-1 -> 0.012032562 | G14: =G13+1 -> 5 | H14: =H13+365 -> 43920 | I14: 9861 | J14: =(I14/I13)-1 -> 0.11047297 | L14: =L13+1 -> 5 | M14: =M13+365 -> 43920 | N14: 29.249815 | O14: =(N14/N13)-1 -> 0.10346941
B15: =B14+1 -> 6 | C15: =C14+365 -> 44285 | D15: 47028 | E15: =(D15/D14)-1 -> 0.18211296 | G15: =G14+1 -> 6 | H15: =H14+365 -> 44285 | I15: 11626 | J15: =(I15/I14)-1 -> 0.17898793 | L15: =L14+1 -> 6 | M15: =M14+365 -> 44285 | N15: 33.320565 | O15: =(N15/N14)-1 -> 0.13917182
B16: =B15+1 -> 7 | C16: =C15+365 -> 44650 | D16: 52446 | E16: =(D16/D15)-1 -> 0.11520796 | G16: =G15+1 -> 7 | H16: =H15+365 -> 44650 | I16: 12857 | J16: =(I16/I15)-1 -> 0.10588336 | L16: =L15+1 -> 7 | M16: =M15+365 -> 44650 | N16: 36.912666 | O16: =(N16/N15)-1 -> 0.10780432
B17: =B16+1 -> 8 | C17: =C16+365 -> 45015 | D17: 60580 | E17: =(D17/D16)-1 -> 0.15509286 | G17: =G16+1 -> 8 | H17: =H16+365 -> 45015 | I17: 14147 | J17: =(I17/I16)-1 -> 0.10033445 | L17: =L16+1 -> 8 | M17: =M16+365 -> 45015 | N17: 41.262343 | O17: =(N17/N16)-1 -> 0.11783697
B18: =B17+1 -> 9 | C18: =C17+365 -> 45380 | D18: 61896 | E18: =(D18/D17)-1 -> 0.021723341 | G18: =G17+1 -> 9 | H18: =H17+365 -> 45380 | I18: 14659 | J18: =(I18/I17)-1 -> 0.036191419 | L18: =L17+1 -> 9 | M18: =M17+365 -> 45380 | N18: 40.283453 | O18: =(N18/N17)-1 -> -0.023723569
B19: =B18+1 -> 10 | C19: =C18+365 -> 45745 | D19: 63121 | E19: =(D19/D18)-1 -> 0.019791263 | G19: =G18+1 -> 10 | H19: =H18+365 -> 45745 | I19: 14843 | J19: =(I19/I18)-1 -> 0.012552016 | L19: =L18+1 -> 10 | M19: =M18+365 -> 45745 | N19: 39.789751 | O19: =(N19/N18)-1 -> -0.012255679
B20: =B19+1 -> 11 | C20: =C19+365 -> 46110 | D20: =FORECAST(B20,$D$10:$D$19,$B$10:$B$19) -> 68218.4 | E20: =(D20/D19)-1 -> 0.080756008 | G20: =G19+1 -> 11 | H20: =H19+365 -> 46110 | I20: =FORECAST(G20,$I$10:$I$19,$G$10:$G$19) -> 16849.333 | J20: =(I20/I19)-1 -> 0.13517034 | L20: =L19+1 -> 11 | M20: =M19+365 -> 46110 | N20: =FORECAST(L20,$N$10:$N$19,$L$10:$L$19) -> 46.840909 | O20: =(N20/N19)-1 -> 0.17721039
B21: =B20+1 -> 12 | C21: =C20+365 -> 46475 | D21: =FORECAST(B21,$D$10:$D$19,$B$10:$B$19) -> 72166.164 | E21: =(D21/D20)-1 -> 0.057869484 | G21: =G20+1 -> 12 | H21: =H20+365 -> 46475 | I21: =FORECAST(G21,$I$10:$I$19,$G$10:$G$19) -> 17974.485 | J21: =(I21/I20)-1 -> 0.066777213 | L21: =L20+1 -> 12 | M21: =M20+365 -> 46475 | N21: =FORECAST(L21,$N$10:$N$19,$L$10:$L$19) -> 49.816958 | O21: =(N21/N20)-1 -> 0.063535251
B22: =B21+1 -> 13 | C22: =C21+365 -> 46840 | D22: =FORECAST(B22,$D$10:$D$19,$B$10:$B$19) -> 76113.927 | E22: =(D22/D21)-1 -> 0.054703804 | G22: =G21+1 -> 13 | H22: =H21+365 -> 46840 | I22: =FORECAST(G22,$I$10:$I$19,$G$10:$G$19) -> 19099.636 | J22: =(I22/I21)-1 -> 0.062597149 | L22: =L21+1 -> 13 | M22: =M21+365 -> 46840 | N22: =FORECAST(L22,$N$10:$N$19,$L$10:$L$19) -> 52.793007 | O22: =(N22/N21)-1 -> 0.059739675
B23: =B22+1 -> 14 | C23: =C22+365 -> 47205 | D23: =FORECAST(B23,$D$10:$D$19,$B$10:$B$19) -> 80061.691 | E23: =(D23/D22)-1 -> 0.051866508 | G23: =G22+1 -> 14 | H23: =H22+365 -> 47205 | I23: =FORECAST(G23,$I$10:$I$19,$G$10:$G$19) -> 20224.788 | J23: =(I23/I22)-1 -> 0.058909578 | L23: =L22+1 -> 14 | M23: =M22+365 -> 47205 | N23: =FORECAST(L23,$N$10:$N$19,$L$10:$L$19) -> 55.769056 | O23: =(N23/N22)-1 -> 0.056372029
B24: =B23+1 -> 15 | C24: =C23+365 -> 47570 | D24: =FORECAST(B24,$D$10:$D$19,$B$10:$B$19) -> 84009.455 | E24: =(D24/D23)-1 -> 0.049309021 | G24: =G23+1 -> 15 | H24: =H23+365 -> 47570 | I24: =FORECAST(G24,$I$10:$I$19,$G$10:$G$19) -> 21349.939 | J24: =(I24/I23)-1 -> 0.055632302 | L24: =L23+1 -> 15 | M24: =M23+365 -> 47570 | N24: =FORECAST(L24,$N$10:$N$19,$L$10:$L$19) -> 58.745105 | O24: =(N24/N23)-1 -> 0.053363803

Sheet Common Size Income Statement
B3: ='Ratio Analysis'!B3 -> HINDUSTAN UNILEVER LTD
B4: ='Ratio Analysis'!B4 -> (HINDUNILVR | BSE Code: 500696)
B6: Common Size Statement
B8: ="Common Size Income Statement"&" "&"-"&'Data Sheet'!$B$1 -> Common Size Income Statement -HINDUSTAN UNILEVER LTD
B10: Particulars | C10: ='Data Sheet'!B16 -> 42460 | D10: ='Data Sheet'!C16 -> 42825 | E10: ='Data Sheet'!D16 -> 43190 | F10: ='Data Sheet'!E16 -> 43555 | G10: ='Data Sheet'!F16 -> 43921 | H10: ='Data Sheet'!G16 -> 44286 | I10: ='Data Sheet'!H16 -> 44651 | J10: ='Data Sheet'!I16 -> 45016 | ... L10: ='Data Sheet'!K16 -> 45747
B12: ='Data Sheet'!A17 -> Sales | C12: ='Data Sheet'!B17/'Data Sheet'!B$17 -> 1 | D12: ='Data Sheet'!C17/'Data Sheet'!C$17 -> 1 | E12: ='Data Sheet'!D17/'Data Sheet'!D$17 -> 1 | F12: ='Data Sheet'!E17/'Data Sheet'!E$17 -> 1 | G12: ='Data Sheet'!F17/'Data Sheet'!F$17 -> 1 | H12: ='Data Sheet'!G17/'Data Sheet'!G$17 -> 1 | I12: ='Data Sheet'!H17/'Data Sheet'!H$17 -> 1 | J12: ='Data Sheet'!I17/'Data Sheet'!I$17 -> 1 | ... L12: ='Data Sheet'!K17/'Data Sheet'!K$17 -> 1
B13: ='Data Sheet'!A18 -> Raw Material Cost | C13: ='Data Sheet'!B18/'Data Sheet'!B$17 -> 0.40961909 | D13: ='Data Sheet'!C18/'Data Sheet'!C$17 -> 0.41028888 | E13: ='Data Sheet'!D18/'Data Sheet'!D$17 -> 0.400422 | F13: ='Data Sheet'!E18/'Data Sheet'!E$17 -> 0.4030781 | G13: ='Data Sheet'!F18/'Data Sheet'!F$17 -> 0.39456552 | H13: ='Data Sheet'!G18/'Data Sheet'!G$17 -> 0.42827677 | I13: ='Data Sheet'!H18/'Data Sheet'!H$17 -> 0.43608664 | J13: ='Data Sheet'!I18/'Data Sheet'!I$17 -> 0.46924728 | ... L13: ='Data Sheet'!K18/'Data Sheet'!K$17 -> 0.43319973
B14: ='Data Sheet'!A19 -> Change in Inventory | C14: ='Data Sheet'!B19/'Data Sheet'!B$17 -> -0.002578761 | D14: ='Data Sheet'!C19/'Data Sheet'!C$17 -> -0.0043423195 | E14: ='Data Sheet'!D19/'Data Sheet'!D$17 -> 0.0020256014 | F14: ='Data Sheet'!E19/'Data Sheet'!E$17 -> -0.00030526584 | G14: ='Data Sheet'!F19/'Data Sheet'!F$17 -> 0.0027147274 | H14: ='Data Sheet'!G19/'Data Sheet'!G$17 -> 0.0086118908 | I14: ='Data Sheet'!H19/'Data Sheet'!H$17 -> 0.00041947908 | J14: ='Data Sheet'!I19/'Data Sheet'!I$17 -> 0.0012380324 | ... L14: ='Data Sheet'!K19/'Data Sheet'!K$17 -> 0.002423916
B15: ='Data Sheet'!A20 -> Power and Fuel | C15: ='Data Sheet'!B20/'Data Sheet'!B$17 -> 0.0096004474 | D15: ='Data Sheet'!C20/'Data Sheet'!C$17 -> 0.008895724 | E15: ='Data Sheet'!D20/'Data Sheet'!D$17 -> 0.0082993389 | F15: ='Data Sheet'!E20/'Data Sheet'!E$17 -> 0.0078351564 | G15: ='Data Sheet'!F20/'Data Sheet'!F$17 -> 0.0075157731 | H15: ='Data Sheet'!G20/'Data Sheet'!G$17 -> 0.0072084715 | I15: ='Data Sheet'!H20/'Data Sheet'!H$17 -> 0.0060633795 | J15: ='Data Sheet'!I20/'Data Sheet'!I$17 -> 0.0063387257 | ... L15: ='Data Sheet'!K20/'Data Sheet'!K$17 -> 0.0067647851
B16: ='Data Sheet'!A21 -> Other Mfr. Exp | C16: ='Data Sheet'!B21/'Data Sheet'!B$17 -> 0.092151867 | D16: ='Data Sheet'!C21/'Data Sheet'!C$17 -> 0.087057475 | E16: ='Data Sheet'!D21/'Data Sheet'!D$17 -> 0.08434379 | F16: ='Data Sheet'!E21/'Data Sheet'!E$17 -> 0.077359451 | G16: ='Data Sheet'!F21/'Data Sheet'!F$17 -> 0.073046276 | H16: ='Data Sheet'!G21/'Data Sheet'!G$17 -> 0.060984945 | I16: ='Data Sheet'!H21/'Data Sheet'!H$17 -> 0.063951493 | J16: ='Data Sheet'!I21/'Data Sheet'!I$17 -> 0.062578409 | ... L16: ='Data Sheet'!K21/'Data Sheet'!K$17 -> 0.060740483
B17: ='Data Sheet'!A22 -> Employee Cost | C17: ='Data Sheet'!B22/'Data Sheet'!B$17 -> 0.052196607 | D17: ='Data Sheet'!C22/'Data Sheet'!C$17 -> 0.052560159 | E17: ='Data Sheet'!D22/'Data Sheet'!D$17 -> 0.052328035 | F17: ='Data Sheet'!E22/'Data Sheet'!E$17 -> 0.047697787 | G17: ='Data Sheet'!F22/'Data Sheet'!F$17 -> 0.045748184 | H17: ='Data Sheet'!G22/'Data Sheet'!G$17 -> 0.050140342 | I17: ='Data Sheet'!H22/'Data Sheet'!H$17 -> 0.048526103 | J17: ='Data Sheet'!I22/'Data Sheet'!I$17 -> 0.047111258 | ... L17: ='Data Sheet'!K22/'Data Sheet'!K$17 -> 0.048747643
B18: ='Data Sheet'!A23 -> Selling and admin | C18: ='Data Sheet'!B23/'Data Sheet'!B$17 -> 0.20943889 | D18: ='Data Sheet'!C23/'Data Sheet'!C$17 -> 0.20170677 | E18: ='Data Sheet'!D23/'Data Sheet'!D$17 -> 0.20402307 | F18: ='Data Sheet'!E23/'Data Sheet'!E$17 -> 0.19832104 | G18: ='Data Sheet'!F23/'Data Sheet'!F$17 -> 0.1915391 | H18: ='Data Sheet'!G23/'Data Sheet'!G$17 -> 0.16811261 | I18: ='Data Sheet'!H23/'Data Sheet'!H$17 -> 0.15566487 | J18: ='Data Sheet'!I23/'Data Sheet'!I$17 -> 0.14501486 | ... L18: ='Data Sheet'!K23/'Data Sheet'!K$17 -> 0.16940479
B19: ='Data Sheet'!A24 -> Other Expenses | C19: ='Data Sheet'!B24/'Data Sheet'!B$17 -> 0.040794134 | D19: ='Data Sheet'!C24/'Data Sheet'!C$17 -> 0.044327845 | E19: ='Data Sheet'!D24/'Data Sheet'!D$17 -> 0.041637361 | F19: ='Data Sheet'!E24/'Data Sheet'!E$17 -> 0.039506487 | G19: ='Data Sheet'!F24/'Data Sheet'!F$17 -> 0.042430184 | H19: ='Data Sheet'!G24/'Data Sheet'!G$17 -> 0.046674322 | I19: ='Data Sheet'!H24/'Data Sheet'!H$17 -> 0.044979598 | J19: ='Data Sheet'!I24/'Data Sheet'!I$17 -> 0.037421591 | ... L19: ='Data Sheet'!K24/'Data Sheet'!K$17 -> 0.048414949
B20: ='Data Sheet'!A25 -> Other Income | C20: ='Data Sheet'!B25/'Data Sheet'!B$17 -> 0.015099733 | D20: ='Data Sheet'!C25/'Data Sheet'!C$17 -> 0.018273928 | E20: ='Data Sheet'!D25/'Data Sheet'!D$17 -> 0.0099310733 | F20: ='Data Sheet'!E25/'Data Sheet'!E$17 -> 0.0081912999 | G20: ='Data Sheet'!F25/'Data Sheet'!F$17 -> 0.010657819 | H20: ='Data Sheet'!G25/'Data Sheet'!G$17 -> 0.0036148677 | I20: ='Data Sheet'!H25/'Data Sheet'!H$17 -> 0.0041757236 | J20: ='Data Sheet'!I25/'Data Sheet'!I$17 -> 0.0073951799 | ... L20: ='Data Sheet'!K25/'Data Sheet'!K$17 -> 0.020943901
B21: ='Data Sheet'!A26 -> Depreciation | C21: ='Data Sheet'!B26/'Data Sheet'!B$17 -> 0.010967501 | D21: ='Data Sheet'!C26/'Data Sheet'!C$17 -> 0.013026959 | E21: ='Data Sheet'!D26/'Data Sheet'!D$17 -> 0.014629343 | F21: ='Data Sheet'!E26/'Data Sheet'!E$17 -> 0.014372933 | G21: ='Data Sheet'!F26/'Data Sheet'!F$17 -> 0.025186638 | H21: ='Data Sheet'!G26/'Data Sheet'!G$17 -> 0.022837459 | I21: ='Data Sheet'!H26/'Data Sheet'!H$17 -> 0.020802349 | J21: ='Data Sheet'!I26/'Data Sheet'!I$17 -> 0.01876857 | ... L21: ='Data Sheet'!K26/'Data Sheet'!K$17 -> 0.021466707
B22: ='Data Sheet'!A27 -> Interest | C22: ='Data Sheet'!B27/'Data Sheet'!B$17 -> 0.00052817995 | D22: ='Data Sheet'!C27/'Data Sheet'!C$17 -> 0.0010554249 | E22: ='Data Sheet'!D27/'Data Sheet'!D$17 -> 0.00073146715 | F22: ='Data Sheet'!E27/'Data Sheet'!E$17 -> 0.00083948105 | G22: ='Data Sheet'!F27/'Data Sheet'!F$17 -> 0.002966091 | H22: ='Data Sheet'!G27/'Data Sheet'!G$17 -> 0.0024878796 | I22: ='Data Sheet'!H27/'Data Sheet'!H$17 -> 0.0020211265 | J22: ='Data Sheet'!I27/'Data Sheet'!I$17 -> 0.0018818092 | ... L22: ='Data Sheet'!K27/'Data Sheet'!K$17 -> 0.0062578223
B23: ='Data Sheet'!A28 -> Profit before tax | C23: ='Data Sheet'!B28/'Data Sheet'!B$17 -> 0.18722426 | D23: ='Data Sheet'!C28/'Data Sheet'!C$17 -> 0.19501236 | E23: ='Data Sheet'!D28/'Data Sheet'!D$17 -> 0.20554227 | F23: ='Data Sheet'!E28/'Data Sheet'!E$17 -> 0.2188756 | G23: ='Data Sheet'!F28/'Data Sheet'!F$17 -> 0.23037478 | H23: ='Data Sheet'!G28/'Data Sheet'!G$17 -> 0.22550396 | I23: ='Data Sheet'!H28/'Data Sheet'!H$17 -> 0.22649964 | J23: ='Data Sheet'!I28/'Data Sheet'!I$17 -> 0.22027072 | ... L23: ='Data Sheet'!K28/'Data Sheet'!K$17 -> 0.22837091
... B26: ='Data Sheet'!A31 -> Dividend Amount | C26: ='Data Sheet'!B31/'Data Sheet'!B$17 -> 0.10737588 | D26: ='Data Sheet'!C31/'Data Sheet'!C$17 -> 0.11072915 | E26: ='Data Sheet'!D31/'Data Sheet'!D$17 -> 0.12153608 | F26: ='Data Sheet'!E31/'Data Sheet'!E$17 -> 0.12088527 | G26: ='Data Sheet'!F31/'Data Sheet'!F$17 -> 0.13573637 | H26: ='Data Sheet'!G31/'Data Sheet'!G$17 -> 0.20237943 | I26: ='Data Sheet'!H31/'Data Sheet'!H$17 -> 0.15234718 | J26: ='Data Sheet'!I31/'Data Sheet'!I$17 -> 0.15128755 | ... L26: ='Data Sheet'!K31/'Data Sheet'!K$17 -> 0.19731943
B27: ='Data Sheet'!A33 -> EBIDTA | C27: ='Data Sheet'!B33/'Data Sheet'!B$17 -> 0.19871994 | D27: ='Data Sheet'!C33/'Data Sheet'!C$17 -> 0.20867258 | E27: ='Data Sheet'!D33/'Data Sheet'!D$17 -> 0.22053735 | F27: ='Data Sheet'!E33/'Data Sheet'!E$17 -> 0.23393539 | G27: ='Data Sheet'!F33/'Data Sheet'!F$17 -> 0.25832642 | H27: ='Data Sheet'!G33/'Data Sheet'!G$17 -> 0.25074424 | I27: ='Data Sheet'!H33/'Data Sheet'!H$17 -> 0.24907524 | J27: ='Data Sheet'!I33/'Data Sheet'!I$17 -> 0.24054143 | ... L27: ='Data Sheet'!K33/'Data Sheet'!K$17 -> 0.2557469
B29: ="Common Size Balance Sheet"&" "&"-"&'Data Sheet'!$B$1 -> Common Size Balance Sheet -HINDUSTAN UNILEVER LTD
B31: Particulars | C31: ='Data Sheet'!B56 -> 42460 | D31: ='Data Sheet'!C56 -> 42825 | E31: ='Data Sheet'!D56 -> 43190 | F31: ='Data Sheet'!E56 -> 43555 | G31: ='Data Sheet'!F56 -> 43921 | H31: ='Data Sheet'!G56 -> 44286 | I31: ='Data Sheet'!H56 -> 44651 | J31: ='Data Sheet'!I56 -> 45016 | ... L31: ='Data Sheet'!K56 -> 45747
B33: Total Liabilities | C33: ='Data Sheet'!B61/'Data Sheet'!B$61 -> 1 | D33: ='Data Sheet'!C61/'Data Sheet'!C$61 -> 1 | E33: ='Data Sheet'!D61/'Data Sheet'!D$61 -> 1 | F33: ='Data Sheet'!E61/'Data Sheet'!E$61 -> 1 | G33: ='Data Sheet'!F61/'Data Sheet'!F$61 -> 1 | H33: ='Data Sheet'!G61/'Data Sheet'!G$61 -> 1 | I33: ='Data Sheet'!H61/'Data Sheet'!H$61 -> 1 | J33: ='Data Sheet'!I61/'Data Sheet'!I$61 -> 1 | ... L33: ='Data Sheet'!K61/'Data Sheet'!K$61 -> 1
B34: ='Data Sheet'!A57 -> Equity Share Capital | C34: ='Data Sheet'!B57/'Data Sheet'!B$61 -> 0.014601501 | D34: ='Data Sheet'!C57/'Data Sheet'!C$61 -> 0.013752706 | E34: ='Data Sheet'!D57/'Data Sheet'!D$61 -> 0.012092711 | F34: ='Data Sheet'!E57/'Data Sheet'!E$61 -> 0.011594825 | G34: ='Data Sheet'!F57/'Data Sheet'!F$61 -> 0.010718007 | H34: ='Data Sheet'!G57/'Data Sheet'!G$61 -> 0.0034186791 | I34: ='Data Sheet'!H57/'Data Sheet'!H$61 -> 0.0033330497 | J34: ='Data Sheet'!I57/'Data Sheet'!I$61 -> 0.0032157861 | ... L34: ='Data Sheet'!K57/'Data Sheet'!K$61 -> 0.0029425391
B35: ='Data Sheet'!A58 -> Reserves | C35: ='Data Sheet'!B58/'Data Sheet'!B$61 -> 0.42973028 | D35: ='Data Sheet'!C58/'Data Sheet'!C$61 -> 0.41563734 | E35: ='Data Sheet'!D58/'Data Sheet'!D$61 -> 0.39553242 | F35: ='Data Sheet'!E58/'Data Sheet'!E$61 -> 0.41070374 | G35: ='Data Sheet'!F58/'Data Sheet'!F$61 -> 0.3976083 | H35: ='Data Sheet'!G58/'Data Sheet'!G$61 -> 0.6901222 | I35: ='Data Sheet'!H58/'Data Sheet'!H$61 -> 0.69250844 | J35: ='Data Sheet'!I58/'Data Sheet'!I$61 -> 0.68515402 | ... L35: ='Data Sheet'!K58/'Data Sheet'!K$61 -> 0.61564179
B36: ='Data Sheet'!A59 -> Borrowings | C36: ='Data Sheet'!B59/'Data Sheet'!B$61 -> 0.011965119 | D36: ='Data Sheet'!C59/'Data Sheet'!C$61 -> 0.017636572 | E36: ='Data Sheet'!D59/'Data Sheet'!D$61 -> 0 | F36: ='Data Sheet'!E59/'Data Sheet'!E$61 -> 0.0053142949 | G36: ='Data Sheet'!F59/'Data Sheet'!F$61 -> 0 | H36: ='Data Sheet'!G59/'Data Sheet'!G$61 -> 0 | I36: ='Data Sheet'!H59/'Data Sheet'!H$61 -> 0.014793067 | J36: ='Data Sheet'!I59/'Data Sheet'!I$61 -> 0.016681035 | ... L36: ='Data Sheet'!K59/'Data Sheet'!K$61 -> 0.020635338
B37: ='Data Sheet'!A60 -> Other Liabilities | C37: ='Data Sheet'!B60/'Data Sheet'!B$61 -> 0.5437031 | D37: ='Data Sheet'!C60/'Data Sheet'!C$61 -> 0.55297339 | E37: ='Data Sheet'!D60/'Data Sheet'!D$61 -> 0.59237487 | F37: ='Data Sheet'!E60/'Data Sheet'!E$61 -> 0.57238714 | G37: ='Data Sheet'!F60/'Data Sheet'!F$61 -> 0.5916737 | H37: ='Data Sheet'!G60/'Data Sheet'!G$61 -> 0.30645912 | I37: ='Data Sheet'!H60/'Data Sheet'!H$61 -> 0.28936544 | J37: ='Data Sheet'!I60/'Data Sheet'!I$61 -> 0.29494916 | ... L37: ='Data Sheet'!K60/'Data Sheet'!K$61 -> 0.36078034
B39: Total Assets | C39: ='Data Sheet'!B75/'Data Sheet'!B$75 -> 1 | D39: ='Data Sheet'!C75/'Data Sheet'!C$75 -> 1 | E39: ='Data Sheet'!D75/'Data Sheet'!D$75 -> 1 | F39: ='Data Sheet'!E75/'Data Sheet'!E$75 -> 1 | G39: ='Data Sheet'!F75/'Data Sheet'!F$75 -> 1 | H39: ='Data Sheet'!G75/'Data Sheet'!G$75 -> 1 | I39: ='Data Sheet'!H75/'Data Sheet'!H$75 -> 1 | J39: ='Data Sheet'!I75/'Data Sheet'!I$75 -> 1 | ... L39: ='Data Sheet'!K75/'Data Sheet'!K$75 -> 1
B40: ='Data Sheet'!A62 -> Net Block | C40: ='Data Sheet'!B62/'Data Sheet'!B$75 -> 0.2202393 | D40: ='Data Sheet'!C62/'Data Sheet'!C$75 -> 0.28135744 | E40: ='Data Sheet'!D62/'Data Sheet'!D$75 -> 0.25349905 | F40: ='Data Sheet'!E62/'Data Sheet'!E$75 -> 0.25310001 | G40: ='Data Sheet'!F62/'Data Sheet'!F$75 -> 0.27187019 | H40: ='Data Sheet'!G62/'Data Sheet'!G$75 -> 0.74837067 | I40: ='Data Sheet'!H62/'Data Sheet'!H$75 -> 0.73005134 | J40: ='Data Sheet'!I62/'Data Sheet'!I$75 -> 0.72085608 | ... L40: ='Data Sheet'!K62/'Data Sheet'!K$75 -> 0.6803526
B41: ='Data Sheet'!A63 -> Capital Work in Progress | C41: ='Data Sheet'!B63/'Data Sheet'!B$75 -> 0.027580612 | D41: ='Data Sheet'!C63/'Data Sheet'!C$75 -> 0.014580415 | E41: ='Data Sheet'!D63/'Data Sheet'!D$75 -> 0.02580898 | F41: ='Data Sheet'!E63/'Data Sheet'!E$75 -> 0.021793977 | G41: ='Data Sheet'!F63/'Data Sheet'!F$75 -> 0.029623381 | H41: ='Data Sheet'!G63/'Data Sheet'!G$75 -> 0.01083794 | I41: ='Data Sheet'!H63/'Data Sheet'!H$75 -> 0.018622529 | J41: ='Data Sheet'!I63/'Data Sheet'!I$75 -> 0.01549051 | ... L41: ='Data Sheet'!K63/'Data Sheet'!K$75 -> 0.012634136
B42: ='Data Sheet'!A64 -> Investments | C42: ='Data Sheet'!B64/'Data Sheet'!B$75 -> 0.17521801 | D42: ='Data Sheet'!C64/'Data Sheet'!C$75 -> 0.24156373 | E42: ='Data Sheet'!D64/'Data Sheet'!D$75 -> 0.16084425 | F42: ='Data Sheet'!E64/'Data Sheet'!E$75 -> 0.14579419 | G42: ='Data Sheet'!F64/'Data Sheet'!F$75 -> 0.062273607 | H42: ='Data Sheet'!G64/'Data Sheet'!G$75 -> 0.039409369 | I42: ='Data Sheet'!H64/'Data Sheet'!H$75 -> 0.049939012 | J42: ='Data Sheet'!I64/'Data Sheet'!I$75 -> 0.039437853 | ... L42: ='Data Sheet'!K64/'Data Sheet'!K$75 -> 0.047706698
B43: ='Data Sheet'!A65 -> Other Assets | C43: ='Data Sheet'!B74/'Data Sheet'!B$75 -> 0.10383289 | D43: ='Data Sheet'!C74/'Data Sheet'!C$75 -> 0.11524258 | E43: ='Data Sheet'!D74/'Data Sheet'!D$75 -> 0.15071101 | F43: ='Data Sheet'!E74/'Data Sheet'!E$75 -> 0.14198293 | G43: ='Data Sheet'!F74/'Data Sheet'!F$75 -> 0.18821019 | H43: ='Data Sheet'!G74/'Data Sheet'!G$75 -> 0.058699447 | I43: ='Data Sheet'!H74/'Data Sheet'!H$75 -> 0.057030607 | J43: ='Data Sheet'!I74/'Data Sheet'!I$75 -> 0.059895726 | ... L43: ='Data Sheet'!K74/'Data Sheet'!K$75 -> 0.061618021
B44: ='Data Sheet'!A67 -> Receivables | C44: ='Data Sheet'!B67/'Data Sheet'!B$75 -> 0.085445819 | D44: ='Data Sheet'!C67/'Data Sheet'!C$75 -> 0.06908188 | E44: ='Data Sheet'!D67/'Data Sheet'!D$75 -> 0.073340052 | F44: ='Data Sheet'!E67/'Data Sheet'!E$75 -> 0.09748242 | G44: ='Data Sheet'!F67/'Data Sheet'!F$75 -> 0.057013844 | H44: ='Data Sheet'!G67/'Data Sheet'!G$75 -> 0.025574629 | I44: ='Data Sheet'!H67/'Data Sheet'!H$75 -> 0.031713613 | J44: ='Data Sheet'!I67/'Data Sheet'!I$75 -> 0.04213364 | ... L44: ='Data Sheet'!K67/'Data Sheet'!K$75 -> 0.047819391
B45: ='Data Sheet'!A68 -> Inventory | C45: ='Data Sheet'!B68/'Data Sheet'!B$75 -> 0.18427635 | D45: ='Data Sheet'!C68/'Data Sheet'!C$75 -> 0.1617853 | E45: ='Data Sheet'!D68/'Data Sheet'!D$75 -> 0.14068973 | F45: ='Data Sheet'!E68/'Data Sheet'!E$75 -> 0.13817167 | G45: ='Data Sheet'!F68/'Data Sheet'!F$75 -> 0.13729966 | H45: ='Data Sheet'!G68/'Data Sheet'!G$75 -> 0.052065755 | I45: ='Data Sheet'!H68/'Data Sheet'!H$75 -> 0.058094347 | J45: ='Data Sheet'!I68/'Data Sheet'!I$75 -> 0.058171518 | ... L45: ='Data Sheet'!K68/'Data Sheet'!K$75 -> 0.055282171
B46: ='Data Sheet'!A69 -> Cash & Bank | C46: ='Data Sheet'!B69/'Data Sheet'!B$75 -> 0.20340702 | D46: ='Data Sheet'!C69/'Data Sheet'!C$75 -> 0.11638864 | E46: ='Data Sheet'!D69/'Data Sheet'!D$75 -> 0.19510693 | F46: ='Data Sheet'!E69/'Data Sheet'!E$75 -> 0.20167481 | G46: ='Data Sheet'!F69/'Data Sheet'!F$75 -> 0.25370913 | H46: ='Data Sheet'!G69/'Data Sheet'!G$75 -> 0.065042188 | I46: ='Data Sheet'!H69/'Data Sheet'!H$75 -> 0.054548549 | J46: ='Data Sheet'!I69/'Data Sheet'!I$75 -> 0.064014669 | ... L46: ='Data Sheet'!K69/'Data Sheet'!K$75 -> 0.09458698

Sheet Ratio Analysis
B3: ='Dupont Analysis'!B3 -> HINDUSTAN UNILEVER LTD
B4: ='Dupont Analysis'!B4 -> (HINDUNILVR | BSE Code: 500696)
B6: Ratio Analysis
B8: ="Ratio Analysis -"&'Data Sheet'!B1 -> Ratio Analysis -HINDUSTAN UNILEVER LTD
B9: Years | C9: ='Data Sheet'!B16 -> 42460 | D9: ='Data Sheet'!C16 -> 42825 | E9: ='Data Sheet'!D16 -> 43190 | F9: ='Data Sheet'!E16 -> 43555 | G9: ='Data Sheet'!F16 -> 43921 | H9: ='Data Sheet'!G16 -> 44286 | I9: ='Data Sheet'!H16 -> 44651 | J9: ='Data Sheet'!I16 -> 45016 | ... L9: ='Data Sheet'!K16 -> 45747 | M9: Trend | N9: Mean | O9: Median
B11: Sales Growth | C11: =IFERROR(HistoricalFS!C13,0) -> - | D11: =IFERROR(HistoricalFS!D13,0) -> 0.030323743 | E11: =IFERROR(HistoricalFS!E13,0) -> 0.071859357 | F11: =IFERROR(HistoricalFS!F13,0) -> 0.10592207 | G11: =IFERROR(HistoricalFS!G13,0) -> 0.012032562 | H11: =IFERROR(HistoricalFS!H13,0) -> 0.18211296 | I11: =IFERROR(HistoricalFS!I13,0) -> 0.11520796 | J11: =IFERROR(HistoricalFS!J13,0) -> 0.15509286 | ... L11: =IFERROR(HistoricalFS!L13,0) -> 0.019791263 | N11: =IFERROR(AVERAGE(D11:L11),0) -> 0.07934068 | O11: =IFERROR(MEDIAN(C11:L11),0) -> 0.071859357
B12: EBIDTA Growth | D12: =IFERROR(HistoricalFS!D24/HistoricalFS!C24-1,0) -> 0.07072758 | E12: =IFERROR(HistoricalFS!E24/HistoricalFS!D24-1,0) -> 0.18505057 | F12: =IFERROR(HistoricalFS!F24/HistoricalFS!E24-1,0) -> 0.18415789 | G12: =IFERROR(HistoricalFS!G24/HistoricalFS!F24-1,0) -> 0.11047297 | H12: =IFERROR(HistoricalFS!H24/HistoricalFS!G24-1,0) -> 0.17898793 | I12: =IFERROR(HistoricalFS!I24/HistoricalFS!H24-1,0) -> 0.10588336 | J12: =IFERROR(HistoricalFS!J24/HistoricalFS!I24-1,0) -> 0.10033445 | K12: =IFERROR(HistoricalFS!K24/HistoricalFS!J24-1,0) -> 0.036191419 | L12: =IFERROR(HistoricalFS!L24/HistoricalFS!K24-1,0) -> 0.012552016 | N12: =IFERROR(AVERAGE(D12:L12),0) -> 0.10937313 | O12: =IFERROR(MEDIAN(C12:L12),0) -> 0.10588336
B13: EBIT Growth | D13: =IFERROR(SUM(HistoricalFS!D33,HistoricalFS!D27)/SUM(HistoricalFS!C33,HistoricalFS!C27)-1,0) -> 0.061004139 | E13: =IFERROR(SUM(HistoricalFS!E33,HistoricalFS!E27)/SUM(HistoricalFS!D33,HistoricalFS!D27)-1,0) -> 0.18368385 | F13: =IFERROR(SUM(HistoricalFS!F33,HistoricalFS!F27)/SUM(HistoricalFS!E33,HistoricalFS!E27)-1,0) -> 0.19143144 | G13: =IFERROR(SUM(HistoricalFS!G33,HistoricalFS!G27)/SUM(HistoricalFS!F33,HistoricalFS!F27)-1,0) -> 0.065423933 | H13: =IFERROR(SUM(HistoricalFS!H33,HistoricalFS!H27)/SUM(HistoricalFS!G33,HistoricalFS!G27)-1,0) -> 0.19110509 | I13: =IFERROR(SUM(HistoricalFS!I33,HistoricalFS!I27)/SUM(HistoricalFS!H33,HistoricalFS!H27)-1,0) -> 0.11504928 | J13: =IFERROR(SUM(HistoricalFS!J33,HistoricalFS!J27)/SUM(HistoricalFS!I33,HistoricalFS!I27)-1,0) -> 0.10572837 | K13: =IFERROR(SUM(HistoricalFS!K33,HistoricalFS!K27)/SUM(HistoricalFS!J33,HistoricalFS!J27)-1,0) -> 0.033282091 | L13: =IFERROR(SUM(HistoricalFS!L33,HistoricalFS!L27)/SUM(HistoricalFS!K33,HistoricalFS!K27)-1,0) -> 0.0033474671 | N13: =IFERROR(AVERAGE(D13:L13),0) -> 0.10556174 | O13: =IFERROR(MEDIAN(C13:L13),0) -> 0.10572837
B14: Net Profit Growth | D14: =IFERROR(HistoricalFS!D39/HistoricalFS!C39-1,0) -> 0.059754434 | E14: =IFERROR(HistoricalFS!E39/HistoricalFS!D39-1,0) -> 0.25489186 | F14: =IFERROR(HistoricalFS!F39/HistoricalFS!E39-1,0) -> 0.17726713 | G14: =IFERROR(HistoricalFS!G39/HistoricalFS!F39-1,0) -> 0.10352039 | H14: =IFERROR(HistoricalFS!H39/HistoricalFS!G39-1,0) -> 0.23641819 | I14: =IFERROR(HistoricalFS!I39/HistoricalFS!H39-1,0) -> 0.10780432 | J14: =IFERROR(HistoricalFS!J39/HistoricalFS!I39-1,0) -> 0.11783697 | K14: =IFERROR(HistoricalFS!K39/HistoricalFS!J39-1,0) -> -0.023723569 | L14: =IFERROR(HistoricalFS!L39/HistoricalFS!K39-1,0) -> -0.012255679 | N14: =IFERROR(AVERAGE(D14:L14),0) -> 0.11350156 | O14: =IFERROR(MEDIAN(C14:L14),0) -> 0.10780432
B15: Dividend Growth | D15: =IFERROR(HistoricalFS!D47/HistoricalFS!C47-1,0) -> 0.062303632 | E15: =IFERROR(HistoricalFS!E47/HistoricalFS!D47-1,0) -> 0.17636188 | F15: =IFERROR(HistoricalFS!F47/HistoricalFS!E47-1,0) -> 0.099898369 | G15: =IFERROR(HistoricalFS!G47/HistoricalFS!F47-1,0) -> 0.13631114 | H15: =IFERROR(HistoricalFS!H47/HistoricalFS!G47-1,0) -> 0.6238764 | I15: =IFERROR(HistoricalFS!I47/HistoricalFS!H47-1,0) -> -0.16049383 | J15: =IFERROR(HistoricalFS!J47/HistoricalFS!I47-1,0) -> 0.14705882 | K15: =IFERROR(HistoricalFS!K47/HistoricalFS!J47-1,0) -> 0.076923077 | L15: =IFERROR(HistoricalFS!L47/HistoricalFS!K47-1,0) -> 0.26190476 | N15: =IFERROR(AVERAGE(D15:L15),0) -> 0.15823825 | O15: =IFERROR(MEDIAN(C15:L15),0) -> 0.13631114
B17: Gross Margin | C17: =IFERROR(HistoricalFS!C19,0) -> 0.43385323 | D17: =IFERROR(HistoricalFS!D19,0) -> 0.43685544 | E17: =IFERROR(HistoricalFS!E19,0) -> 0.45663244 | F17: =IFERROR(HistoricalFS!F19,0) -> 0.46372424 | G17: =IFERROR(HistoricalFS!G19,0) -> 0.48183898 | H17: =IFERROR(HistoricalFS!H19,0) -> 0.46200136 | I17: =IFERROR(HistoricalFS!I19,0) -> 0.44579186 | J17: =IFERROR(HistoricalFS!J19,0) -> 0.41596236 | ... L17: =IFERROR(HistoricalFS!L19,0) -> 0.45297128 | N17: =IFERROR(AVERAGE(C17:L17),0) -> 0.45059612 | O17: =IFERROR(MEDIAN(C17:L17),0) -> 0.45465063
B18: EBIDTA Margin | C18: =IFERROR(HistoricalFS!C25,0) -> 0.18362021 | D18: =IFERROR(HistoricalFS!D25,0) -> 0.19082082 | E18: =IFERROR(HistoricalFS!E25,0) -> 0.21097201 | F18: =IFERROR(HistoricalFS!F25,0) -> 0.22589672 | G18: =IFERROR(HistoricalFS!G25,0) -> 0.24786969 | H18: =IFERROR(HistoricalFS!H25,0) -> 0.24721443 | I18: =IFERROR(HistoricalFS!I25,0) -> 0.24514739 | J18: =IFERROR(HistoricalFS!J25,0) -> 0.23352592 | ... L18: =IFERROR(HistoricalFS!L25,0) -> 0.23515153 | N18: =IFERROR(AVERAGE(C18:L18),0) -> 0.22570515 | O18: =IFERROR(MEDIAN(C18:L18),0) -> 0.23433873
B19: EBIT Margin | C19: =IFERROR((HistoricalFS!C33+HistoricalFS!C27)/(HistoricalFS!C12),0) -> 0.17265271 | D19: =IFERROR((HistoricalFS!D33+HistoricalFS!D27)/(HistoricalFS!D12),0) -> 0.17779386 | E19: =IFERROR((HistoricalFS!E33+HistoricalFS!E27)/(HistoricalFS!E12),0) -> 0.19634266 | F19: =IFERROR((HistoricalFS!F33+HistoricalFS!F27)/(HistoricalFS!F12),0) -> 0.21152379 | G19: =IFERROR((HistoricalFS!G33+HistoricalFS!G27)/(HistoricalFS!G12),0) -> 0.22268306 | H19: =IFERROR((HistoricalFS!H33+HistoricalFS!H27)/(HistoricalFS!H12),0) -> 0.22437697 | I19: =IFERROR((HistoricalFS!I33+HistoricalFS!I27)/(HistoricalFS!I12),0) -> 0.22434504 | J19: =IFERROR((HistoricalFS!J33+HistoricalFS!J27)/(HistoricalFS!J12),0) -> 0.21475735 | ... L19: =IFERROR((HistoricalFS!L33+HistoricalFS!L27)/(HistoricalFS!L12),0) -> 0.21368483 | N19: =IFERROR(AVERAGE(C19:L19),0) -> 0.20753471 | O19: =IFERROR(MEDIAN(C19:L19),0) -> 0.21422109
B20: EBT Margin | C20: =IFERROR(HistoricalFS!C34,0) -> 0.17212453 | D20: =IFERROR(HistoricalFS!D34,0) -> 0.17673844 | E20: =IFERROR(HistoricalFS!E34,0) -> 0.1956112 | F20: =IFERROR(HistoricalFS!F34,0) -> 0.2106843 | G20: =IFERROR(HistoricalFS!G34,0) -> 0.21971696 | H20: =IFERROR(HistoricalFS!H34,0) -> 0.22188909 | I20: =IFERROR(HistoricalFS!I34,0) -> 0.22232391 | J20: =IFERROR(HistoricalFS!J34,0) -> 0.21287554 | ... L20: =IFERROR(HistoricalFS!L34,0) -> 0.20742701 | N20: =IFERROR(AVERAGE(C20:L20),0) -> 0.20511817 | O20: =IFERROR(MEDIAN(C20:L20),0) -> 0.21123753
B21: Net Profit Margin | C21: =IFERROR(HistoricalFS!C40,0) -> 0.11386938 | D21: =IFERROR(HistoricalFS!D40,0) -> 0.11712201 | E21: =IFERROR(HistoricalFS!E40,0) -> 0.13712196 | F21: =IFERROR(HistoricalFS!F40,0) -> 0.14596795 | G21: =IFERROR(HistoricalFS!G40,0) -> 0.15916346 | H21: =IFERROR(HistoricalFS!H40,0) -> 0.16647529 | I21: =IFERROR(HistoricalFS!I40,0) -> 0.16537009 | J21: =IFERROR(HistoricalFS!J40,0) -> 0.16003632 | ... L21: =IFERROR(HistoricalFS!L40,0) -> 0.14811236 | N21: =IFERROR(AVERAGE(C21:L21),0) -> 0.14661566 | O21: =IFERROR(MEDIAN(C21:L21),0) -> 0.15051508
B23: SalesExpenses%Sales | C23: =IFERROR(HistoricalFS!C22,0) -> 0.25023302 | D23: =IFERROR(HistoricalFS!D22,0) -> 0.24603462 | E23: =IFERROR(HistoricalFS!E22,0) -> 0.24566043 | F23: =IFERROR(HistoricalFS!F22,0) -> 0.23782752 | G23: =IFERROR(HistoricalFS!G22,0) -> 0.23396928 | H23: =IFERROR(HistoricalFS!H22,0) -> 0.21478694 | I23: =IFERROR(HistoricalFS!I22,0) -> 0.20064447 | J23: =IFERROR(HistoricalFS!J22,0) -> 0.18243645 | ... L23: =IFERROR(HistoricalFS!L22,0) -> 0.21781974 | N23: =IFERROR(AVERAGE(C23:L23),0) -> 0.22489097 | O23: =IFERROR(MEDIAN(C23:L23),0) -> 0.22673325
B24: Depreciation%Sales | C24: =IFERROR(HistoricalFS!C31,0) -> 0.010967501 | D24: =IFERROR(HistoricalFS!D31,0) -> 0.013026959 | E24: =IFERROR(HistoricalFS!E31,0) -> 0.014629343 | F24: =IFERROR(HistoricalFS!F31,0) -> 0.014372933 | G24: =IFERROR(HistoricalFS!G31,0) -> 0.025186638 | H24: =IFERROR(HistoricalFS!H31,0) -> 0.022837459 | I24: =IFERROR(HistoricalFS!I31,0) -> 0.020802349 | J24: =IFERROR(HistoricalFS!J31,0) -> 0.01876857 | ... L24: =IFERROR(HistoricalFS!L31,0) -> 0.021466707 | N24: =IFERROR(AVERAGE(C24:L24),0) -> 0.018170432 | O24: =IFERROR(MEDIAN(C24:L24),0) -> 0.019207214
B25: OperatingIncome%Sales | C25: =C19 -> 0.17265271 | D25: =D19 -> 0.17779386 | E25: =E19 -> 0.19634266 | F25: =F19 -> 0.21152379 | G25: =G19 -> 0.22268306 | H25: =H19 -> 0.22437697 | I25: =I19 -> 0.22434504 | J25: =J19 -> 0.21475735 | ... L25: =L19 -> 0.21368483 | N25: =IFERROR(AVERAGE(C25:L25),0) -> 0.20753471 | O25: =IFERROR(MEDIAN(C25:L25),0) -> 0.21422109
B27: Return On Captial Employed | C27: =IFERROR((HistoricalFS!C24-HistoricalFS!C30)/SUM(HistoricalFS!C53:C55),0) -> 0.82325926 | D27: =IFERROR((HistoricalFS!D24-HistoricalFS!D30)/SUM(HistoricalFS!D53:D55),0) -> 0.83976642 | E27: =IFERROR((HistoricalFS!E24-HistoricalFS!E30)/SUM(HistoricalFS!E53:E55),0) -> 0.95852218 | F27: =IFERROR((HistoricalFS!F24-HistoricalFS!F30)/SUM(HistoricalFS!F53:F55),0) -> 1.0438112 | G27: =IFERROR((HistoricalFS!G24-HistoricalFS!G30)/SUM(HistoricalFS!G53:G55),0) -> 1.0765585 | H27: =IFERROR((HistoricalFS!H24-HistoricalFS!H30)/SUM(HistoricalFS!H53:H55),0) -> 0.22133658 | I27: =IFERROR((HistoricalFS!I24-HistoricalFS!I30)/SUM(HistoricalFS!I53:I55),0) -> 0.23483155 | J27: =IFERROR((HistoricalFS!J24-HistoricalFS!J30)/SUM(HistoricalFS!J53:J55),0) -> 0.25250859 | ... L27: =IFERROR((HistoricalFS!L24-HistoricalFS!L30)/SUM(HistoricalFS!L53:L55),0) -> 0.26421156 | N27: =IFERROR(AVERAGE(C27:L27),0) -> 0.59698815 | O27: =IFERROR(MEDIAN(C27:L27),0) -> 0.54373541
B28: Retained Earnings | C28: =IFERROR(HistoricalFS!C50,0) -> 0.057025921 | D28: =IFERROR(HistoricalFS!D50,0) -> 0.054582904 | E28: =IFERROR(HistoricalFS!E50,0) -> 0.11366434 | F28: =IFERROR(HistoricalFS!F50,0) -> 0.17183688 | G28: =IFERROR(HistoricalFS!G50,0) -> 0.14718888 | H28: =IFERROR(HistoricalFS!H50,0) -> -0.2156725 | I28: =IFERROR(HistoricalFS!I50,0) -> 0.078750144 | J28: =IFERROR(HistoricalFS!J50,0) -> 0.054667354 | ... L28: =IFERROR(HistoricalFS!L50,0) -> -0.33222805 | N28: =IFERROR(AVERAGE(C28:L28),0) -> 0.0087026655 | O28: =IFERROR(MEDIAN(C28:L28),0) -> 0.055846638
B29: Return on Equity | C29: =IFERROR(HistoricalFS!C39/SUM(HistoricalFS!C53:C54),0) -> 0.55758406 | D29: =IFERROR(HistoricalFS!D39/SUM(HistoricalFS!D53:D54),0) -> 0.57591934 | E29: =IFERROR(HistoricalFS!E39/SUM(HistoricalFS!E53:E54),0) -> 0.66941354 | F29: =IFERROR(HistoricalFS!F39/SUM(HistoricalFS!F53:F54),0) -> 0.72937587 | G29: =IFERROR(HistoricalFS!G39/SUM(HistoricalFS!G53:G54),0) -> 0.76947381 | H29: =IFERROR(HistoricalFS!H39/SUM(HistoricalFS!H53:H54),0) -> 0.16421949 | I29: =IFERROR(HistoricalFS!I39/SUM(HistoricalFS!I53:I54),0) -> 0.17677993 | J29: =IFERROR(HistoricalFS!J39/SUM(HistoricalFS!J53:J54),0) -> 0.19272821 | ... L29: =IFERROR(HistoricalFS!L39/SUM(HistoricalFS!L53:L54),0) -> 0.18924335 | N29: =IFERROR(AVERAGE(C29:L29),0) -> 0.42095359 | O29: =IFERROR(MEDIAN(C29:L29),0) -> 0.37515613
B30: Self Sustained Growth Rate | C30: =IFERROR(C29*C28,0) -> 0.031796744 | D30: =IFERROR(D29*D28,0) -> 0.03143535 | E30: =IFERROR(E29*E28,0) -> 0.076088449 | F30: =IFERROR(F29*F28,0) -> 0.12533367 | G30: =IFERROR(G29*G28,0) -> 0.11325799 | H30: =IFERROR(H29*H28,0) -> -0.035417628 | I30: =IFERROR(I29*I28,0) -> 0.013921445 | J30: =IFERROR(J29*J28,0) -> 0.010535941 | ... L30: =IFERROR(L29*L28,0) -> -0.062871949 | N30: =IFERROR(AVERAGE(C30:L30),0) -> 0.029617264 | O30: =IFERROR(MEDIAN(C30:L30),0) -> 0.022678397
B31: Interest Coverage Ratio | C31: =IFERROR((HistoricalFS!C24-HistoricalFS!C30)/HistoricalFS!C27,0) -> 326.88235 | D31: =IFERROR((HistoricalFS!D24-HistoricalFS!D30)/HistoricalFS!D27,0) -> 168.45714 | E31: =IFERROR((HistoricalFS!E24-HistoricalFS!E30)/HistoricalFS!E27,0) -> 268.42308 | F31: =IFERROR((HistoricalFS!F24-HistoricalFS!F30)/HistoricalFS!F27,0) -> 251.9697 | G31: =IFERROR((HistoricalFS!G24-HistoricalFS!G30)/HistoricalFS!G27,0) -> 75.076271 | H31: =IFERROR((HistoricalFS!H24-HistoricalFS!H30)/HistoricalFS!H27,0) -> 90.188034 | I31: =IFERROR((HistoricalFS!I24-HistoricalFS!I30)/HistoricalFS!I27,0) -> 111 | J31: =IFERROR((HistoricalFS!J24-HistoricalFS!J30)/HistoricalFS!J27,0) -> 114.12281 | ... L31: =IFERROR((HistoricalFS!L24-HistoricalFS!L30)/HistoricalFS!L27,0) -> 34.146835 | N31: =IFERROR(AVERAGE(C31:L31),0) -> 148.05147 | O31: =IFERROR(MEDIAN(C31:L31),0) -> 112.5614
B33: Debtor Turnover Ratio | C33: =IFERROR(HistoricalFS!C12/HistoricalFS!C65,0) -> 25.463608 | D33: =IFERROR(HistoricalFS!D12/HistoricalFS!D65,0) -> 30.564055 | E33: =IFERROR(HistoricalFS!E12/HistoricalFS!E65,0) -> 27.133588 | F33: =IFERROR(HistoricalFS!F12/HistoricalFS!F65,0) -> 21.646476 | G33: =IFERROR(HistoricalFS!G12/HistoricalFS!G65,0) -> 34.624021 | H33: =IFERROR(HistoricalFS!H12/HistoricalFS!H65,0) -> 26.750853 | I33: =IFERROR(HistoricalFS!I12/HistoricalFS!I65,0) -> 23.455277 | J33: =IFERROR(HistoricalFS!J12/HistoricalFS!J65,0) -> 19.675219 | ... L33: =IFERROR(HistoricalFS!L12/HistoricalFS!L65,0) -> 16.528149 | N33: =IFERROR(AVERAGE(C33:L33),0) -> 24.64939 | O33: =IFERROR(MEDIAN(C33:L33),0) -> 24.459442
B34: Creditor Turnover Ratio | C34: =IFERROR(HistoricalFS!C12/HistoricalFS!C56,0) -> 4.0017406 | D34: =IFERROR(HistoricalFS!D12/HistoricalFS!D56,0) -> 3.8183074 | E34: =IFERROR(HistoricalFS!E12/HistoricalFS!E56,0) -> 3.3593233 | F34: =IFERROR(HistoricalFS!F12/HistoricalFS!F56,0) -> 3.6865798 | G34: =IFERROR(HistoricalFS!G12/HistoricalFS!G56,0) -> 3.3363804 | H34: =IFERROR(HistoricalFS!H12/HistoricalFS!H56,0) -> 2.2324124 | I34: =IFERROR(HistoricalFS!I12/HistoricalFS!I56,0) -> 2.5706303 | J34: =IFERROR(HistoricalFS!J12/HistoricalFS!J56,0) -> 2.8106152 | ... L34: =IFERROR(HistoricalFS!L12/HistoricalFS!L56,0) -> 2.1907125 | N34: =IFERROR(AVERAGE(C34:L34),0) -> 3.0406981 | O34: =IFERROR(MEDIAN(C34:L34),0) -> 3.0734978
B35: Inventory Turnover Ratio | C35: =IFERROR(HistoricalFS!C15/HistoricalFS!C66,0) -> 6.6845194 | D35: =IFERROR(HistoricalFS!D15/HistoricalFS!D66,0) -> 7.3494687 | E35: =IFERROR(HistoricalFS!E15/HistoricalFS!E66,0) -> 7.6856347 | F35: =IFERROR(HistoricalFS!F15/HistoricalFS!F66,0) -> 8.1899767 | G35: =IFERROR(HistoricalFS!G15/HistoricalFS!G66,0) -> 7.4499458 | H35: =IFERROR(HistoricalFS!H15/HistoricalFS!H66,0) -> 7.0692931 | I35: =IFERROR(HistoricalFS!I15/HistoricalFS!I66,0) -> 7.0961914 | J35: =IFERROR(HistoricalFS!J15/HistoricalFS!J66,0) -> 8.3229828 | ... L35: =IFERROR(HistoricalFS!L15/HistoricalFS!L66,0) -> 7.8208381 | N35: =IFERROR(AVERAGE(C35:L35),0) -> 7.6035584 | O35: =IFERROR(MEDIAN(C35:L35),0) -> 7.5677902
B36: Fixed Assets Turnover Ratio | C36: =IFERROR(HistoricalFS!C12/HistoricalFS!C59,0) -> 9.8790669 | D36: =IFERROR(HistoricalFS!D12/HistoricalFS!D59,0) -> 7.5044128 | E36: =IFERROR(HistoricalFS!E12/HistoricalFS!E59,0) -> 7.8500442 | F36: =IFERROR(HistoricalFS!F12/HistoricalFS!F59,0) -> 8.3372216 | G36: =IFERROR(HistoricalFS!G12/HistoricalFS!G59,0) -> 7.2609965 | H36: =IFERROR(HistoricalFS!H12/HistoricalFS!H59,0) -> 0.91417686 | I36: =IFERROR(HistoricalFS!I12/HistoricalFS!I59,0) -> 1.0189031 | J36: =IFERROR(HistoricalFS!J12/HistoricalFS!J59,0) -> 1.1500057 | ... L36: =IFERROR(HistoricalFS!L12/HistoricalFS!L59,0) -> 1.1617006 | N36: =IFERROR(AVERAGE(C36:L36),0) -> 4.622821 | O36: =IFERROR(MEDIAN(C36:L36),0) -> 4.2113485
B37: Equity Capital Turnover Ratio | C37: =IFERROR(HistoricalFS!C12/SUM(HistoricalFS!C53:C54),0) -> 4.8966986 | D37: =IFERROR(HistoricalFS!D12/SUM(HistoricalFS!D53:D54),0) -> 4.9172598 | E37: =IFERROR(HistoricalFS!E12/SUM(HistoricalFS!E53:E54),0) -> 4.8818844 | F37: =IFERROR(HistoricalFS!F12/SUM(HistoricalFS!F53:F54),0) -> 4.9968222 | G37: =IFERROR(HistoricalFS!G12/SUM(HistoricalFS!G53:G54),0) -> 4.8344878 | H37: =IFERROR(HistoricalFS!H12/SUM(HistoricalFS!H53:H54),0) -> 0.98644964 | I37: =IFERROR(HistoricalFS!I12/SUM(HistoricalFS!I53:I54),0) -> 1.0689957 | J37: =IFERROR(HistoricalFS!J12/SUM(HistoricalFS!J53:J54),0) -> 1.204278 | ... L37: =IFERROR(HistoricalFS!L12/SUM(HistoricalFS!L53:L54),0) -> 1.2777013 | N37: =IFERROR(AVERAGE(C37:L37),0) -> 3.0273059 | O37: =IFERROR(MEDIAN(C37:L37),0) -> 3.0560945
B38: Total Capital turnover ratio | C38: =IFERROR(HistoricalFS!C12/SUM(HistoricalFS!C53:C55),0) -> 4.7682963 | D38: =IFERROR(HistoricalFS!D12/SUM(HistoricalFS!D53:D55),0) -> 4.7232588 | E38: =IFERROR(HistoricalFS!E12/SUM(HistoricalFS!E53:E55),0) -> 4.8818844 | F38: =IFERROR(HistoricalFS!F12/SUM(HistoricalFS!F53:F55),0) -> 4.9347226 | G38: =IFERROR(HistoricalFS!G12/SUM(HistoricalFS!G53:G55),0) -> 4.8344878 | H38: =IFERROR(HistoricalFS!H12/SUM(HistoricalFS!H53:H55),0) -> 0.98644964 | I38: =IFERROR(HistoricalFS!I12/SUM(HistoricalFS!I53:I55),0) -> 1.0467428 | J38: =IFERROR(HistoricalFS!J12/SUM(HistoricalFS!J53:J55),0) -> 1.1757856 | ... L38: =IFERROR(HistoricalFS!L12/SUM(HistoricalFS!L53:L55),0) -> 1.2364545 | N38: =IFERROR(AVERAGE(C38:L38),0) -> 2.9762535 | O38: =IFERROR(MEDIAN(C38:L38),0) -> 2.9798566
B40: Debtor Days | C40: =IFERROR(365/C33,0) -> 14.334183 | D40: =IFERROR(365/D33,0) -> 11.942133 | E40: =IFERROR(365/E33,0) -> 13.451962 | F40: =IFERROR(365/F33,0) -> 16.861867 | G40: =IFERROR(365/G33,0) -> 10.541814 | H40: =IFERROR(365/H33,0) -> 13.644425 | I40: =IFERROR(365/I33,0) -> 15.56153 | J40: =IFERROR(365/J33,0) -> 18.551255 | ... L40: =IFERROR(365/L33,0) -> 22.083538 | N40: =IFERROR(AVERAGE(C40:L40),0) -> 15.464598 | O40: =IFERROR(MEDIAN(C40:L40),0) -> 14.947856
B41: Payable Days | C41: =IFERROR(365/C34,0) -> 91.210309 | D41: =IFERROR(365/D34,0) -> 95.592093 | E41: =IFERROR(365/E34,0) -> 108.65283 | F41: =IFERROR(365/F34,0) -> 99.007759 | G41: =IFERROR(365/G34,0) -> 109.39999 | H41: =IFERROR(365/H34,0) -> 163.50026 | I41: =IFERROR(365/I34,0) -> 141.98852 | J41: =IFERROR(365/J34,0) -> 129.86481 | ... L41: =IFERROR(365/L34,0) -> 166.61246 | N41: =IFERROR(AVERAGE(C41:L41),0) -> 125.78947 | O41: =IFERROR(MEDIAN(C41:L41),0) -> 119.6324
B42: Inventory Days | C42: =IFERROR(365/C35,0) -> 54.603776 | D42: =IFERROR(365/D35,0) -> 49.663454 | E42: =IFERROR(365/E35,0) -> 47.491198 | F42: =IFERROR(365/F35,0) -> 44.566671 | G42: =IFERROR(365/G35,0) -> 48.993645 | H42: =IFERROR(365/H35,0) -> 51.631754 | I42: =IFERROR(365/I35,0) -> 51.436042 | J42: =IFERROR(365/J35,0) -> 43.85447 | ... L42: =IFERROR(365/L35,0) -> 46.67019 | N42: =IFERROR(AVERAGE(C42:L42),0) -> 48.253635 | O42: =IFERROR(MEDIAN(C42:L42),0) -> 48.242422
B43: Cash Conversion cycle | C43: =IFERROR(SUM(C40,C42)-C41,0) -> -22.272351 | D43: =IFERROR(SUM(D40,D42)-D41,0) -> -33.986507 | E43: =IFERROR(SUM(E40,E42)-E41,0) -> -47.709674 | F43: =IFERROR(SUM(F40,F42)-F41,0) -> -37.57922 | G43: =IFERROR(SUM(G40,G42)-G41,0) -> -49.864536 | H43: =IFERROR(SUM(H40,H42)-H41,0) -> -98.224077 | I43: =IFERROR(SUM(I40,I42)-I41,0) -> -74.990949 | J43: =IFERROR(SUM(J40,J42)-J41,0) -> -67.459082 | ... L43: =IFERROR(SUM(L40,L42)-L41,0) -> -97.85873 | N43: =IFERROR(AVERAGE(C43:L43),0) -> -62.071234 | O43: =IFERROR(MEDIAN(C43:L43),0) -> -58.661809
B45: CFO/Sales | C45: =IFERROR(HistoricalFS!C114/HistoricalFS!C12,0) -> 0.12959051 | D45: =IFERROR(HistoricalFS!D114/HistoricalFS!D12,0) -> 0.15635366 | E45: =IFERROR(HistoricalFS!E114/HistoricalFS!E12,0) -> 0.17045998 | F45: =IFERROR(HistoricalFS!F114/HistoricalFS!F12,0) -> 0.14754515 | G45: =IFERROR(HistoricalFS!G114/HistoricalFS!G12,0) -> 0.19161451 | H45: =IFERROR(HistoricalFS!H114/HistoricalFS!H12,0) -> 0.19484137 | I45: =IFERROR(HistoricalFS!I114/HistoricalFS!I12,0) -> 0.17252031 | J45: =IFERROR(HistoricalFS!J114/HistoricalFS!J12,0) -> 0.16492242 | ... L45: =IFERROR(HistoricalFS!L114/HistoricalFS!L12,0) -> 0.188305 | N45: =IFERROR(AVERAGE(C45:L45),0) -> 0.17660721 | O45: =IFERROR(MEDIAN(C45:L45),0) -> 0.17149014
B46: CFO/Total Assets | C46: =IFERROR(HistoricalFS!C114/HistoricalFS!C70,0) -> 0.28195768 | D46: =IFERROR(HistoricalFS!D114/HistoricalFS!D70,0) -> 0.33012861 | E46: =IFERROR(HistoricalFS!E114/HistoricalFS!E70,0) -> 0.33921173 | F46: =IFERROR(HistoricalFS!F114/HistoricalFS!F70,0) -> 0.31134253 | G46: =IFERROR(HistoricalFS!G114/HistoricalFS!G70,0) -> 0.37825634 | H46: =IFERROR(HistoricalFS!H114/HistoricalFS!H70,0) -> 0.13329939 | I46: =IFERROR(HistoricalFS!I114/HistoricalFS!I70,0) -> 0.1283295 | J46: =IFERROR(HistoricalFS!J114/HistoricalFS!J70,0) -> 0.1367188 | ... L46: =IFERROR(HistoricalFS!L114/HistoricalFS!L70,0) -> 0.14882987 | N46: =IFERROR(AVERAGE(C46:L46),0) -> 0.23851594 | O46: =IFERROR(MEDIAN(C46:L46),0) -> 0.23952131
B47: CFO/Total Debt | C47: =IFERROR(HistoricalFS!C114/HistoricalFS!C55,0) -> 23.564972 | D47: =IFERROR(HistoricalFS!D114/HistoricalFS!D55,0) -> 18.718412 | E47: =IFERROR(HistoricalFS!E114/HistoricalFS!E55,0) -> 0 | F47: =IFERROR(HistoricalFS!F114/HistoricalFS!F55,0) -> 58.585859 | G47: =IFERROR(HistoricalFS!G114/HistoricalFS!G55,0) -> 0 | H47: =IFERROR(HistoricalFS!H114/HistoricalFS!H55,0) -> 0 | I47: =IFERROR(HistoricalFS!I114/HistoricalFS!I55,0) -> 8.674976 | J47: =IFERROR(HistoricalFS!J114/HistoricalFS!J55,0) -> 8.1960623 | ... L47: =IFERROR(HistoricalFS!L114/HistoricalFS!L55,0) -> 7.2123786 | N47: =IFERROR(AVERAGE(C47:L47),0) -> 13.537651 | O47: =IFERROR(MEDIAN(C47:L47),0) -> 8.4355192

Sheet Dupont Analysis
B3: ='Data Sheet'!B1 -> HINDUSTAN UNILEVER LTD
B4: =CONCATENATE("","(",VLOOKUP(B3,'List of Stocks'!A2:D5442,3,FALSE)," | ", "BSE Code: ",VLOOKUP('Dupont Analysis'!B3,'List of Stocks'!A2:D5442,2,FALSE),")") -> (HINDUNILVR | BSE Code: 500696)
B5: =CONCATENATE("","INR "&'Data Sheet'!B8) -> INR 2082.5
B6: 52 Week High - INR 2,750.00 & Low - 2,022.50
B9: About the Company
B10: Hindustan Unilever Limited (HUL) is an Indian fast-moving consumer goods company, headquartered in Mumbai.It is a subsidiary of the Anglo-Dutch company Unilever. Its products include foods, beverages, cleaning agents, personal care products and other consumer staples.The company was established in India in 1931 as Hindustan Vanaspati Manufacturing Co. Following a merger of constituent groups in 1956, it was renamed Hindustan Lever Limited. The company was renamed again in June 2007 as Hindustan Unilever Limited.
B15: Financial Summary
B70: Return on Equity
C71: =HistoricalFS!F9 -> 43555 | D71: =HistoricalFS!G9 -> 43921 | E71: =HistoricalFS!H9 -> 44286 | F71: =HistoricalFS!I9 -> 44651 | G71: =HistoricalFS!J9 -> 45016 | H71: =HistoricalFS!K9 -> 45382 | I71: =HistoricalFS!L9 -> 45747
B72: Net Profit | C72: ='Data Sheet'!E30 -> 6054 | D72: ='Data Sheet'!F30 -> 6748 | E72: ='Data Sheet'!G30 -> 7995 | F72: ='Data Sheet'!H30 -> 8879 | G72: ='Data Sheet'!I30 -> 10120 | H72: ='Data Sheet'!J30 -> 10277 | I72: ='Data Sheet'!K30 -> 10649
B73: Average Shareholder Equity | C73: =(('Data Sheet'!E57+'Data Sheet'!E58)+('Data Sheet'!D57+'Data Sheet'!D58))/2 -> 7574 | D73: =(('Data Sheet'!F57+'Data Sheet'!F58)+('Data Sheet'!E57+'Data Sheet'!E58))/2 -> 8048 | E73: =(('Data Sheet'!G57+'Data Sheet'!G58)+('Data Sheet'!F57+'Data Sheet'!F58))/2 -> 27951.5 | F73: =(('Data Sheet'!H57+'Data Sheet'!H58)+('Data Sheet'!G57+'Data Sheet'!G58))/2 -> 48367.5 | G73: =(('Data Sheet'!I57+'Data Sheet'!I58)+('Data Sheet'!H57+'Data Sheet'!H58))/2 -> 49682.5 | H73: =(('Data Sheet'!J57+'Data Sheet'!J58)+('Data Sheet'!I57+'Data Sheet'!I58))/2 -> 50761 | I73: =(('Data Sheet'!K57+'Data Sheet'!K58)+('Data Sheet'!J57+'Data Sheet'!J58))/2 -> 50310
B74: Return on Equity | C74: =C72/C73 -> 0.79931344 | D74: =D72/D73 -> 0.83846918 | E74: =E72/E73 -> 0.28603116 | F74: =F72/F73 -> 0.18357368 | G74: =G72/G73 -> 0.20369345 | H74: =H72/H73 -> 0.20245858 | I74: =I72/I73 -> 0.21166766
B76: ROE- Dupont Equation
C77: =C71 -> 43555 | D77: =D71 -> 43921 | E77: =E71 -> 44286 | F77: =F71 -> 44651 | G77: =G71 -> 45016 | H77: =H71 -> 45382 | I77: =I71 -> 45747
B78: =B72 -> Net Profit | C78: =C72 -> 6054 | D78: =D72 -> 6748 | E78: =E72 -> 7995 | F78: =F72 -> 8879 | G78: =G72 -> 10120 | H78: =H72 -> 10277 | I78: =I72 -> 10649
B79: Revenue | C79: ='Data Sheet'!E17 -> 39310 | D79: ='Data Sheet'!F17 -> 39783 | E79: ='Data Sheet'!G17 -> 47028 | F79: ='Data Sheet'!H17 -> 52446 | G79: ='Data Sheet'!I17 -> 60580 | H79: ='Data Sheet'!J17 -> 61896 | I79: ='Data Sheet'!K17 -> 63121
B80: Net Profit Margin(A) | C80: =C78/C79 -> 0.15400661 | D80: =D78/D79 -> 0.16962019 | E80: =E78/E79 -> 0.1700051 | F80: =F78/F79 -> 0.16929794 | G80: =G78/G79 -> 0.16705183 | H80: =H78/H79 -> 0.16603658 | I80: =I78/I79 -> 0.16870772
B82: Revenue | C82: =C79 -> 39310 | D82: =D79 -> 39783 | E82: =E79 -> 47028 | F82: =F79 -> 52446 | G82: =G79 -> 60580 | H82: =H79 -> 61896 | I82: =I79 -> 63121
B83: Average Total Asset | C83: =('Data Sheet'!E66+'Data Sheet'!D66)/2 -> 18245.5 | D83: =('Data Sheet'!F66+'Data Sheet'!E66)/2 -> 19391 | E83: =('Data Sheet'!G66+'Data Sheet'!F66)/2 -> 44446.5 | F83: =('Data Sheet'!H66+'Data Sheet'!G66)/2 -> 69623 | G83: =('Data Sheet'!I66+'Data Sheet'!H66)/2 -> 71791.5 | H83: =('Data Sheet'!J66+'Data Sheet'!I66)/2 -> 75783 | I83: =('Data Sheet'!K66+'Data Sheet'!J66)/2 -> 79176
B84: Asset Turnover Ratio(B) | C84: =C82/C83 -> 2.1545039 | D84: =D82/D83 -> 2.0516219 | E84: =E82/E83 -> 1.0580811 | F84: =F82/F83 -> 0.75328555 | G84: =G82/G83 -> 0.84383249 | H84: =H82/H83 -> 0.8167531 | I84: =I82/I83 -> 0.79722391
B86: =B83 -> Average Total Asset | C86: =C83 -> 18245.5 | D86: =D83 -> 19391 | E86: =E83 -> 44446.5 | F86: =F83 -> 69623 | G86: =G83 -> 71791.5 | H86: =H83 -> 75783 | I86: =I83 -> 79176
B87: =B73 -> Average Shareholder Equity | C87: =C73 -> 7574 | D87: =D73 -> 8048 | E87: =E73 -> 27951.5 | F87: =F73 -> 48367.5 | G87: =G73 -> 49682.5 | H87: =H73 -> 50761 | I87: =I73 -> 50310
B88: Equity Multiplier(C) | C88: =C86/C87 -> 2.4089649 | D88: =D86/D87 -> 2.4094185 | E88: =E86/E87 -> 1.5901293 | F88: =F86/F87 -> 1.4394583 | G88: =G86/G87 -> 1.4450058 | H88: =H86/H87 -> 1.4929375 | I88: =I86/I87 -> 1.5737627
B90: Return on Equity(A*B*C) | C90: =C88*C84*C80 -> 0.79931344 | D90: =D88*D84*D80 -> 0.83846918 | E90: =E88*E84*E80 -> 0.28603116 | F90: =F88*F84*F80 -> 0.18357368 | G90: =G88*G84*G80 -> 0.20369345 | H90: =H88*H84*H80 -> 0.20245858 | I90: =I88*I84*I80 -> 0.21166766
B92: Return on Asset
C93: =C77 -> 43555 | D93: =D77 -> 43921 | E93: =E77 -> 44286 | F93: =F77 -> 44651 | G93: =G77 -> 45016 | H93: =H77 -> 45382 | I93: =I77 -> 45747
B94: =B78 -> Net Profit | C94: =C78 -> 6054 | D94: =D78 -> 6748 | E94: =E78 -> 7995 | F94: =F78 -> 8879 | G94: =G78 -> 10120 | H94: =H78 -> 10277 | I94: =I78 -> 10649
B95: =B83 -> Average Total Asset | C95: =C86 -> 18245.5 | D95: =D86 -> 19391 | E95: =E86 -> 44446.5 | F95: =F86 -> 69623 | G95: =G86 -> 71791.5 | H95: =H86 -> 75783 | I95: =I86 -> 79176
B96: Return on Asset | C96: =C94/C95 -> 0.33180784 | D96: =D94/D95 -> 0.34799649 | E96: =E94/E95 -> 0.17987918 | F96: =F94/F95 -> 0.1275297 | G96: =G94/G95 -> 0.14096376 | H96: =H94/H95 -> 0.13561089 | I96: =I94/I95 -> 0.13449783
B98: ROA- Dupont Equation
C99: =C93 -> 43555 | D99: =D93 -> 43921 | E99: =E93 -> 44286 | F99: =F93 -> 44651 | G99: =G93 -> 45016 | H99: =H93 -> 45382 | I99: =I93 -> 45747
B100: =B94 -> Net Profit | C100: =C78 -> 6054 | D100: =D78 -> 6748 | E100: =E78 -> 7995 | F100: =F78 -> 8879 | G100: =G78 -> 10120 | H100: =H78 -> 10277 | I100: =I78 -> 10649
B101: Revenue | C101: =C79 -> 39310 | D101: =D79 -> 39783 | E101: =E79 -> 47028 | F101: =F79 -> 52446 | G101: =G79 -> 60580 | H101: =H79 -> 61896 | I101: =I79 -> 63121
B102: Net Profit Margin(A) | C102: =C100/C101 -> 0.15400661 | D102: =D100/D101 -> 0.16962019 | E102: =E100/E101 -> 0.1700051 | F102: =F100/F101 -> 0.16929794 | G102: =G100/G101 -> 0.16705183 | H102: =H100/H101 -> 0.16603658 | I102: =I100/I101 -> 0.16870772
B104: Revenue | C104: =C101 -> 39310 | D104: =D101 -> 39783 | E104: =E101 -> 47028 | F104: =F101 -> 52446 | G104: =G101 -> 60580 | H104: =H101 -> 61896 | I104: =I101 -> 63121
B105: Average Total Asset | C105: =C95 -> 18245.5 | D105: =D95 -> 19391 | E105: =E95 -> 44446.5 | F105: =F95 -> 69623 | G105: =G95 -> 71791.5 | H105: =H95 -> 75783 | I105: =I95 -> 79176
B106: Asset Turnover Ratio(B) | C106: =C104/C105 -> 2.1545039 | D106: =D104/D105 -> 2.0516219 | E106: =E104/E105 -> 1.0580811 | F106: =F104/F105 -> 0.75328555 | G106: =G104/G105 -> 0.84383249 | H106: =H104/H105 -> 0.8167531 | I106: =I104/I105 -> 0.79722391
B108: Return on Asset(A*B) | C108: =C102*C106 -> 0.33180784 | D108: =D102*D106 -> 0.34799649 | E108: =E102*E106 -> 0.17987918 | F108: =F102*F106 -> 0.1275297 | G108: =G102*G106 -> 0.14096376 | H108: =H102*H106 -> 0.13561089 | I108: =I102*I106 -> 0.13449783
G125: p

Sheet Data>

Sheet Hind. Uni Share Price Daily 5y
A1: Date | B1: Adj Close | C1: Volume
A2: 2021-04-15 | B2: 2262.8271 | C2: 3.352379 | D2: 1000000
A3: 2021-04-16 | B3: 2261.2175 | C3: 1.225517
A4: 2021-04-19 | B4: 2240.7563 | C4: 1.746316
A5: 2021-04-20 | B5: 2204.708 | C5: 1.589508
A6: 2021-04-22 | B6: 2160.521 | C6: 1.721265
A7: 2021-04-23 | B7: 2122.2195 | C7: 1.949756
A8: 2021-04-26 | B8: 2170.8662 | C8: 1.946867
A9: 2021-04-27 | B9: 2188.5234 | C9: 1.668456
A10: 2021-04-28 | B10: 2213.0764 | C10: 1.951215
A11: 2021-04-29 | B11: 2214.042 | C11: 3.15115
A12: 2021-04-30 | B12: 2164.521 | C12: 4.010778
A13: 2021-05-03 | B13: 2214.4099 | C13: 1.692239
A14: 2021-05-04 | B14: 2214.0876 | C14: 1.453111
... A1235: 2026-04-10 | B1235: 2155.3 | C1235: 2.144484
E1237: 100
B1239: Shareholder's name | C1239: N. Shares (In Crs.) | D1239: % Holding | E1239: Market Value (In Crs.)
B1240: UNILEVER PLC | C1240: 111.43701 | D1240: 0.4743 | E1240: =2232*C1240 -> 248727.42
B1241: LIFE INSURANCE CORPORATION OF INDIA | C1241: 15.743276 | D1241: 0.067 | E1241: =2232*C1241 -> 35138.992
B1242: UNILEVER GROUP LIMITED | C1242: 10.673946 | D1242: 0.0454 | E1242: =2232*C1242 -> 23824.247
B1243: UNILEVER OVERSEAS HOLDINGS AG | C1243: 6.878432 | D1243: 0.0293 | E1243: =2232*C1243 -> 15352.66
B1244: UNILEVER UK&CN HOLDINGS LIMITED | C1244: 6.008625 | D1244: 0.0256 | E1244: =2232*C1244 -> 13411.251
B1245: UNILEVER SOUTH INDIA ESTATES LIMITED | C1245: 5.27472 | D1245: 0.0224 | E1245: =2232*C1245 -> 11773.175
B1246: SBI ESG EXCLUSIONARY STRATEGY FUND | C1246: 3.8897573 | D1246: 0.0166 | E1246: =2232*C1246 -> 8681.9383
B1247: ICICI PRUDENTIAL SENSEX ETF | C1247: 3.4496318 | D1247: 0.0147 | E1247: =2232*C1247 -> 7699.5782
B1248: UNILEVER ASSAM ESTATES LIMITED | C1248: 3.282048 | D1248: 0.014 | E1248: =2232*C1248 -> 7325.5311
B1249: UNILEVER OVERSEAS HOLDINGS B V | C1249: 1.8865 | D1249: 0.008 | E1249: =2232*C1249 -> 4210.668
B1251: Promoters | C1251: 0.619
B1252: FIIs | C1252: 0.1071
B1253: DIIs | C1253: 0.1568
B1254: Public & Govt. | C1254: =11.64%+0.07% -> 0.1171

Sheet Cash Flow Data
F2: 41699 | G2: 42064 | H2: 42430 | I2: 42795 | J2: 43160 | K2: 43525 | L2: 43891 | M2: 44256 | N2: 44621 | O2: 44986 | P2: 45352 | Q2: 45717
C3: Cash from Operating Activity - | F3: 3818 | G3: 3292 | H3: 4171 | I3: 5185 | J3: 6059 | K3: 5800 | L3: 7623 | M3: 9163 | N3: 9048 | O3: 9991 | P3: 15469 | Q3: 11886
C4: Profit from operations | F4: 4802 | G4: 5510 | H4: 6025 | I4: 6512 | J4: 7485 | K4: 8909 | L4: 9723 | M4: 11672 | N4: 12829 | O4: 14089 | P4: 14537 | Q4: 14942
C5: Receivables | F5: -17 | G5: 3 | H5: -257 | I5: 173 | J5: 0 | K5: 0 | L5: 0 | M5: 0 | N5: 0 | O5: 0 | P5: 0 | Q5: 0
C6: Inventory | F6: -201 | G6: 91 | H6: 89 | I6: 37 | J6: -146 | K6: -195 | L6: -331 | M6: -543 | N6: -758 | O6: -339 | P6: 74 | Q6: -584
C7: Payables | F7: 546 | G7: -327 | H7: 164 | I7: 501 | J7: 0 | K7: 0 | L7: 0 | M7: 0 | N7: 0 | O7: 0 | P7: 0 | Q7: 0
C8: Loans Advances | F8: -4 | G8: -148 | H8: 0 | I8: 0 | J8: 0 | K8: 0 | L8: 0 | M8: 0 | N8: 0 | O8: 0 | P8: 0 | Q8: 0
C9: Operating Deposits | F9: 0 | G9: 0 | H9: 0 | I9: -46 | J9: 0 | K9: 0 | L9: 0 | M9: 0 | N9: 0 | O9: 0 | P9: 0 | Q9: 0
C10: Other WC items | F10: 81 | G10: 38 | H10: -77 | I10: -99 | J10: 982 | K10: -147 | L10: 742 | M10: 442 | N10: -242 | O10: -621 | P10: 1239 | Q10: -204
C11: Direct Taxes | F11: -1384 | G11: -1862 | H11: -1765 | I11: -1859 | J11: -2264 | K11: -2767 | L11: -2505 | M11: -2407 | N11: -2784 | O11: -3138 | P11: -381 | Q11: -2268
C12: Other Opertaing Items | F12: -5 | G12: -14 | H12: -8 | I12: -21 | J12: 0 | K12: 0 | L12: 0 | M12: 0 | N12: 0 | O12: 0 | P12: 0 | Q12: 0
C13: Exceptional CF Items | F13: 0 | G13: 0 | H13: 0 | I13: -13 | J13: 2 | K13: 0 | L13: -6 | M13: -1 | N13: 3 | O13: 0 | P13: 0 | Q13: 0
C14: Cash from Investing Activity - | F14: -475 | G14: 138 | H14: -282 | I14: -1173 | J14: -1063 | K14: -438 | L14: 1791 | M14: -1228 | N14: -1728 | O14: -1484 | P14: -5324 | Q14: 6473
... C34: Net Cash Flow | F34: 383 | G34: -33 | H34: 25 | I34: -202 | J34: 21 | K34: -28 | L34: 2595 | M34: -1374 | N34: -695 | O34: -446 | P34: 111 | Q34: 5258

Sheet Data Sheet
A1: COMPANY NAME | B1: HINDUSTAN UNILEVER LTD | E1: =IF(B2<>B3, "A NEW VERSION OF THE WORKSHEET IS AVAILABLE", "")
A2: LATEST VERSION | B2: 2.1 | E2: PLEASE DO NOT MAKE ANY CHANGES TO THIS SHEET
A3: CURRENT VERSION | B3: 2.1
A5: META
A6: Number of shares | B6: =IF(B9>0, B9/B8, 0) -> 234.95918
A7: Face Value | B7: 1
A8: Current Price | B8: 2082.5
A9: Market Capitalization | B9: 489302.49
A15: PROFIT & LOSS
A16: Report Date | B16: 42460 | C16: 42825 | D16: 43190 | E16: 43555 | F16: 43921 | G16: 44286 | H16: 44651 | I16: 45016 | J16: 45382 | K16: 45747
A17: Sales | B17: 32186 | C17: 33162 | D17: 35545 | E17: 39310 | F17: 39783 | G17: 47028 | H17: 52446 | I17: 60580 | J17: 61896 | K17: 63121
A18: Raw Material Cost | B18: 13184 | C18: 13606 | D18: 14233 | E18: 15845 | F18: 15697 | G18: 20141 | H18: 22871 | I18: 28427 | J18: 26822 | K18: 27344
A19: Change in Inventory | B19: -83 | C19: -144 | D19: 72 | E19: -12 | F19: 108 | G19: 405 | H19: 22 | I19: 75 | J19: 11 | K19: 153
A20: Power and Fuel | B20: 309 | C20: 295 | D20: 295 | E20: 308 | F20: 299 | G20: 339 | H20: 318 | I20: 384 | J20: 446 | K20: 427
A21: Other Mfr. Exp | B21: 2966 | C21: 2887 | D21: 2998 | E21: 3041 | F21: 2906 | G21: 2868 | H21: 3354 | I21: 3791 | J21: 3385 | K21: 3834
A22: Employee Cost | B22: 1680 | C22: 1743 | D22: 1860 | E22: 1875 | F22: 1820 | G22: 2358 | H22: 2545 | I22: 2854 | J22: 3009 | K22: 3077
A23: Selling and admin | B23: 6741 | C23: 6689 | D23: 7252 | E23: 7796 | F23: 7620 | G23: 7906 | H23: 8164 | I23: 8785 | J23: 10780 | K23: 10693
A24: Other Expenses | B24: 1313 | C24: 1470 | D24: 1480 | E24: 1553 | F24: 1688 | G24: 2195 | H24: 2359 | I24: 2267 | J24: 2806 | K24: 3056
A25: Other Income | B25: 486 | C25: 606 | D25: 353 | E25: 322 | F25: 424 | G25: 170 | H25: 219 | I25: 448 | J25: 817 | K25: 1322
A26: Depreciation | B26: 353 | C26: 432 | D26: 520 | E26: 565 | F26: 1002 | G26: 1074 | H26: 1091 | I26: 1137 | J26: 1216 | K26: 1355
A27: Interest | B27: 17 | C27: 35 | D27: 26 | E27: 33 | F27: 118 | G27: 117 | H27: 106 | I27: 114 | J27: 334 | K27: 395
... A31: Dividend Amount | B31: 3456 | C31: 3672 | D31: 4320 | E31: 4752 | F31: 5400 | G31: 9517.5 | H31: 7990 | I31: 9165 | J31: 9870 | K31: 12455
A33: EBIDTA | B33: =B30+B29+B26+B27 -> 6396 | C33: =C30+C29+C26+C27 -> 6920 | D33: =D30+D29+D26+D27 -> 7839 | E33: =E30+E29+E26+E27 -> 9196 | F33: =F30+F29+F26+F27 -> 10277 | G33: =G30+G29+G26+G27 -> 11792 | H33: =H30+H29+H26+H27 -> 13063 | I33: =I30+I29+I26+I27 -> 14572 | ... K33: =K30+K29+K26+K27 -> 16143
A40: Quarters
A41: Report Date | B41: 45199 | C41: 45291 | D41: 45382 | E41: 45473 | F41: 45565 | G41: 45657 | H41: 45747 | I41: 45838 | J41: 45930 | K41: 46022
A42: Sales | B42: 15623 | C42: 15567 | D42: 15210 | E42: 15707 | F42: 15926 | G42: 15556 | H42: 15670 | I42: 16514 | J42: 15919 | K42: 16441
A43: Expenses | B43: 11828 | C43: 11902 | D43: 11675 | E43: 11965 | F43: 12139 | G43: 11867 | H43: 12052 | I43: 12797 | J43: 12137 | K43: 12660
A44: Other Income | B44: 178 | C44: 184 | D44: 309 | E44: 209 | F44: 203 | G44: 733 | H44: 171 | I44: 74 | J44: 269 | K44: 4048
A45: Depreciation | B45: 297 | C45: 313 | D45: 320 | E45: 329 | F45: 338 | G45: 318 | H45: 347 | I45: 361 | J45: 322 | K45: 337
A46: Interest | B46: 88 | C46: 91 | D46: 105 | E46: 93 | F46: 110 | G46: 109 | H46: 80 | I46: 127 | J46: 124 | K46: 88
A47: Profit before tax | B47: 3588 | C47: 3445 | D47: 3419 | E47: 3529 | F47: 3542 | G47: 3995 | H47: 3362 | I47: 3303 | J47: 3605 | K47: 7404
A48: Tax | B48: 931 | C48: 937 | D48: 858 | E48: 917 | F48: 947 | G48: 1006 | H48: 887 | I48: 535 | J48: 911 | K48: 801
A49: Net profit | B49: 2656 | C49: 2509 | D49: 2558 | E49: 2610 | F49: 2591 | G49: 2984 | H49: 2464 | I49: 2756 | J49: 2685 | K49: 6607
A50: Operating Profit | B50: 3795 | C50: 3665 | D50: 3535 | E50: 3742 | F50: 3787 | G50: 3689 | H50: 3618 | I50: 3717 | J50: 3782 | K50: 3781
A55: BALANCE SHEET
A56: Report Date | B56: 42460 | C56: 42825 | D56: 43190 | E56: 43555 | F56: 43921 | G56: 44286 | H56: 44651 | I56: 45016 | J56: 45382 | K56: 45747
A57: Equity Share Capital | B57: 216 | C57: 216 | D57: 216 | E57: 216 | F57: 216 | G57: 235 | H57: 235 | I57: 235 | J57: 235 | K57: 235
A58: Reserves | B58: 6357 | C58: 6528 | D58: 7065 | E58: 7651 | F58: 8013 | G58: 47439 | H58: 48826 | I58: 50069 | J58: 50983 | K58: 49167
A59: Borrowings | B59: 177 | C59: 277 | E59: 99 | H59: 1043 | I59: 1219 | J59: 1484 | K59: 1648
A60: Other Liabilities | B60: 8043 | C60: 8685 | D60: 10581 | E60: 10663 | F60: 11924 | G60: 21066 | H60: 20402 | I60: 21554 | J60: 25787 | K60: 28813
A61: Total | B61: 14793 | C61: 15706 | D61: 17862 | E61: 18629 | F61: 20153 | G61: 68740 | H61: 70506 | I61: 73077 | J61: 78489 | K61: 79863
A62: Net Block | B62: 3258 | C62: 4419 | D62: 4528 | E62: 4715 | F62: 5479 | G62: 51443 | H62: 51473 | I62: 52678 | J62: 53744 | K62: 54335
A63: Capital Work in Progress | B63: 408 | C63: 229 | D63: 461 | E63: 406 | F63: 597 | G63: 745 | H63: 1313 | I63: 1132 | J63: 1025 | K63: 1009
A64: Investments | B64: 2592 | C64: 3794 | D64: 2873 | E64: 2716 | F64: 1255 | G64: 2709 | H64: 3521 | I64: 2882 | J64: 4625 | K64: 3810
A65: Other Assets | B65: 8535 | C65: 7264 | D65: 10000 | E65: 10792 | F65: 12822 | G65: 13843 | H65: 14199 | I65: 16385 | J65: 19095 | K65: 20709
A66: Total | B66: 14793 | C66: 15706 | D66: 17862 | E66: 18629 | F66: 20153 | G66: 68740 | H66: 70506 | I66: 73077 | J66: 78489 | K66: 79863
A67: Receivables | B67: 1264 | C67: 1085 | D67: 1310 | E67: 1816 | F67: 1149 | G67: 1758 | H67: 2236 | I67: 3079 | J67: 2997 | K67: 3819
A68: Inventory | B68: 2726 | C68: 2541 | D68: 2513 | E68: 2574 | F68: 2767 | G68: 3579 | H68: 4096 | I68: 4251 | J68: 4022 | K68: 4415
A69: Cash & Bank | B69: 3009 | C69: 1828 | D69: 3485 | E69: 3757 | F69: 5113 | G69: 4471 | H69: 3846 | I69: 4678 | J69: 7559 | K69: 7554
A70: No. of Equity Shares | B70: 2163936971 | C70: 2164349639 | D70: 2164528777 | E70: 2164704405 | F70: 2164704405 | G70: 2349567819 | H70: 2349591262 | I70: 2349591262 | J70: 2349591262 | K70: 2349591262
A71: New Bonus Shares
A72: Face value | B72: 1 | C72: 1 | D72: 1 | E72: 1 | F72: 1 | G72: 1 | H72: 1 | I72: 1 | J72: 1 | K72: 1
A74: Other | B74: =B65-(SUM(B67:B69)) -> 1536 | C74: =C65-(SUM(C67:C69)) -> 1810 | D74: =D65-(SUM(D67:D69)) -> 2692 | E74: =E65-(SUM(E67:E69)) -> 2645 | F74: =F65-(SUM(F67:F69)) -> 3793 | G74: =G65-(SUM(G67:G69)) -> 4035 | H74: =H65-(SUM(H67:H69)) -> 4021 | I74: =I65-(SUM(I67:I69)) -> 4377 | ... K74: =K65-(SUM(K67:K69)) -> 4921
A75: Total Assets | B75: =B61 -> 14793 | C75: =C61 -> 15706 | D75: =D61 -> 17862 | E75: =E61 -> 18629 | F75: =F61 -> 20153 | G75: =G61 -> 68740 | H75: =H61 -> 70506 | I75: =I61 -> 73077 | ... K75: =K61 -> 79863
A80: CASH FLOW:
A81: Report Date | B81: 42460 | C81: 42825 | D81: 43190 | E81: 43555 | F81: 43921 | G81: 44286 | H81: 44651 | I81: 45016 | J81: 45382 | K81: 45747
A82: Cash from Operating Activity | B82: 4171 | C82: 5185 | D82: 6059 | E82: 5800 | F82: 7623 | G82: 9163 | H82: 9048 | I82: 9991 | J82: 15469 | K82: 11886
A83: Cash from Investing Activity | B83: -282 | C83: -1173 | D83: -1063 | E83: -438 | F83: 1791 | G83: -1228 | H83: -1728 | I83: -1484 | J83: -5324 | K83: 6473
A84: Cash from Financing Activity | B84: -3864 | C84: -4214 | D84: -4975 | E84: -5390 | F84: -6819 | G84: -9309 | H84: -8015 | I84: -8953 | J84: -10034 | K84: -13101
A85: Net Cash Flow | B85: 25 | C85: -202 | D85: 21 | E85: -28 | F85: 2595 | G85: -1374 | H85: -695 | I85: -446 | J85: 111 | K85: 5258
A90: PRICE: | B90: 832.17 | C90: 872.61 | D90: 1276.11 | E90: 1633.53 | F90: 2199.83 | G90: 2327.12 | H90: 1960.7 | I90: 2450.44 | J90: 2167.14 | K90: 2161.88
A92: DERIVED:
A93: Adjusted Equity Shares in Cr | B93: 216.39 | C93: 216.43 | D93: 216.45 | E93: 216.47 | F93: 216.48 | G93: 234.96 | H93: 234.96 | I93: 234.96 | J93: 234.96 | K93: 234.96

Sheet Data Room>

Sheet Raw FS
B2: Particulars | C2: 42430 | D2: 42795 | E2: 43160 | F2: 43525 | G2: 43891 | H2: 44256 | I2: 44621 | J2: 44986 | K2: 45352 | L2: 45717
B4: Equity Capital | C4: 216 | D4: 216 | E4: 216 | F4: 216 | G4: 216 | H4: 235 | I4: 235 | J4: 235 | K4: 235 | L4: 235
B5: Reserves | C5: 6357 | D5: 6528 | E5: 7065 | F5: 7651 | G5: 8013 | H5: 47439 | I5: 48826 | J5: 50069 | K5: 50983 | L5: 49167
B6: Borrowings -
B7: Long term Borrowings | C7: 0 | D7: 0 | E7: 0 | F7: 0 | G7: 0 | H7: 0 | I7: 0 | J7: 0 | K7: 0 | L7: 0
B8: Short term Borrowings | C8: 177 | D8: 277 | E8: 0 | F8: 99 | G8: 0 | H8: 0 | I8: 0 | J8: 98 | K8: 13 | L8: 1
B9: Lease Liabilities | C9: 0 | D9: 0 | E9: 0 | F9: 0 | G9: 0 | H9: 0 | I9: 1043 | J9: 1121 | K9: 1471 | L9: 1647
B10: Other Borrowings | C10: 16212 | D10: 13662 | E10: 38029 | F10: 16933 | G10: 44877 | H10: 0 | I10: 0 | J10: 4425 | K10: 4577 | L10: 4738
B11: Other Liabilities -
B12: Non controlling int | C12: 20 | D12: 22 | E12: 20 | F12: 18 | G12: 17 | H12: 20 | I12: 26 | J12: 218 | K12: 205 | L12: 207
B13: Trade Payables | C13: 5685 | D13: 6186 | E13: 7170 | F13: 7206 | G13: 7535 | H13: 8802 | I13: 9068 | J13: 9574 | K13: 10486 | L13: 11315
B14: Advance from customers | C14: 45 | D14: 78 | E14: 62 | F14: 43 | G14: 158 | H14: 96 | I14: 119 | J14: 98 | K14: 91 | L14: 105
B15: Other liability items | C15: 2293 | D15: 2399 | E15: 3329 | F15: 3396 | G15: 4214 | H15: 12148 | I15: 11189 | J15: 11664 | K15: 15005 | L15: 17186
B16: Total Liabilities | C16: 14793 | D16: 15706 | E16: 17862 | F16: 18629 | G16: 20153 | H16: 68740 | I16: 70506 | J16: 73077 | K16: 78489 | L16: 79863
B18: Fixed Assets -
B19: Land | C19: 88 | D19: 89 | E19: 87 | F19: 86 | G19: 59 | H19: 477 | I19: 477 | J19: 609 | K19: 633 | L19: 628
B20: Building | C20: 931 | D20: 1210 | E20: 1343 | F20: 1527 | G20: 2044 | H20: 2602 | I20: 2788 | J20: 3101 | K20: 3590 | L20: 3833
B21: Plant Machinery | C21: 2370 | D21: 3270 | E21: 3691 | F21: 4092 | G21: 5001 | H21: 6097 | I21: 6566 | J21: 7612 | K21: 8946 | L21: 9900
B22: Railway Sidings | C22: 0 | D22: 0 | E22: 0 | F22: 0 | G22: 0 | H22: 0 | I22: 0 | J22: 0 | K22: 0 | L22: 0
B23: Equipments | C23: 41 | D23: 62 | E23: 74 | F23: 95 | G23: 139 | H23: 175 | I23: 181 | J23: 185 | K23: 206 | L23: 245
B24: Furniture n fittings | C24: 61 | D24: 66 | E24: 76 | F24: 88 | G24: 154 | H24: 156 | I24: 152 | J24: 161 | K24: 165 | L24: 174
B25: Vehicles | C25: 0 | D25: 0 | E25: 0 | F25: 0 | G25: 0 | H25: 0 | I25: 0 | J25: 33 | K25: 39 | L25: 102
B26: Intangible Assets | C26: 85 | D26: 455 | E26: 455 | F26: 511 | G26: 511 | H26: 45262 | I26: 45262 | J26: 45692 | K26: 45692 | L26: 45692
B27: Other fixed assets | C27: 19 | D27: 19 | E27: 26 | F27: 60 | G27: 71 | H27: 155 | I27: 152 | J27: 171 | K27: 180 | L27: 190
B28: Gross Block | C28: 3595 | D28: 5171 | E28: 5752 | F28: 6459 | G28: 7979 | H28: 54924 | I28: 55578 | J28: 57564 | K28: 59451 | L28: 60764
B29: Accumulated Depreciation | C29: 337 | D29: 752 | E29: 1224 | F29: 1744 | G29: 2500 | H29: 3481 | I29: 4105 | J29: 4886 | K29: 5707 | L29: 6429
B30: Net Block | C30: =C28-C29 -> 3258 | D30: =D28-D29 -> 4419 | E30: =E28-E29 -> 4528 | F30: =F28-F29 -> 4715 | G30: =G28-G29 -> 5479 | H30: =H28-H29 -> 51443 | I30: =I28-I29 -> 51473 | J30: =J28-J29 -> 52678 | ... L30: =L28-L29 -> 54335
B32: CWIP | C32: 408 | D32: 229 | E32: 461 | F32: 406 | G32: 597 | H32: 745 | I32: 1313 | J32: 1132 | K32: 1025 | L32: 1009
B33: Investments | C33: 2592 | D33: 3794 | E33: 2873 | F33: 2716 | G33: 1255 | H33: 2709 | I33: 3521 | J33: 2882 | K33: 4625 | L33: 3810
B35: Other Assets -
B36: Inventories | C36: 2726 | D36: 2541 | E36: 2513 | F36: 2574 | G36: 2767 | H36: 3579 | I36: 4096 | J36: 4251 | K36: 4022 | L36: 4415
B37: Trade receivables | C37: 1264 | D37: 1085 | E37: 1310 | F37: 1816 | G37: 1149 | H37: 1758 | I37: 2236 | J37: 3079 | K37: 2997 | L37: 3819
B38: Cash Equivalents | C38: 3009 | D38: 1828 | E38: 3485 | F38: 3757 | G38: 5113 | H38: 4471 | I38: 3846 | J38: 4678 | K38: 7559 | L38: 7554
B39: Loans n Advances | C39: 0 | D39: 71 | E39: 40 | F39: 26 | G39: 19 | H39: 78 | I39: 170 | J39: 188 | K39: 172 | L39: 242
B40: Other asset items | C40: 1536 | D40: 1739 | E40: 2652 | F40: 2619 | G40: 3774 | H40: 3957 | I40: 3851 | J40: 4189 | K40: 4345 | L40: 4679
B41: Total Assets | C41: 14793 | D41: 15706 | E41: 17862 | F41: 18629 | G41: 20153 | H41: 68740 | I41: 70506 | J41: 73077 | K41: 78489 | L41: 79863

Sheet DCF>

Sheet Intrinsic Growth
B3: ='Common Size Income Statement'!$B$3 -> HINDUSTAN UNILEVER LTD
B4: ='Common Size Income Statement'!$B$4 -> (HINDUNILVR | BSE Code: 500696)
B6: Intrinsic Growth
B8: Calculation of ROIC | G8: ='Raw FS'!H$2 -> 44256 | H8: ='Raw FS'!I$2 -> 44621 | I8: ='Raw FS'!J$2 -> 44986 | J8: ='Raw FS'!K$2 -> 45352 | K8: ='Raw FS'!L$2 -> 45717
B10: Current Assets
B11: ='Raw FS'!B36 -> Inventories | G11: ='Raw FS'!H36 -> 3579 | H11: ='Raw FS'!I36 -> 4096 | I11: ='Raw FS'!J36 -> 4251 | J11: ='Raw FS'!K36 -> 4022 | K11: ='Raw FS'!L36 -> 4415
B12: ='Raw FS'!B37 -> Trade receivables | G12: ='Raw FS'!H37 -> 1758 | H12: ='Raw FS'!I37 -> 2236 | I12: ='Raw FS'!J37 -> 3079 | J12: ='Raw FS'!K37 -> 2997 | K12: ='Raw FS'!L37 -> 3819
B13: ='Raw FS'!B39 -> Loans n Advances | G13: ='Raw FS'!H39 -> 78 | H13: ='Raw FS'!I39 -> 170 | I13: ='Raw FS'!J39 -> 188 | J13: ='Raw FS'!K39 -> 172 | K13: ='Raw FS'!L39 -> 242
B14: ='Raw FS'!B40 -> Other asset items | G14: ='Raw FS'!H40 -> 3957 | H14: ='Raw FS'!I40 -> 3851 | I14: ='Raw FS'!J40 -> 4189 | J14: ='Raw FS'!K40 -> 4345 | K14: ='Raw FS'!L40 -> 4679
B15: Total Current Assets | G15: =SUM(G11:G14) -> 9372 | H15: =SUM(H11:H14) -> 10353 | I15: =SUM(I11:I14) -> 11707 | J15: =SUM(J11:J14) -> 11536 | K15: =SUM(K11:K14) -> 13155
B17: Current Liabilities
B18: ='Raw FS'!B13 -> Trade Payables | G18: ='Raw FS'!H13 -> 8802 | H18: ='Raw FS'!I13 -> 9068 | I18: ='Raw FS'!J13 -> 9574 | J18: ='Raw FS'!K13 -> 10486 | K18: ='Raw FS'!L13 -> 11315
B19: Advance from Customers | G19: ='Raw FS'!H14 -> 96 | H19: ='Raw FS'!I14 -> 119 | I19: ='Raw FS'!J14 -> 98 | J19: ='Raw FS'!K14 -> 91 | K19: ='Raw FS'!L14 -> 105
B20: ='Raw FS'!B15 -> Other liability items | G20: ='Raw FS'!H15 -> 12148 | H20: ='Raw FS'!I15 -> 11189 | I20: ='Raw FS'!J15 -> 11664 | J20: ='Raw FS'!K15 -> 15005 | K20: ='Raw FS'!L15 -> 17186
B21: Total Current Liabilities | G21: =SUM(G18:G20) -> 21046 | H21: =SUM(H18:H20) -> 20376 | I21: =SUM(I18:I20) -> 21336 | J21: =SUM(J18:J20) -> 25582 | K21: =SUM(K18:K20) -> 28606
A23: # | B23: Net Working Capital | G23: =G15-G21 -> -11674 | H23: =H15-H21 -> -10023 | I23: =I15-I21 -> -9629 | J23: =J15-J21 -> -14046 | K23: =K15-K21 -> -15451
B25: Non - Current Assets
B26: ='Raw FS'!B19 -> Land | G26: ='Raw FS'!H19 -> 477 | H26: ='Raw FS'!I19 -> 477 | I26: ='Raw FS'!J19 -> 609 | J26: ='Raw FS'!K19 -> 633 | K26: ='Raw FS'!L19 -> 628
B27: ='Raw FS'!B20 -> Building | G27: ='Raw FS'!H20 -> 2602 | H27: ='Raw FS'!I20 -> 2788 | I27: ='Raw FS'!J20 -> 3101 | J27: ='Raw FS'!K20 -> 3590 | K27: ='Raw FS'!L20 -> 3833
B28: ='Raw FS'!B21 -> Plant Machinery | G28: ='Raw FS'!H21 -> 6097 | H28: ='Raw FS'!I21 -> 6566 | I28: ='Raw FS'!J21 -> 7612 | J28: ='Raw FS'!K21 -> 8946 | K28: ='Raw FS'!L21 -> 9900
B29: ='Raw FS'!B22 -> Railway Sidings | G29: ='Raw FS'!H22 -> 0 | H29: ='Raw FS'!I22 -> 0 | I29: ='Raw FS'!J22 -> 0 | J29: ='Raw FS'!K22 -> 0 | K29: ='Raw FS'!L22 -> 0
B30: ='Raw FS'!B23 -> Equipments | G30: ='Raw FS'!H23 -> 175 | H30: ='Raw FS'!I23 -> 181 | I30: ='Raw FS'!J23 -> 185 | J30: ='Raw FS'!K23 -> 206 | K30: ='Raw FS'!L23 -> 245
B31: ='Raw FS'!B24 -> Furniture n fittings | G31: ='Raw FS'!H24 -> 156 | H31: ='Raw FS'!I24 -> 152 | I31: ='Raw FS'!J24 -> 161 | J31: ='Raw FS'!K24 -> 165 | K31: ='Raw FS'!L24 -> 174
B32: ='Raw FS'!B25 -> Vehicles | G32: ='Raw FS'!H25 -> 0 | H32: ='Raw FS'!I25 -> 0 | I32: ='Raw FS'!J25 -> 33 | J32: ='Raw FS'!K25 -> 39 | K32: ='Raw FS'!L25 -> 102
B33: ='Raw FS'!B26 -> Intangible Assets | G33: ='Raw FS'!H26 -> 45262 | H33: ='Raw FS'!I26 -> 45262 | I33: ='Raw FS'!J26 -> 45692 | J33: ='Raw FS'!K26 -> 45692 | K33: ='Raw FS'!L26 -> 45692
B34: ='Raw FS'!B27 -> Other fixed assets | G34: ='Raw FS'!H27 -> 155 | H34: ='Raw FS'!I27 -> 152 | I34: ='Raw FS'!J27 -> 171 | J34: ='Raw FS'!K27 -> 180 | K34: ='Raw FS'!L27 -> 190
B36: Gross Block | G36: =SUM(G26:G34) -> 54924 | H36: =SUM(H26:H34) -> 55578 | I36: =SUM(I26:I34) -> 57564 | J36: =SUM(J26:J34) -> 59451 | K36: =SUM(K26:K34) -> 60764
B37: Accumulated Depriciation | G37: =-'Raw FS'!H29 -> -3481 | H37: =-'Raw FS'!I29 -> -4105 | I37: =-'Raw FS'!J29 -> -4886 | J37: =-'Raw FS'!K29 -> -5707 | K37: =-'Raw FS'!L29 -> -6429
A38: # | B38: Net Non Current Assets | G38: =SUM(G36:G37) -> 51443 | H38: =SUM(H36:H37) -> 51473 | I38: =SUM(I36:I37) -> 52678 | J38: =SUM(J36:J37) -> 53744 | K38: =SUM(K36:K37) -> 54335
A40: # | B40: Invested Capital | G40: =SUM(G38+G23) -> 39769 | H40: =SUM(H38+H23) -> 41450 | I40: =SUM(I38+I23) -> 43049 | J40: =SUM(J38+J23) -> 39698 | K40: =SUM(K38+K23) -> 38884
B41: EBIT | G41: =HistoricalFS!H24-HistoricalFS!H30 -> 10552 | H41: =HistoricalFS!I24-HistoricalFS!I30 -> 11766 | I41: =HistoricalFS!J24-HistoricalFS!J30 -> 13010 | J41: =HistoricalFS!K24-HistoricalFS!K30 -> 13443 | K41: =HistoricalFS!L24-HistoricalFS!L30 -> 13488
A43: # | B43: ROIC | G43: =G53/G40 -> 0.19899922 | H43: =H53/H40 -> 0.21289505 | I43: =I53/I40 -> 0.22666032 | J43: =J53/J40 -> 0.25397375 | K43: =K53/K40 -> 0.26015842
B46: Calculation of Reinvestment Rate | G46: ='Raw FS'!H$2 -> 44256 | H46: ='Raw FS'!I$2 -> 44621 | I46: ='Raw FS'!J$2 -> 44986 | J46: ='Raw FS'!K$2 -> 45352 | K46: ='Raw FS'!L$2 -> 45717
B48: Net Capex | G48: =-SUM('Cash Flow Data'!M15:M16) -> 4066 | H48: =-SUM('Cash Flow Data'!N15:N16) -> 1053 | I48: =-SUM('Cash Flow Data'!O15:O16) -> 1011 | J48: =-SUM('Cash Flow Data'!P15:P16) -> 1457 | K48: =-SUM('Cash Flow Data'!Q15:Q16) -> 1262
B49: Change in Working Capital | H49: =H23-G23 -> 1651 | I49: =I23-H23 -> 394 | J49: =J23-I23 -> -4417 | K49: =K23-J23 -> -1405
B51: EBIT | G51: =G41 -> 10552 | H51: =H41 -> 11766 | I51: =I41 -> 13010 | J51: =J41 -> 13443 | K51: =K41 -> 13488
B52: Marginal Tax Rate | G52: 0.25 | H52: 0.25 | I52: 0.25 | J52: 0.25 | K52: 0.25
B53: EBIT(1-T) | G53: =G51*(1-G52) -> 7914 | H53: =H51*(1-H52) -> 8824.5 | I53: =I51*(1-I52) -> 9757.5 | J53: =J51*(1-J52) -> 10082.25 | K53: =K51*(1-K52) -> 10116
B55: Reinvestment | H55: =SUM(H48:H49) -> 2704 | I55: =SUM(I48:I49) -> 1405 | J55: =SUM(J48:J49) -> -2960 | K55: =SUM(K48:K49) -> -143
B57: Reinvestment Rate | H57: =H55/H53 -> 0.30641963 | I57: =I55/I53 -> 0.1439918 | J57: =J55/J53 -> -0.29358526 | K57: =K55/K53 -> -0.014136022
J59: 4 Year Average | K59: =AVERAGE(H57:K57) -> 0.035672536
J60: 4 Year median | K60: =MEDIAN(H57:K57) -> 0.06492789
B62: Calculation of Growth Rate | G62: ='Raw FS'!H$2 -> 44256 | H62: ='Raw FS'!I$2 -> 44621 | I62: ='Raw FS'!J$2 -> 44986 | J62: ='Raw FS'!K$2 -> 45352 | K62: ='Raw FS'!L$2 -> 45717
B64: Reinvestment Rate | H64: =H57 -> 0.30641963 | I64: =I57 -> 0.1439918 | J64: =J57 -> -0.29358526 | K64: =K57 -> -0.014136022
B65: ROIC | H65: =H43 -> 0.21289505 | I65: =I43 -> 0.22666032 | J65: =J43 -> 0.25397375 | K65: =K43 -> 0.26015842
B67: Intrinsic Growth | H67: =H64*H65 -> 0.065235223 | I67: =I64*I65 -> 0.032637227 | J67: =J64*J65 -> -0.07456295 | K67: =K64*K65 -> -0.0036776052
J69: 4 Year Average | K69: =AVERAGE(H67:K67) -> 0.0049079738
J70: 4 Year median | K70: =MEDIAN(H67:K67) -> 0.014479811

Sheet Beta
B3: ='Common Size Income Statement'!B3 -> HINDUSTAN UNILEVER LTD
B4: ='Common Size Income Statement'!B4 -> (HINDUNILVR | BSE Code: 500696)
B6: Beta & Beta Drifting
B8: HUL Weekly Returns | F8: Nifty Returns | J8: Beta Drifting
B10: Date | C10: Closing Price | D10: Return | F10: Date | G10: Closing Price | H10: Return | N10: Beta 1 | O10: =SLOPE(D12:D115,H12:H115) -> 0.97863212
B11: 45383 | C11: 2395.45 | F11: 45383 | G11: 22345.6 | J11: Levered Beta | L11: =O10 -> 0.97863212 | N11: Beta 2 | O11: =_xlfn.COVARIANCE.S(D11:D115,H11:H115)/_xlfn.VAR.S(H11:H115) -> 0.97863212
B12: 45390 | C12: 2410.3 | D12: =(C12/C11)-1 -> 0.0061992528 | F12: 45390 | G12: 22480.3 | H12: =(G12/G11)-1 -> 0.0060280324 | J12: Raw Beta Weight | L12: 0.75
B13: 45397 | C13: 2388.75 | D13: =(C13/C12)-1 -> -0.0089407958 | F13: 45397 | G13: 22310.75 | H13: =(G13/G12)-1 -> -0.0075421591 | N13: Beta 3 | O13: =O33 -> 0.97863212
B14: 45404 | C14: 2425.6 | D14: =(C14/C13)-1 -> 0.015426478 | F14: 45404 | G14: 22650.6 | H14: =(G14/G13)-1 -> 0.015232567 | J14: Market Beta | L14: 1
B15: 45411 | C15: 2408.9 | D15: =(C15/C14)-1 -> -0.0068848945 | F15: 45411 | G15: 22580.9 | H15: =(G15/G14)-1 -> -0.0030771812 | J15: Market Beta Weight | L15: 0.25
B16: 45418 | C16: 2375.8 | D16: =(C16/C15)-1 -> -0.013740712 | F16: 45418 | G16: 22275.8 | H16: =(G16/G15)-1 -> -0.013511419 | N16: SUMMARY OUTPUT
B17: 45425 | C17: 2390.45 | D17: =(C17/C16)-1 -> 0.006166344 | F17: 45425 | G17: 22420.45 | H17: =(G17/G16)-1 -> 0.0064935939 | J17: Adjusted Beta | L17: =(L11*L12)+(L14*L15) -> 0.98397409
B18: 45432 | C18: 2405.3 | D18: =(C18/C17)-1 -> 0.0062122195 | F18: 45432 | G18: 22560.3 | H18: =(G18/G17)-1 -> 0.006237609 | N18: Regression Statistics
B19: 45439 | C19: 2380.6 | D19: =(C19/C18)-1 -> -0.010268989 | F19: 45439 | G19: 22340.6 | H19: =(G19/G18)-1 -> -0.0097383457 | N19: Multiple R | O19: 0.96796186
B20: 45446 | C20: 2445.75 | D20: =(C20/C19)-1 -> 0.02736705 | F20: 45446 | G20: 22945.75 | H20: =(G20/G19)-1 -> 0.027087455 | N20: R Square | O20: 0.93695017
B21: 45453 | C21: 2460.2 | D21: =(C21/C20)-1 -> 0.0059082081 | F21: 45453 | G21: 23120.2 | H21: =(G21/G20)-1 -> 0.0076027151 | N21: Adjusted R Square | O21: 0.93633203
B22: 45460 | C22: 2432.9 | D22: =(C22/C21)-1 -> -0.011096659 | F22: 45460 | G22: 22890.9 | H22: =(G22/G21)-1 -> -0.0099177343 | N22: Standard Error | O22: 0.0035369839
B23: 45467 | C23: 2446.35 | D23: =(C23/C22)-1 -> 0.0055283818 | F23: 45467 | G23: 23010.35 | H23: =(G23/G22)-1 -> 0.0052182308 | N23: Observations | O23: 104
B24: 45474 | C24: 2488.6 | D24: =(C24/C23)-1 -> 0.017270628 | F24: 45474 | G24: 23480.6 | H24: =(G24/G23)-1 -> 0.020436456
B25: 45481 | C25: 2520.25 | D25: =(C25/C24)-1 -> 0.012717994 | F25: 45481 | G25: 23820.25 | H25: =(G25/G24)-1 -> 0.014465133 | N25: ANOVA
B26: 45488 | C26: 2555.4 | D26: =(C26/C25)-1 -> 0.013947029 | F26: 45488 | G26: 24150.4 | H26: =(G26/G25)-1 -> 0.013860056 | O26: df | P26: SS | Q26: MS | R26: F | S26: Significance F
B27: 45495 | C27: 2595.75 | D27: =(C27/C26)-1 -> 0.015790092 | F27: 45495 | G27: 24595.75 | H27: =(G27/G26)-1 -> 0.018440688 | N27: Regression | O27: 1 | P27: 0.018962643 | Q27: 0.018962643 | R27: 1515.768 | S27: 4.9467262e-63
B28: 45502 | C28: 2550.9 | D28: =(C28/C27)-1 -> -0.017278243 | F28: 45502 | G28: 24250.9 | H28: =(G28/G27)-1 -> -0.014020715 | N28: Residual | O28: 102 | P28: 0.001276046 | Q28: 1.2510255e-05
B29: 45509 | C29: 2578.6 | D29: =(C29/C28)-1 -> 0.010858913 | F29: 45509 | G29: 24480.6 | H29: =(G29/G28)-1 -> 0.0094718134 | N29: Total | O29: 103 | P29: 0.020238689
B30: 45516 | C30: 2605.1 | D30: =(C30/C29)-1 -> 0.010276894 | F30: 45516 | G30: 24720.1 | H30: =(G30/G29)-1 -> 0.0097832569
B31: 45523 | C31: 2620.45 | D31: =(C31/C30)-1 -> 0.0058922882 | F31: 45523 | G31: 24920.45 | H31: =(G31/G30)-1 -> 0.0081047407 | O31: Coefficients | P31: Standard Error | Q31: t Stat | R31: P-value | S31: Lower 95% | T31: Upper 95% | U31: Lower 95.0% | V31: Upper 95.0%
B32: 45530 | C32: 2582.3 | D32: =(C32/C31)-1 -> -0.014558568 | F32: 45530 | G32: 24680.3 | H32: =(G32/G31)-1 -> -0.0096366639 | N32: Intercept | O32: -0.00086396818 | P32: 0.00034684013 | Q32: -2.4909695 | R32: 0.014352908 | S32: -0.0015519239 | T32: -0.00017601243 | U32: -0.0015519239 | V32: -0.00017601243
B33: 45537 | C33: 2595.8 | D33: =(C33/C32)-1 -> 0.0052278976 | F33: 45537 | G33: 24850.8 | H33: =(G33/G32)-1 -> 0.0069083439 | N33: X Variable 1 | O33: 0.97863212 | P33: 0.025136402 | Q33: 38.932865 | R33: 4.9467262e-63 | S33: 0.92877419 | T33: 1.0284901 | U33: 0.92877419 | V33: 1.0284901
B34: 45544 | C34: 2628.6 | D34: =(C34/C33)-1 -> 0.012635796 | F34: 45544 | G34: 25120.6 | H34: =(G34/G33)-1 -> 0.010856793
B35: 45551 | C35: 2655.9 | D35: =(C35/C34)-1 -> 0.010385757 | F35: 45551 | G35: 25355.9 | H35: =(G35/G34)-1 -> 0.0093668145
B36: 45558 | C36: 2685.4 | D36: =(C36/C35)-1 -> 0.011107346 | F36: 45558 | G36: 25585.4 | H36: =(G36/G35)-1 -> 0.0090511479
B37: 45565 | C37: 2598.75 | D37: =(C37/C36)-1 -> -0.032267074 | F37: 45565 | G37: 24980.75 | H37: =(G37/G36)-1 -> -0.023632619
B38: 45572 | C38: 2555.6 | D38: =(C38/C37)-1 -> -0.016604137 | F38: 45572 | G38: 24755.6 | H38: =(G38/G37)-1 -> -0.00901294
B39: 45579 | C39: 2538.45 | D39: =(C39/C38)-1 -> -0.0067107529 | F39: 45579 | G39: 24580.45 | H39: =(G39/G38)-1 -> -0.0070751668
B40: 45586 | C40: 2505.3 | D40: =(C40/C39)-1 -> -0.01305915 | F40: 45586 | G40: 24305.3 | H40: =(G40/G39)-1 -> -0.011193855
B41: 45593 | C41: 2472.15 | D41: =(C41/C40)-1 -> -0.013231948 | F41: 45593 | G41: 24020.15 | H41: =(G41/G40)-1 -> -0.011732009
B42: 45600 | C42: 2438.9 | D42: =(C42/C41)-1 -> -0.013449831 | F42: 45600 | G42: 23780.9 | H42: =(G42/G41)-1 -> -0.0099603874
B43: 45607 | C43: 2405.7 | D43: =(C43/C42)-1 -> -0.013612694 | F43: 45607 | G43: 23505.7 | H43: =(G43/G42)-1 -> -0.011572312
B44: 45614 | C44: 2422.5 | D44: =(C44/C43)-1 -> 0.0069834144 | F44: 45614 | G44: 23680.5 | H44: =(G44/G43)-1 -> 0.0074364941
B45: 45621 | C45: 2455.6 | D45: =(C45/C44)-1 -> 0.013663571 | F45: 45621 | G45: 23955.6 | H45: =(G45/G44)-1 -> 0.011617153
... B115: 46111 | C115: 2143.9 | D115: =(C115/C114)-1 -> -0.0028372093 | F115: 46111 | G115: 21880.9 | H115: =(G115/G114)-1 -> -0.0031480638

Sheet Wacc
B3: ='Common Size Income Statement'!B3 -> HINDUSTAN UNILEVER LTD
B4: ='Common Size Income Statement'!B4 -> (HINDUNILVR | BSE Code: 500696)
B6: Weighted Average Cost of Capital
B8: All Figures are in INR Unless Stated Otherwise
B10: Peer Comps
G11: Debt / | H11: Debt/ | I11: Levered | J11: Unlevered
B12: Name Of the company | C12: Country | D12: Total Debt | E12: Total Equity | F12: Tax Rate 1 | G12: Equity | H12: Capital | I12: Beta 2 | J12: Beta 3
B14: Hindustand Uniliver | C14: India | D14: 1775 | E14: 496227 | F14: 0.3 | G14: =D14/E14 -> 0.003576992 | H14: =D14/(E14+D14) -> 0.0035642427 | I14: ='Comps Data Beta'!AB8 -> 0.82152208 | J14: =I14/(1+(1-F14)*G14) -> 0.81947021
B15: ITC | C15: India | D15: 363 | E15: 374131 | F15: 0.3 | G15: =D15/E15 -> 0.00097024839 | H15: =D15/(E15+D15) -> 0.00096930792 | I15: ='[1]Comps- Data Beta'!T8 -> 1.3741249 | J15: =I15/(1+(1-F15)*G15) -> 1.3731922
B16: Godrej | C16: India | D16: 4113 | E16: 105174 | F16: 0.3 | G16: =D16/E16 -> 0.039106623 | H16: =D16/(E16+D16) -> 0.037634851 | I16: ='[1]Comps- Data Beta'!T18 -> 0.74564327 | J16: =I16/(1+(1-F16)*G16) -> 0.72577543
B17: Hindustan Foods | C17: India | D17: 901 | E17: 5825 | F17: 0.3 | G17: =D17/E17 -> 0.15467811 | H17: =D17/(E17+D17) -> 0.13395778 | I17: ='[1]Comps- Data Beta'!T28 -> 1.7045001 | J17: =I17/(1+(1-F17)*G17) -> 1.5379762
B18: Dabur | C18: India | D18: 1301 | E18: 73395 | F18: 0.3 | G18: =D18/E18 -> 0.017726003 | H18: =D18/(E18+D18) -> 0.017417265 | I18: ='[1]Comps- Data Beta'!T38 -> 0.74922983 | J18: =I18/(1+(1-F18)*G18) -> 0.74004718
E20: Average | F20: =AVERAGE(F14:F18) -> 0.3 | G20: =AVERAGE(G14:G18) -> 0.043211596 | H20: =AVERAGE(H14:H18) -> 0.038708688 | I20: =AVERAGE(I14:I18) -> 1.079004 | J20: =AVERAGE(J14:J18) -> 1.0392922
E21: Median | F21: =MEDIAN(F14:F18) -> 0.3 | G21: =MEDIAN(G14:G18) -> 0.017726003 | H21: =MEDIAN(H14:H18) -> 0.017417265 | I21: =MEDIAN(I14:I18) -> 0.82152208 | J21: =MEDIAN(J14:J18) -> 0.81947021
B24: Cost of Debt | H24: Cost of Equity
B26: Pre-Tax Cost of Debt | E26: =69/1609.91 -> 0.042859539 | H26: Risk Free Rate | J26: 0.0666
B27: Tax Rate | E27: =F20 -> 0.3 | H27: Equity Risk Premium | J27: =Rm!F8-Wacc!J26 -> 0.097692308
B28: Post-Tax Cost of Debt | E28: =E26*(1-E27) -> 0.030001677 | H28: Levered Beta 4 | J28: =J37 -> 0.82963837
H29: Cost of Equity | J29: =J26+(J27*J28) -> 0.14764929
B32: Capital Structure | H32: Levered Beta
D34: Current | E34: Target | H34: Comps Median Unlevered Beta | J34: =J21 -> 0.81947021
B35: Total Debt | C35: =D14 -> 1775 | D35: =C35/$C$37 -> 0.0035642427 | E35: =H21 -> 0.017417265 | H35: Target Debt/Equity | J35: =E39 -> 0.017726003
B36: Market Capitalization | C36: =E14 -> 496227 | D36: =C36/$C$37 -> 0.99643576 | E36: =E37-E35 -> 0.98258274 | H36: Tax Rate | J36: =E27 -> 0.3
B37: Total Capital | C37: =SUM(C35:C36) -> 498002 | D37: =SUM(D35:D36) -> 1 | E37: =D37 -> 1 | H37: Levered Beta | J37: =J34*(1+(1-J36)*J35) -> 0.82963837
B39: Debt / Equity | D39: =D35/D36 -> 0.003576992 | E39: =E35/E36 -> 0.017726003 | H39: Weighted Average Cost of Capital
B41: Notes: | H41: Cost of Equity | J41: =J29 -> 0.14764929
B42: 1. Tax Rate considered as Marginal Tax Rate for the country | H42: Equity Weight | J42: =E36 -> 0.98258274
B43: 2. Levered Beta is based on 5 year monthly data
B44: 3. Unlevered Beta = Levered Beta/(1+(1-Tax Rate) x Debt/Equity) | H44: Cost of debt | J44: =E28 -> 0.030001677
B45: 4. Levered Beta = Unlevered Beta*(1+(1-Tax Rate) x Debt/Equity) | H45: Debt Weight | J45: =E35 -> 0.017417265
H47: WACC | J47: =(J41*J42)+(J44*J45) -> 0.14560019

Sheet DCF
B3: ='Intrinsic Growth'!B3 -> HINDUSTAN UNILEVER LTD
B4: ='Intrinsic Growth'!B4 -> (HINDUNILVR | BSE Code: 500696)
B6: Free Cash Flow to the Firm
B8: Calculation of PV of FCFF | F8: ='Intrinsic Growth'!K8 -> 45717 | G8: =F8+366 -> 46083 | H8: =G8+366 -> 46449 | I8: =H8+366 -> 46815 | J8: =I8+366 -> 47181 | K8: =J8+366 -> 47547 | L8: =K8+366 -> 47913
B10: EBIT | F10: =HistoricalFS!L24-HistoricalFS!L30 -> 13488 | G10: =F10*(1+$D$20) -> 13683.304 | H10: =G10*(1+$D$20) -> 13881.435 | I10: =H10*(1+$D$20) -> 14082.436 | J10: =I10*(1+$D$20) -> 14286.347 | K10: =J10*(1+$D$20) -> 14493.211 | L10: =K10*(1+$D$20) -> 14703.069
B11: Tax Rate | F11: 0.25 | G11: =F11 -> 0.25 | H11: =G11 -> 0.25 | I11: =H11 -> 0.25 | J11: =I11 -> 0.25 | K11: =J11 -> 0.25 | L11: =K11 -> 0.25
B12: EBIT(1-T) | F12: =F10*(1-F11) -> 10116 | G12: =G10*(1-G11) -> 10262.478 | H12: =H10*(1-H11) -> 10411.077 | I12: =I10*(1-I11) -> 10561.827 | J12: =J10*(1-J11) -> 10714.76 | K12: =K10*(1-K11) -> 10869.908 | L12: =L10*(1-L11) -> 11027.302
B13: Less: Reinvestment Rate | F13: ='Intrinsic Growth'!K60 -> 0.06492789 | G13: =F13 -> 0.06492789 | H13: =G13 -> 0.06492789 | I13: =H13 -> 0.06492789 | J13: =I13 -> 0.06492789 | K13: =J13 -> 0.06492789 | L13: =K13 -> 0.06492789
B14: Free Cash Flow to Firm | F14: =F12*(1-F13) -> 9459.1895 | G14: =G12*(1-G13) -> 9596.1567 | H14: =H12*(1-H13) -> 9735.1073 | I14: =I12*(1-I13) -> 9876.0698 | J14: =J12*(1-J13) -> 10019.073 | K14: =K12*(1-K13) -> 10164.148 | L14: =L12*(1-L13) -> 10311.323
B15: Mid Year Convention | G15: 0.5 | H15: =G15+1 -> 1.5 | I15: =H15+1 -> 2.5 | J15: =I15+1 -> 3.5 | K15: =J15+1 -> 4.5 | L15: =K15+1 -> 5.5
B16: Discounting Factor | G16: =1/(1+$D$22)^G15 -> 0.93429379 | H16: =1/(1+$D$22)^H15 -> 0.81554961 | I16: =1/(1+$D$22)^I15 -> 0.71189724 | J16: =1/(1+$D$22)^J15 -> 0.62141858 | K16: =1/(1+$D$22)^K15 -> 0.54243931 | L16: =1/(1+$D$22)^L15 -> 0.47349793
B18: PV of FCFF | G18: =G14*G16 -> 8965.6297 | H18: =H14*H16 -> 7939.463 | I18: =I14*I16 -> 7030.7468 | J18: =J14*J16 -> 6226.0384 | K18: =K14*K16 -> 5513.4333 | L18: =L14*L16 -> 4882.3899
B20: Expected Growth | D20: ='Intrinsic Growth'!K70 -> 0.014479811
B21: Terminal Growth | D21: 0.05
B22: WACC | D22: =Wacc!J47 -> 0.14560019
B24: Calculation of Terminal Value | G24: Sensitivity Analysis
G25: =D36 -> 94182.172 | H25: 0.13 | I25: 0.1456 | J25: 0.16 | K25: 0.18 | L25: 0.2
B26: FCFF(n+1) | D26: =L14*(1+D21) -> 10826.889 | G26: 0.03 | H26: 91822.795 | I26: 84904.668 | J26: 79992.389 | K26: 74734.43 | L26: 70713.639
B27: WACC | D27: =D22 -> 0.14560019 | G27: 0.04 | H27: 97518.917 | I27: 89104.192 | J27: 83278.613 | K27: 77175.625 | L27: 72598.385
B28: Terminal Growth Rate | D28: =D21 -> 0.05 | G28: 0.05 | H28: 104639.07 | I28: 94182.276 | J28: 87162.332 | K28: 79992.389 | L28: 74734.43
G29: 0.06 | H29: 113793.55 | I29: 100446.83 | J29: 91822.795 | K29: 83278.613 | L29: 77175.625
B30: Terminal Value | D30: =D26/(D27-D28) -> 113251.75 | G30: 0.07 | H30: 125999.52 | I30: 108368.67 | J30: 97518.917 | K30: 87162.332 | L30: 79992.389
B32: Calculation of Equity Value Per Share
B34: PV of FCFF | D34: =SUM(G18:L18) -> 40557.701
B35: PV of Terminal Value | D35: =D30*L16 -> 53624.47
B36: Value of Operating Assets | D36: =SUM(D34:D35) -> 94182.172
B38: Add: Cash | D38: ='Data Sheet'!K69 -> 7554
B39: Less: Debt | D39: =SUM('Raw FS'!L7:L9) -> 1648
B40: Value of Equity | D40: =D36+D38-D39 -> 100088.17
B41: No. of Shares | D41: ='Data Sheet'!B6 -> 234.95918
B43: Equity Value Per share | D43: =D40/D41 -> 425.98111
B45: Share Price | D45: 2110
B46: Discount/Premium | D46: =(D45/D43) -> 4.9532713

Sheet Comps Data Beta
B7: ITC Weekly Returns | F7: Godrej Weekly Returns | J7: Hindustan Foods Weekly Returns | N7: Dabur Weekly Returns | R7: Nifty Returns | V7: ITC Beta Drifting | Z7: ITC Beta Calculation
B8: Date | C8: Closing Price | D8: Return | F8: Date | G8: Closing Price | H8: Return | J8: Date | K8: Closing Price | L8: Return | N8: Date | O8: Closing Price | P8: Return | R8: Date | S8: Closing Price | T8: Return | V8: Levered Beta | X8: =AB8 -> 0.82152208 | Z8: Beta 1 | AB8: =SLOPE(D10:D113,T10:T113) -> 0.82152208
B9: 45383 | C9: 382.74 | F9: 45383 | G9: 1186.45 | J9: 45383 | K9: 525.4 | N9: 45383 | O9: 520.45 | R9: 45383 | S9: 22345.6 | V9: Raw Beta Weight | X9: 0.75 | Z9: Beta 2 | AB9: =_xlfn.COVARIANCE.S(D9:D113,T9:T113)/_xlfn.VAR.S(T9:T113) -> 0.82152208
B10: 45390 | C10: 385.02 | D10: =(C10/C9)-1 -> 0.0059570466 | F10: 45390 | G10: 1201.32 | H10: =(G10/G9)-1 -> 0.012533187 | J10: 45390 | K10: 532.1 | L10: =(K10/K9)-1 -> 0.012752189 | N10: 45390 | O10: 525.3 | P10: =(O10/O9)-1 -> 0.0093188587 | R10: 45390 | S10: 22480.3 | T10: =(S10/S9)-1 -> 0.0060280324
B11: 45397 | C11: 380.23 | D11: =(C11/C10)-1 -> -0.012440912 | F11: 45397 | G11: 1194.87 | H11: =(G11/G10)-1 -> -0.005369094 | J11: 45397 | K11: 528.75 | L11: =(K11/K10)-1 -> -0.0062958091 | N11: 45397 | O11: 518.75 | P11: =(O11/O10)-1 -> -0.012469065 | R11: 45397 | S11: 22310.75 | T11: =(S11/S10)-1 -> -0.0075421591 | V11: Market Beta | X11: 1 | Z11: Beta 3 | AB11: Can be calculated using data analysis Regression
B12: 45404 | C12: 393.89 | D12: =(C12/C11)-1 -> 0.035925624 | F12: 45404 | G12: 1210.55 | H12: =(G12/G11)-1 -> 0.013122766 | J12: 45404 | K12: 535.6 | L12: =(K12/K11)-1 -> 0.012955083 | N12: 45404 | O12: 532.6 | P12: =(O12/O11)-1 -> 0.026698795 | R12: 45404 | S12: 22650.6 | T12: =(S12/S11)-1 -> 0.015232567 | V12: Market Beta Weight | X12: 0.25
B13: 45411 | C13: 390.71 | D13: =(C13/C12)-1 -> -0.00807332 | F13: 45411 | G13: 1203.1 | H13: =(G13/G12)-1 -> -0.0061542274 | J13: 45411 | K13: 530.9 | L13: =(K13/K12)-1 -> -0.0087752054 | N13: 45411 | O13: 528.9 | P13: =(O13/O12)-1 -> -0.0069470522 | R13: 45411 | S13: 22580.9 | T13: =(S13/S12)-1 -> -0.0030771812
B14: 45418 | C14: 387.93 | D14: =(C14/C13)-1 -> -0.0071152517 | F14: 45418 | G14: 1189.75 | H14: =(G14/G13)-1 -> -0.011096334 | J14: 45418 | K14: 522.8 | L14: =(K14/K13)-1 -> -0.015257111 | N14: 45418 | O14: 515.8 | P14: =(O14/O13)-1 -> -0.024768387 | R14: 45418 | S14: 22275.8 | T14: =(S14/S13)-1 -> -0.013511419 | V14: Adjusted Beta | X14: =(X8*X9)+(X11*X12) -> 0.86614156
B15: 45425 | C15: 390.89 | D15: =(C15/C14)-1 -> 0.0076302426 | F15: 45425 | G15: 1198.2 | H15: =(G15/G14)-1 -> 0.0071023324 | J15: 45425 | K15: 526.45 | L15: =(K15/K14)-1 -> 0.0069816373 | N15: 45425 | O15: 520.45 | P15: =(O15/O14)-1 -> 0.0090151221 | R15: 45425 | S15: 22420.45 | T15: =(S15/S14)-1 -> 0.0064935939
B16: 45432 | C16: 390.48 | D16: =(C16/C15)-1 -> -0.0010488884 | F16: 45432 | G16: 1205.6 | H16: =(G16/G15)-1 -> 0.0061759306 | J16: 45432 | K16: 529.3 | L16: =(K16/K15)-1 -> 0.0054136195 | N16: 45432 | O16: 525.3 | P16: =(O16/O15)-1 -> 0.0093188587 | R16: 45432 | S16: 22560.3 | T16: =(S16/S15)-1 -> 0.006237609 | V16: Godrej Beta Drifting | Z16: Godrej Beta Calculation
B17: 45439 | C17: 381.76 | D17: =(C17/C16)-1 -> -0.022331489 | F17: 45439 | G17: 1192.3 | H17: =(G17/G16)-1 -> -0.011031851 | J17: 45439 | K17: 523.6 | L17: =(K17/K16)-1 -> -0.01076894 | N17: 45439 | O17: 518.6 | P17: =(O17/O16)-1 -> -0.012754616 | R17: 45439 | S17: 22340.6 | T17: =(S17/S16)-1 -> -0.0097383457 | V17: Levered Beta | X17: =AB17 -> 0.47834663 | Z17: Beta 1 | AB17: =SLOPE(H10:H113,T10:T113) -> 0.47834663
B18: 45446 | C18: 393.12 | D18: =(C18/C17)-1 -> 0.029756915 | F18: 45446 | G18: 1215.8 | H18: =(G18/G17)-1 -> 0.019709805 | J18: 45446 | K18: 540.75 | L18: =(K18/K17)-1 -> 0.032754011 | N18: 45446 | O18: 535.75 | P18: =(O18/O17)-1 -> 0.033069803 | R18: 45446 | S18: 22945.75 | T18: =(S18/S17)-1 -> 0.027087455 | V18: Raw Beta weight | X18: 0.75 | Z18: Beta2 | AB18: =_xlfn.COVARIANCE.S(H9:H113,T9:T113)/_xlfn.VAR.S(T9:T113) -> 0.47834663
B19: 45453 | C19: 393.08 | D19: =(C19/C18)-1 -> -0.0001017501 | F19: 45453 | G19: 1220.45 | H19: =(G19/G18)-1 -> 0.0038246422 | J19: 45453 | K19: 545.2 | L19: =(K19/K18)-1 -> 0.0082293111 | N19: 45453 | O19: 540.2 | P19: =(O19/O18)-1 -> 0.0083061129 | R19: 45453 | S19: 23120.2 | T19: =(S19/S18)-1 -> 0.0076027151
B20: 45460 | C20: 382.55 | D20: =(C20/C19)-1 -> -0.02678844 | F20: 45460 | G20: 1208.9 | H20: =(G20/G19)-1 -> -0.0094637224 | J20: 45460 | K20: 538.9 | L20: =(K20/K19)-1 -> -0.011555393 | N20: 45460 | O20: 532.9 | P20: =(O20/O19)-1 -> -0.013513514 | R20: 45460 | S20: 22890.9 | T20: =(S20/S19)-1 -> -0.0099177343 | V20: Market Beta | X20: 1 | Z20: Beta 3 | AB20: Can be calculated using data analysis Regression
B21: 45467 | C21: 387.38 | D21: =(C21/C20)-1 -> 0.012625801 | F21: 45467 | G21: 1212.35 | H21: =(G21/G20)-1 -> 0.0028538341 | J21: 45467 | K21: 542.35 | L21: =(K21/K20)-1 -> 0.0064019299 | N21: 45467 | O21: 536.35 | P21: =(O21/O20)-1 -> 0.0064740101 | R21: 45467 | S21: 23010.35 | T21: =(S21/S20)-1 -> 0.0052182308 | V21: Market Beta weight | X21: 0.25
B22: 45474 | C22: 395.36 | D22: =(C22/C21)-1 -> 0.020599928 | F22: 45474 | G22: 1235.6 | H22: =(G22/G21)-1 -> 0.01917763 | J22: 45474 | K22: 555.6 | L22: =(K22/K21)-1 -> 0.024430718 | N22: 45474 | O22: 548.6 | P22: =(O22/O21)-1 -> 0.022839564 | R22: 45474 | S22: 23480.6 | T22: =(S22/S21)-1 -> 0.020436456
B23: 45481 | C23: 418.51 | D23: =(C23/C22)-1 -> 0.058554229 | F23: 45481 | G23: 1250.25 | H23: =(G23/G22)-1 -> 0.011856588 | J23: 45481 | K23: 568.25 | L23: =(K23/K22)-1 -> 0.022768179 | N23: 45481 | O23: 560.25 | P23: =(O23/O22)-1 -> 0.021235873 | R23: 45481 | S23: 23820.25 | T23: =(S23/S22)-1 -> 0.014465133 | V23: Adjusted Beta | X23: =(X17*X18)+(X20*X21) -> 0.60875997
B24: 45488 | C24: 432.64 | D24: =(C24/C23)-1 -> 0.033762634 | F24: 45488 | G24: 1268.4 | H24: =(G24/G23)-1 -> 0.014517097 | J24: 45488 | K24: 580.4 | L24: =(K24/K23)-1 -> 0.021381434 | N24: 45488 | O24: 572.4 | P24: =(O24/O23)-1 -> 0.021686747 | R24: 45488 | S24: 24150.4 | T24: =(S24/S23)-1 -> 0.013860056
B25: 45495 | C25: 457.85 | D25: =(C25/C24)-1 -> 0.058270155 | F25: 45495 | G25: 1285.75 | H25: =(G25/G24)-1 -> 0.01367865 | J25: 45495 | K25: 595.75 | L25: =(K25/K24)-1 -> 0.026447278 | N25: 45495 | O25: 585.75 | P25: =(O25/O24)-1 -> 0.023322851 | R25: 45495 | S25: 24595.75 | T25: =(S25/S24)-1 -> 0.018440688 | V25: Hindustan Foods Beta Drifting | Z25: Hindustan Foods Beta Calculation
B26: 45502 | C26: 445.91 | D26: =(C26/C25)-1 -> -0.02607841 | F26: 45502 | G26: 1272.9 | H26: =(G26/G25)-1 -> -0.0099941668 | J26: 45502 | K26: 582.9 | L26: =(K26/K25)-1 -> -0.02156945 | N26: 45502 | O26: 570.9 | P26: =(O26/O25)-1 -> -0.025352113 | R26: 45502 | S26: 24250.9 | T26: =(S26/S25)-1 -> -0.014020715 | V26: Levered Beta | X26: =AB26 -> 1.0084319 | Z26: Beta 1 | AB26: =SLOPE(L10:L113,T10:T113) -> 1.0084319
B27: 45509 | C27: 452.11 | D27: =(C27/C26)-1 -> 0.013904151 | F27: 45509 | G27: 1280.6 | H27: =(G27/G26)-1 -> 0.006049179 | J27: 45509 | K27: 590.6 | L27: =(K27/K26)-1 -> 0.013209813 | N27: 45509 | O27: 578.6 | P27: =(O27/O26)-1 -> 0.013487476 | R27: 45509 | S27: 24480.6 | T27: =(S27/S26)-1 -> 0.0094718134 | V27: Raw Beta weight | X27: 0.75 | Z27: Beta 2 | AB27: =_xlfn.COVARIANCE.S(L9:L113,T9:T113)/_xlfn.VAR.S(T9:T113) -> 1.0084319
B28: 45516 | C28: 458.26 | D28: =(C28/C27)-1 -> 0.013602884 | F28: 45516 | G28: 1295.1 | H28: =(G28/G27)-1 -> 0.011322817 | J28: 45516 | K28: 602.1 | L28: =(K28/K27)-1 -> 0.019471724 | N28: 45516 | O28: 590.1 | P28: =(O28/O27)-1 -> 0.019875562 | R28: 45516 | S28: 24720.1 | T28: =(S28/S27)-1 -> 0.0097832569
B29: 45523 | C29: 461.14 | D29: =(C29/C28)-1 -> 0.0062846419 | F29: 45523 | G29: 1302.45 | H29: =(G29/G28)-1 -> 0.0056752374 | J29: 45523 | K29: 608.45 | L29: =(K29/K28)-1 -> 0.010546421 | N29: 45523 | O29: 595.45 | P29: =(O29/O28)-1 -> 0.00906626 | R29: 45523 | S29: 24920.45 | T29: =(S29/S28)-1 -> 0.0081047407 | V29: Market Beta | X29: 1 | Z29: Beta 3 | AB29: Can be calculated using data analysis Regression
B30: 45530 | C30: 457.58 | D30: =(C30/C29)-1 -> -0.0077199983 | F30: 45530 | G30: 1290.3 | H30: =(G30/G29)-1 -> -0.0093285731 | J30: 45530 | K30: 595.3 | L30: =(K30/K29)-1 -> -0.021612294 | N30: 45530 | O30: 582.3 | P30: =(O30/O29)-1 -> -0.022084138 | R30: 45530 | S30: 24680.3 | T30: =(S30/S29)-1 -> -0.0096366639 | V30: Market Beta weight | X30: 0.25
B31: 45537 | C31: 457.4 | D31: =(C31/C30)-1 -> -0.00039337384 | F31: 45537 | G31: 1305.8 | H31: =(G31/G30)-1 -> 0.01201271 | J31: 45537 | K31: 602.8 | L31: =(K31/K30)-1 -> 0.01259869 | N31: 45537 | O31: 590.8 | P31: =(O31/O30)-1 -> 0.014597287 | R31: 45537 | S31: 24850.8 | T31: =(S31/S30)-1 -> 0.0069083439
B32: 45544 | C32: 468.47 | D32: =(C32/C31)-1 -> 0.024202011 | F32: 45544 | G32: 1318.6 | H32: =(G32/G31)-1 -> 0.00980242 | J32: 45544 | K32: 610.6 | L32: =(K32/K31)-1 -> 0.012939615 | N32: 45544 | O32: 602.6 | P32: =(O32/O31)-1 -> 0.019972918 | R32: 45544 | S32: 25120.6 | T32: =(S32/S31)-1 -> 0.010856793 | V32: Adjusted Beta | X32: =(X26*X27)+(X29*X30) -> 1.0063239
B33: 45551 | C33: 468.98 | D33: =(C33/C32)-1 -> 0.0010886503 | F33: 45551 | G33: 1325.9 | H33: =(G33/G32)-1 -> 0.0055361747 | J33: 45551 | K33: 618.9 | L33: =(K33/K32)-1 -> 0.013593187 | N33: 45551 | O33: 610.9 | P33: =(O33/O32)-1 -> 0.013773648 | R33: 45551 | S33: 25355.9 | T33: =(S33/S32)-1 -> 0.0093668145
B34: 45558 | C34: 476.54 | D34: =(C34/C33)-1 -> 0.01612009 | F34: 45558 | G34: 1332.4 | H34: =(G34/G33)-1 -> 0.0049023305 | J34: 45558 | K34: 625.4 | L34: =(K34/K33)-1 -> 0.010502504 | N34: 45558 | O34: 615.4 | P34: =(O34/O33)-1 -> 0.007366181 | R34: 45558 | S34: 25585.4 | T34: =(S34/S33)-1 -> 0.0090511479 | V34: Dabur Beta Drifting | Z34: Dabur Beta Calculation
B35: 45565 | C35: 459.08 | D35: =(C35/C34)-1 -> -0.036639107 | F35: 45565 | G35: 1308.75 | H35: =(G35/G34)-1 -> -0.017749925 | J35: 45565 | K35: 598.75 | L35: =(K35/K34)-1 -> -0.042612728 | N35: 45565 | O35: 588.75 | P35: =(O35/O34)-1 -> -0.043305167 | R35: 45565 | S35: 24980.75 | T35: =(S35/S34)-1 -> -0.023632619 | V35: Levered Beta | X35: =AB36 -> 1.273097 | Z35: Beta 1 | AB35: =SLOPE(P10:P113,T10:T113) -> 1.273097
B36: 45572 | C36: 445.09 | D36: =(C36/C35)-1 -> -0.030473991 | F36: 45572 | G36: 1295.6 | H36: =(G36/G35)-1 -> -0.010047755 | J36: 45572 | K36: 585.6 | L36: =(K36/K35)-1 -> -0.021962422 | N36: 45572 | O36: 575.6 | P36: =(O36/O35)-1 -> -0.022335456 | R36: 45572 | S36: 24755.6 | T36: =(S36/S35)-1 -> -0.00901294 | V36: Raw Beta weight | X36: 0.75 | Z36: Beta 2 | AB36: =_xlfn.COVARIANCE.S(P9:P113,T9:T113)/_xlfn.VAR.S(T9:T113) -> 1.273097
B37: 45579 | C37: 443.72 | D37: =(C37/C36)-1 -> -0.0030780292 | F37: 45579 | G37: 1288.45 | H37: =(G37/G36)-1 -> -0.0055186786 | J37: 45579 | K37: 578.45 | L37: =(K37/K36)-1 -> -0.012209699 | N37: 45579 | O37: 568.45 | P37: =(O37/O36)-1 -> -0.012421821 | R37: 45579 | S37: 24580.45 | T37: =(S37/S36)-1 -> -0.0070751668
B38: 45586 | C38: 439.71 | D38: =(C38/C37)-1 -> -0.0090372307 | F38: 45586 | G38: 1275.3 | H38: =(G38/G37)-1 -> -0.010206062 | J38: 45586 | K38: 565.3 | L38: =(K38/K37)-1 -> -0.022733166 | N38: 45586 | O38: 555.3 | P38: =(O38/O37)-1 -> -0.023133081 | R38: 45586 | S38: 24305.3 | T38: =(S38/S37)-1 -> -0.011193855 | V38: Market Beta | X38: 1 | Z38: Beta 3 | AB38: Can be calculated using data analysis Regression
B39: 45593 | C39: 447 | D39: =(C39/C38)-1 -> 0.016579109 | F39: 45593 | G39: 1262.15 | H39: =(G39/G38)-1 -> -0.010311299 | J39: 45593 | K39: 552.15 | L39: =(K39/K38)-1 -> -0.023261985 | N39: 45593 | O39: 542.15 | P39: =(O39/O38)-1 -> -0.023680893 | R39: 45593 | S39: 24020.15 | T39: =(S39/S38)-1 -> -0.011732009 | V39: Market Beta weight | X39: 0.25
B40: 45600 | C40: 435.84 | D40: =(C40/C39)-1 -> -0.024966443 | F40: 45600 | G40: 1248.9 | H40: =(G40/G39)-1 -> -0.01049796 | J40: 45600 | K40: 538.9 | L40: =(K40/K39)-1 -> -0.023997102 | N40: 45600 | O40: 528.9 | P40: =(O40/O39)-1 -> -0.024439731 | R40: 45600 | S40: 23780.9 | T40: =(S40/S39)-1 -> -0.0099603874
B41: 45607 | C41: 424.8 | D41: =(C41/C40)-1 -> -0.025330396 | F41: 45607 | G41: 1235.7 | H41: =(G41/G40)-1 -> -0.010569301 | J41: 45607 | K41: 525.7 | L41: =(K41/K40)-1 -> -0.02449434 | N41: 45607 | O41: 515.7 | P41: =(O41/O40)-1 -> -0.024957459 | R41: 45607 | S41: 23505.7 | T41: =(S41/S40)-1 -> -0.011572312 | V41: Adjusted Beta | X41: =(X35*X36)+(X38*X39) -> 1.2048227
B42: 45614 | C42: 432.74 | D42: =(C42/C41)-1 -> 0.018691149 | F42: 45614 | G42: 1242.5 | H42: =(G42/G41)-1 -> 0.0055029538 | J42: 45614 | K42: 532.5 | L42: =(K42/K41)-1 -> 0.012935134 | N42: 45614 | O42: 522.5 | P42: =(O42/O41)-1 -> 0.013185961 | R42: 45614 | S42: 23680.5 | T42: =(S42/S41)-1 -> 0.0074364941
B43: 45621 | C43: 434.65 | D43: =(C43/C42)-1 -> 0.0044137357 | F43: 45621 | G43: 1255.6 | H43: =(G43/G42)-1 -> 0.01054326 | J43: 45621 | K43: 545.6 | L43: =(K43/K42)-1 -> 0.024600939 | N43: 45621 | O43: 535.6 | P43: =(O43/O42)-1 -> 0.02507177 | R43: 45621 | S43: 23955.6 | T43: =(S43/S42)-1 -> 0.011617153
B44: 45628 | C44: 429.55 | D44: =(C44/C43)-1 -> -0.011733579 | F44: 45628 | G44: 1248.4 | H44: =(G44/G43)-1 -> -0.0057343103 | J44: 45628 | K44: 538.4 | L44: =(K44/K43)-1 -> -0.013196481 | N44: 45628 | O44: 528.4 | P44: =(O44/O43)-1 -> -0.013442868 | R44: 45628 | S44: 23780.4 | T44: =(S44/S43)-1 -> -0.00731353
B45: 45635 | C45: 428.5 | D45: =(C45/C44)-1 -> -0.0024444186 | F45: 45635 | G45: 1232.9 | H45: =(G45/G44)-1 -> -0.012415892 | J45: 45635 | K45: 522.9 | L45: =(K45/K44)-1 -> -0.028789004 | N45: 45635 | O45: 512.9 | P45: =(O45/O44)-1 -> -0.029333838 | R45: 45635 | S45: 23420.9 | T45: =(S45/S44)-1 -> -0.015117492
B46: 45642 | C46: 423.62 | D46: =(C46/C45)-1 -> -0.011388565 | F46: 45642 | G46: 1225.6 | H46: =(G46/G45)-1 -> -0.0059209993 | J46: 45642 | K46: 515.6 | L46: =(K46/K45)-1 -> -0.013960604 | N46: 45642 | O46: 505.6 | P46: =(O46/O45)-1 -> -0.014232794 | R46: 45642 | S46: 23275.6 | T46: =(S46/S45)-1 -> -0.0062038607
B47: 45649 | C47: 436.34 | D47: =(C47/C46)-1 -> 0.030026911 | F47: 45649 | G47: 1218.75 | H47: =(G47/G46)-1 -> -0.0055890992 | J47: 45649 | K47: 508.75 | L47: =(K47/K46)-1 -> -0.013285493 | N47: 45649 | O47: 498.75 | P47: =(O47/O46)-1 -> -0.013548259 | R47: 45649 | S47: 23120.75 | T47: =(S47/S46)-1 -> -0.0066528897
B48: 45656 | C48: 439.07 | D48: =(C48/C47)-1 -> 0.0062565889 | F48: 45656 | G48: 1205.3 | H48: =(G48/G47)-1 -> -0.011035897 | J48: 45656 | K48: 505.3 | L48: =(K48/K47)-1 -> -0.0067813268 | N48: 45656 | O48: 495.3 | P48: =(O48/O47)-1 -> -0.0069172932 | R48: 45656 | S48: 22945.3 | T48: =(S48/S47)-1 -> -0.0075884217
B49: 45663 | C49: 421.23 | D49: =(C49/C48)-1 -> -0.040631334 | F49: 45663 | G49: 1198.2 | H49: =(G49/G48)-1 -> -0.0058906496 | J49: 45663 | K49: 498.2 | L49: =(K49/K48)-1 -> -0.014051059 | N49: 45663 | O49: 488.2 | P49: =(O49/O48)-1 -> -0.014334747 | R49: 45663 | S49: 22680.2 | T49: =(S49/S48)-1 -> -0.011553564
B50: 45670 | C50: 416.78 | D50: =(C50/C49)-1 -> -0.0105643 | F50: 45670 | G50: 1185.6 | H50: =(G50/G49)-1 -> -0.010515774 | J50: 45670 | K50: 485.6 | L50: =(K50/K49)-1 -> -0.025291048 | N50: 45670 | O50: 475.6 | P50: =(O50/O49)-1 -> -0.025809095 | R50: 45670 | S50: 22405.6 | T50: =(S50/S49)-1 -> -0.012107477
B51: 45677 | C51: 418.11 | D51: =(C51/C50)-1 -> 0.003191132 | F51: 45677 | G51: 1192.4 | H51: =(G51/G50)-1 -> 0.0057354926 | J51: 45677 | K51: 492.4 | L51: =(K51/K50)-1 -> 0.014003295 | N51: 45677 | O51: 482.4 | P51: =(O51/O50)-1 -> 0.014297729 | R51: 45677 | S51: 22520.4 | T51: =(S51/S50)-1 -> 0.0051237191
B52: 45684 | C52: 437.95 | D52: =(C52/C51)-1 -> 0.047451628 | F52: 45684 | G52: 1210.75 | H52: =(G52/G51)-1 -> 0.015389131 | J52: 45684 | K52: 510.75 | L52: =(K52/K51)-1 -> 0.03726645 | N52: 45684 | O52: 500.75 | P52: =(O52/O51)-1 -> 0.038038972 | R52: 45684 | S52: 22950.75 | T52: =(S52/S51)-1 -> 0.019109341
B53: 45691 | C53: 407.93 | D53: =(C53/C52)-1 -> -0.068546638 | F53: 45691 | G53: 1188.3 | H53: =(G53/G52)-1 -> -0.018542226 | J53: 45691 | K53: 488.3 | L53: =(K53/K52)-1 -> -0.043954968 | N53: 45691 | O53: 478.3 | P53: =(O53/O52)-1 -> -0.044832751 | R53: 45691 | S53: 22380.3 | T53: =(S53/S52)-1 -> -0.024855397
... B113: 46111 | C113: 292.85 | D113: =(C113/C112)-1 -> -0.0062775704 | F113: 46111 | G113: 1098.2 | H113: =(G113/G112)-1 -> -0.0066931983 | J113: 46111 | K113: 398.2 | L113: =(K113/K112)-1 -> -0.018244576 | N113: 46111 | O113: 462.8 | P113: =(O113/O112)-1 -> -0.0062271849 | R113: 46111 | S113: 21880.9 | T113: =(S113/S112)-1 -> -0.0031480638

Sheet Comps_Val
B3: =Beta!B3 -> HINDUSTAN UNILEVER LTD
B4: =Beta!B4 -> (HINDUNILVR | BSE Code: 500696)
B6: Comps Valuation
B8: Amount in crores
B9: Comparable Company Valuation
D11: Market Data | K11: Financials | O11: Valuation
B12: Company | C12: Ticker | D12: Share Price | E12: Share Outstanding | F12: Equity Value | G12: Net Debt | H12: Enterprise Value | K12: Revenue | L12: EBITDA | M12: Net Income | O12: EV/Revenue | P12: EV/EBITDA | Q12: P/E
B14: =Data_Comps!C3 -> Hind. Unilever | C14: HINDUNILVR | D14: =Data_Comps!D3 -> 2133.2 | E14: =Data_Comps!E3 -> 234.96 | F14: =E14*D14 -> 501216.67 | G14: =Data_Comps!I3 -> -5779 | H14: =F14+G14 -> 495437.67 | K14: =Data_Comps!K3 -> 64544 | L14: =Data_Comps!L3 -> 15860 | M14: =Data_Comps!M3 -> 14540 | O14: =$H14/K14 -> 7.6759679 | P14: =$H14/L14 -> 31.238189 | Q14: =F14/M14 -> 34.471573
B15: =Data_Comps!C4 -> ITC | C15: ITC | D15: =Data_Comps!D4 -> 303 | E15: =Data_Comps!E4 -> 1252.95 | F15: =E15*D15 -> 379643.85 | G15: =Data_Comps!I4 -> -3649.39 | H15: =F15+G15 -> 375994.46 | K15: =Data_Comps!K4 -> 79808.72 | L15: =Data_Comps!L4 -> 28479.56 | M15: =Data_Comps!M4 -> 35356.29 | O15: =$H15/K15 -> 4.7111952 | P15: =$H15/L15 -> 13.202257 | Q15: =F15/M15 -> 10.737661
B16: =Data_Comps!C5 -> Nestle India | C16: NESTLEIND | D16: =Data_Comps!D5 -> 1228.7 | E16: =Data_Comps!E5 -> 192.83 | F16: =E16*D16 -> 236930.22 | G16: =Data_Comps!I5 -> 381.2 | H16: =F16+G16 -> 237311.42 | K16: =Data_Comps!K5 -> 21910.69 | L16: =Data_Comps!L5 -> 4830.19 | M16: =Data_Comps!M5 -> 3315.9 | O16: =$H16/K16 -> 10.830851 | P16: =$H16/L16 -> 49.130867 | Q16: =F16/M16 -> 71.452764
B17: =Data_Comps!C6 -> Varun Beverages | C17: VBL | D17: =Data_Comps!D6 -> 422.9 | E17: =Data_Comps!E6 -> 338.21 | F17: =E17*D17 -> 143029.01 | G17: =Data_Comps!I6 -> 509.69 | H17: =F17+G17 -> 143538.7 | K17: =Data_Comps!K6 -> 21685.37 | L17: =Data_Comps!L6 -> 5338.21 | M17: =Data_Comps!M6 -> 3062.04 | O17: =$H17/K17 -> 6.6191492 | P17: =$H17/L17 -> 26.88892 | Q17: =F17/M17 -> 46.710366
B18: =Data_Comps!C7 -> Britannia Inds. | C18: BRITANNIA | D18: =Data_Comps!D7 -> 5475 | E18: =Data_Comps!E7 -> 24.09 | F18: =E18*D18 -> 131892.75 | G18: =Data_Comps!I7 -> 1883.82 | H18: =F18+G18 -> 133776.57 | K18: =Data_Comps!K7 -> 18864.86 | L18: =Data_Comps!L7 -> 3402.26 | M18: =Data_Comps!M7 -> 2416.46 | O18: =$H18/K18 -> 7.09131 | P18: =$H18/L18 -> 39.319914 | Q18: =F18/M18 -> 54.580978
B19: =Data_Comps!C8 -> Godrej Consumer | C19: GODREJCP | D19: =Data_Comps!D8 -> 1063.35 | E19: =Data_Comps!E8 -> 102.32 | F19: =E19*D19 -> 108801.97 | G19: =Data_Comps!I8 -> 3630.43 | H19: =F19+G19 -> 112432.4 | K19: =Data_Comps!K8 -> 15184.02 | L19: =Data_Comps!L8 -> 3291.51 | M19: =Data_Comps!M8 -> 1821.6 | O19: =$H19/K19 -> 7.4046532 | P19: =$H19/L19 -> 34.158305 | Q19: =F19/M19 -> 59.728794
B20: =Data_Comps!C9 -> Tata Consumer | C20: TATACONSUM | D20: =Data_Comps!D9 -> 1078 | E20: =Data_Comps!E9 -> 98.96 | F20: =E20*D20 -> 106678.88 | G20: =Data_Comps!I9 -> -241.75 | H20: =F20+G20 -> 106437.13 | K20: =Data_Comps!K9 -> 19465.03 | L20: =Data_Comps!L9 -> 2647.81 | M20: =Data_Comps!M9 -> 1471.5 | O20: =$H20/K20 -> 5.4681205 | P20: =$H20/L20 -> 40.198175 | Q20: =F20/M20 -> 72.49669
B21: =Data_Comps!C10 -> Marico | C21: MARICO | D21: =Data_Comps!D10 -> 747.35 | E21: =Data_Comps!E10 -> 129.81 | F21: =E21*D21 -> 97013.504 | G21: =Data_Comps!I10 -> -202 | H21: =F21+G21 -> 96811.504 | K21: =Data_Comps!K10 -> 13008 | L21: =Data_Comps!L10 -> 2327 | M21: =Data_Comps!M10 -> 1750 | O21: =$H21/K21 -> 7.4424588 | P21: =$H21/L21 -> 41.603568 | Q21: =F21/M21 -> 55.436288
B22: =Data_Comps!C11 -> United Spirits | C22: UNITDSPR | D22: =Data_Comps!D11 -> 1249.7 | E22: =Data_Comps!E11 -> 72.74 | F22: =E22*D22 -> 90903.178 | G22: =Data_Comps!I11 -> -1618 | H22: =F22+G22 -> 89285.178 | K22: =Data_Comps!K11 -> 12919 | L22: =Data_Comps!L11 -> 2399 | M22: =Data_Comps!M11 -> 1720 | O22: =$H22/K22 -> 6.9111524 | P22: =$H22/L22 -> 37.217665 | Q22: =F22/M22 -> 52.850685
B23: =Data_Comps!C12 -> Dabur India | C23: DABUR | D23: =Data_Comps!D12 -> 429.4 | E23: =Data_Comps!E12 -> 177.37 | F23: =E23*D23 -> 76162.678 | G23: =Data_Comps!I12 -> 723.42 | H23: =F23+G23 -> 76886.098 | K23: =Data_Comps!K12 -> 12984.69 | L23: =Data_Comps!L12 -> 2857.67 | M23: =Data_Comps!M12 -> 1819.42 | O23: =$H23/K23 -> 5.9212887 | P23: =$H23/L23 -> 26.90517 | Q23: =F23/M23 -> 41.860966
B25: High | O25: =MAX(O14:O23) -> 10.830851 | P25: =MAX(P14:P23) -> 49.130867 | Q25: =MAX(Q14:Q23) -> 72.49669
B26: 75th Percentile | O26: =QUARTILE(O14:O23,3) -> 7.4330074 | P26: =QUARTILE(P14:P23,3) -> 39.97861 | Q26: =QUARTILE(Q14:Q23,3) -> 58.655668
B27: Average | O27: =AVERAGE(O14:O23) -> 7.0076147 | P27: =AVERAGE(P14:P23) -> 33.986303 | Q27: =AVERAGE(Q14:Q23) -> 50.032677
B28: Median | O28: =MEDIAN(O14:O23) -> 7.0012312 | P28: =MEDIAN(P14:P23) -> 35.687985 | Q28: =MEDIAN(Q14:Q23) -> 53.715831
B29: 25th Percentile | O29: =QUARTILE(O14:O23,1) -> 6.0957538 | P29: =QUARTILE(P14:P23,1) -> 27.988425 | Q29: =QUARTILE(Q14:Q23,1) -> 43.073316
B30: Low | O30: =MIN(O14:O23) -> 4.7111952 | P30: =MIN(P14:P23) -> 13.202257 | Q30: =MIN(Q14:Q23) -> 10.737661
B32: Hind. Uniliver Comparable Valuation | O32: EV/Revenue | P32: EV/EBITDA | Q32: P/E
B34: Implied Enterprise Value | O34: =O28*K14 -> 451887.47 | P34: =P28*L14 -> 566011.44 | Q34: =Q36+Q35 -> 775249.19
B35: Net Debt | O35: =$G$14 -> -5779 | P35: =$G$14 -> -5779 | Q35: =$G$14 -> -5779
B36: Implied Market Value | O36: =O34-O35 -> 457666.47 | P36: =P34-P35 -> 571790.44 | Q36: =Q28*M14 -> 781028.19
B37: Shares Outstanding | O37: =$E$14 -> 234.96 | P37: =$E$14 -> 234.96 | Q37: =$E$14 -> 234.96
B39: Implied Value Per Share | O39: =O36/O37 -> 1947.8484 | P39: =P36/P37 -> 2433.565 | Q39: =Q36/Q37 -> 3324.09
B41: Source: The Valuation School,Screener.in
O42: =IF(O39>$D$14,"Undervalued","Overvalued") -> Overvalued | P42: =IF(P39>$D$14,"Undervalued","Overvalued") -> Undervalued | Q42: =IF(Q39>$D$14,"Undervalued","Overvalued") -> Undervalued

Sheet Football Field Analysis 
B3: ='Historical Approach'!$B$3 -> HINDUSTAN UNILEVER LTD
B4: ='Historical Approach'!$B$4 -> (HINDUNILVR | BSE Code: 500696)
B6: Football Field Analysis
B8: Football Field Analysis-Data
D9: OpenLow | E9: Low | F9: OpenHigh | G9: High
B10: Comps | D10: 1947.8484 | E10: 1947.8484 | F10: 3324.09 | G10: 3324.09
B11: DCF Bear | D11: 326.09766 | E11: 326.09766 | F11: 365.58856 | G11: 365.58856
B12: DCF Base | D12: 386.49551 | E12: 386.49551 | F12: 486.35968 | G12: 486.35968
B13: DCF Bull | D13: 415.93946 | E13: 415.93946 | F13: 561.39762 | G13: 561.39762
B14: 52W H/L | D14: 2022.5 | E14: 2022.5 | F14: 2779.7 | G14: 2779.7

Sheet Data2

Sheet Beta-Comps
A3: S.No. | B3: Name | C3: CMP Rs. | D3: Mar Cap Rs.Cr. | E3: Debt Rs.Cr. | F3: Debt / Eq
A4: 1 | B4: ITC | C4: 297.3 | D4: 372501.11 | E4: 362.97 | F4: 0.01
A5: 2 | B5: Godrej Consumer | C5: 1034.05 | D5: 105808.55 | E5: 4113.49 | F5: 0.34
A6: 3 | B6: Hindustan Foods | C6: 495.85 | D6: 5924.5 | E6: 900.81 | F6: 0.87
A7: 4 | B7: Dabur India | C7: 414.7 | D7: 73554.98 | E7: 1301.43 | F7: 0.12

Sheet Rm
A3: Return on Markets
A5: Year | B5: Annual Return
A6: 2000 | B6: -0.1465 | E6: Average Return | F6: =AVERAGE(B6:B31) -> 0.15149231
A7: 2001 | B7: -0.1618 | E7: Dividend Yield | F7: 0.0128
A8: 2002 | B8: 0.0325 | E8: Total Market Return | F8: =SUM(F6:F7) -> 0.16429231
A9: 2003 | B9: 0.719
A10: 2004 | B10: 0.1068
A11: 2005 | B11: 0.3634
A12: 2006 | B12: 0.3983
A13: 2007 | B13: 0.5477
A14: 2008 | B14: -0.5179
A15: 2009 | B15: 0.7576
A16: 2010 | B16: 0.1795
A17: 2011 | B17: -0.2462
A18: 2012 | B18: 0.277
A19: 2013 | B19: 0.0676
A20: 2014 | B20: 0.3139
... A31: 2025 | B31: 0.1051

Sheet Data of Peers
B2: ITC | E2: Godrej | H2: Hindustan Foods | K2: Dabur | N2: HUL | R2: Nifty
B3: Date | C3: Adj Close | E3: Date | F3: Adj Close | H3: Date | I3: Adj Close | K3: Date | L3: Adj Close | N3: Date | O3: Adj Close | R3: Date | S3: Adj Close
B4: 45383 | C4: 382.74 | E4: 45383 | F4: 1186.45 | H4: 45383 | I4: 525.4 | K4: 45383 | L4: 520.45 | N4: 45383 | O4: 2395.45 | R4: 45383 | S4: 22345.6
B5: 45390 | C5: 385.02 | E5: 45390 | F5: 1201.32 | H5: 45390 | I5: 532.1 | K5: 45390 | L5: 525.3 | N5: 45390 | O5: 2410.3 | R5: 45390 | S5: 22480.3
B6: 45397 | C6: 380.23 | E6: 45397 | F6: 1194.87 | H6: 45397 | I6: 528.75 | K6: 45397 | L6: 518.75 | N6: 45397 | O6: 2388.75 | R6: 45397 | S6: 22310.75
B7: 45404 | C7: 393.89 | E7: 45404 | F7: 1210.55 | H7: 45404 | I7: 535.6 | K7: 45404 | L7: 532.6 | N7: 45404 | O7: 2425.6 | R7: 45404 | S7: 22650.6
B8: 45411 | C8: 390.71 | E8: 45411 | F8: 1203.1 | H8: 45411 | I8: 530.9 | K8: 45411 | L8: 528.9 | N8: 45411 | O8: 2408.9 | R8: 45411 | S8: 22580.9
B9: 45418 | C9: 387.93 | E9: 45418 | F9: 1189.75 | H9: 45418 | I9: 522.8 | K9: 45418 | L9: 515.8 | N9: 45418 | O9: 2375.8 | R9: 45418 | S9: 22275.8
B10: 45425 | C10: 390.89 | E10: 45425 | F10: 1198.2 | H10: 45425 | I10: 526.45 | K10: 45425 | L10: 520.45 | N10: 45425 | O10: 2390.45 | R10: 45425 | S10: 22420.45
B11: 45432 | C11: 390.48 | E11: 45432 | F11: 1205.6 | H11: 45432 | I11: 529.3 | K11: 45432 | L11: 525.3 | N11: 45432 | O11: 2405.3 | R11: 45432 | S11: 22560.3
B12: 45439 | C12: 381.76 | E12: 45439 | F12: 1192.3 | H12: 45439 | I12: 523.6 | K12: 45439 | L12: 518.6 | N12: 45439 | O12: 2380.6 | R12: 45439 | S12: 22340.6
B13: 45446 | C13: 393.12 | E13: 45446 | F13: 1215.8 | H13: 45446 | I13: 540.75 | K13: 45446 | L13: 535.75 | N13: 45446 | O13: 2445.75 | R13: 45446 | S13: 22945.75
B14: 45453 | C14: 393.08 | E14: 45453 | F14: 1220.45 | H14: 45453 | I14: 545.2 | K14: 45453 | L14: 540.2 | N14: 45453 | O14: 2460.2 | R14: 45453 | S14: 23120.2
B15: 45460 | C15: 382.55 | E15: 45460 | F15: 1208.9 | H15: 45460 | I15: 538.9 | K15: 45460 | L15: 532.9 | N15: 45460 | O15: 2432.9 | R15: 45460 | S15: 22890.9
... B108: 46111 | C108: 292.85 | E108: 46111 | F108: 1098.2 | H108: 46111 | I108: 398.2 | K108: 46111 | L108: 462.8 | N108: 46111 | O108: 2143.9 | R108: 46111 | S108: 21880.9

Sheet Data_Comps
B2: S.No. | C2: Name | D2: CMP Rs. | E2: No. Eq. Shares Cr. | F2: Market Cap | G2: Debt Rs.Cr. | H2: Cash End Rs.Cr. | I2: Net Debt | J2: EV | K2: Sales Rs.Cr. | L2: EBIDT Ann Rs.Cr. | M2: NP 12M Rs.Cr.
B3: 3 | C3: Hind. Unilever | D3: 2133.2 | E3: 234.96 | F3: =E3*D3 -> 501216.67 | G3: 1775 | H3: 7554 | I3: =G3-H3 -> -5779 | J3: =F3+G3-H3 -> 495437.67 | K3: 64544 | L3: 15860 | M3: 14540
B4: 1 | C4: ITC | D4: 303 | E4: 1252.95 | F4: =E4*D4 -> 379643.85 | G4: 362.97 | H4: 4012.36 | I4: =G4-H4 -> -3649.39 | J4: =F4+G4-H4 -> 375994.46 | K4: 79808.72 | L4: 28479.56 | M4: 35356.29
B5: 7 | C5: Nestle India | D5: 1228.7 | E5: 192.83 | F5: =E5*D5 -> 236930.22 | G5: 476.85 | H5: 95.65 | I5: =G5-H5 -> 381.2 | J5: =F5+G5-H5 -> 237311.42 | K5: 21910.69 | L5: 4830.19 | M5: 3315.9
B6: 8 | C6: Varun Beverages | D6: 422.9 | E6: 338.21 | F6: =E6*D6 -> 143029.01 | G6: 2508.18 | H6: 1998.49 | I6: =G6-H6 -> 509.69 | J6: =F6+G6-H6 -> 143538.7 | K6: 21685.37 | L6: 5338.21 | M6: 3062.04
B7: 11 | C7: Britannia Inds. | D7: 5475 | E7: 24.09 | F7: =E7*D7 -> 131892.75 | G7: 2196.3 | H7: 312.48 | I7: =G7-H7 -> 1883.82 | J7: =F7+G7-H7 -> 133776.57 | K7: 18864.86 | L7: 3402.26 | M7: 2416.46
B8: 12 | C8: Godrej Consumer | D8: 1063.35 | E8: 102.32 | F8: =E8*D8 -> 108801.97 | G8: 4113.49 | H8: 483.06 | I8: =G8-H8 -> 3630.43 | J8: =F8+G8-H8 -> 112432.4 | K8: 15184.02 | L8: 3291.51 | M8: 1821.6
B9: 9 | C9: Tata Consumer | D9: 1078 | E9: 98.96 | F9: =E9*D9 -> 106678.88 | G9: 2576.11 | H9: 2817.86 | I9: =G9-H9 -> -241.75 | J9: =F9+G9-H9 -> 106437.13 | K9: 19465.03 | L9: 2647.81 | M9: 1471.5
B10: 13 | C10: Marico | D10: 747.35 | E10: 129.81 | F10: =E10*D10 -> 97013.504 | G10: 575 | H10: 777 | I10: =G10-H10 -> -202 | J10: =F10+G10-H10 -> 96811.504 | K10: 13008 | L10: 2327 | M10: 1750
B11: 15 | C11: United Spirits | D11: 1249.7 | E11: 72.74 | F11: =E11*D11 -> 90903.178 | G11: 412 | H11: 2030 | I11: =G11-H11 -> -1618 | J11: =F11+G11-H11 -> 89285.178 | K11: 12919 | L11: 2399 | M11: 1720
B12: 14 | C12: Dabur India | D12: 429.4 | E12: 177.37 | F12: =E12*D12 -> 76162.678 | G12: 1301.43 | H12: 578.01 | I12: =G12-H12 -> 723.42 | J12: =F12+G12-H12 -> 76886.098 | K12: 12984.69 | L12: 2857.67 | M12: 1819.42
B13: 4 | C13: Patanjali Foods | D13: 459.7 | E13: 108.81 | F13: =E13*D13 -> 50019.957 | G13: 2895.22 | H13: 275.3 | I13: =G13-H13 -> 2619.92 | J13: =F13+G13-H13 -> 52639.877 | K13: 38718.82 | L13: 2088.81 | M13: 1649.39
B16: 20 | C16: United Breweries | D16: 1467.2 | E16: 26.44 | F16: =E16*D16 -> 38792.768 | G16: 776.87 | H16: 442.88 | J16: =F16+G16-H16 -> 39126.758 | K16: 9312.85 | L16: 876.67 | M16: 409.28
B17: 23 | C17: Godfrey Phillips | D17: 2034.8 | E17: 15.6 | F17: =E17*D17 -> 31742.88 | G17: 175.26 | H17: 30.3 | J17: =F17+G17-H17 -> 31887.84 | K17: 6177.23 | L17: 1441.51 | M17: 1284.17
B18: 2 | C18: AWL Agri Busine. | D18: 177.1 | E18: 129.97 | F18: =E18*D18 -> 23017.687 | G18: 1095.97 | H18: 2325.14 | J18: =F18+G18-H18 -> 21788.517 | K18: 71495.48 | L18: 2724.36 | M18: 942.49
B19: 18 | C19: Hatsun Agro | D19: 909.25 | E19: 22.27 | F19: =E19*D19 -> 20248.998 | G19: 2009.95 | H19: 61.84 | J19: =F19+G19-H19 -> 22197.108 | K19: 9441.19 | L19: 1026.99 | M19: 385.04
B20: 5 | C20: EID Parry | D20: 830.7 | E20: 17.79 | F20: =E20*D20 -> 14778.153 | G20: 2665.73 | H20: 3691.01 | J20: =F20+G20-H20 -> 13752.873 | K20: 37474.82 | L20: 2883.24 | M20: 2207.06
B21: 16 | C21: L T Foods | D21: 405.15 | E21: 34.73 | F21: =E21*D21 -> 14070.859 | G21: 1804.46 | H21: 144.16 | J21: =F21+G21-H21 -> 15731.159 | K21: 10267.22 | L21: 1092.56 | M21: 650.22
B22: 17 | C22: Godrej Agrovet | D22: 586.9 | E22: 19.23 | F22: =E22*D22 -> 11286.087 | G22: 2158.57 | H22: 39.33 | J22: =F22+G22-H22 -> 13405.327 | K22: 10033.67 | L22: 917.57 | M22: 409
B23: 10 | C23: The Bombay Burmah | D23: 1445.4 | E23: 6.98 | F23: =E23*D23 -> 10088.892 | G23: 2463.63 | H23: 542.8 | J23: =F23+G23-H23 -> 12009.722 | K23: 19239.45 | L23: 3550.02 | M23: 2303.23
B24: 24 | C24: Balrampur Chini | D24: 477.7 | E24: 20.2 | F24: =E24*D24 -> 9649.54 | G24: 774.4 | H24: 3.42 | J24: =F24+G24-H24 -> 10420.52 | K24: 6170.83 | L24: 773.65 | M24: 448.01
B25: 22 | C25: Triven.Engg.Ind. | D25: 382.75 | E25: 21.89 | F25: =E25*D25 -> 8378.3975 | G25: 768.09 | H25: 54.73 | J25: =F25+G25-H25 -> 9091.7575 | K25: 6411.8 | L25: 535.55 | M25: 288.38
B26: 25 | C26: KRBL | D26: 325.95 | E26: 22.89 | F26: =E26*D26 -> 7460.9955 | G26: 70.99 | H26: 462.18 | J26: =F26+G26-H26 -> 7069.8055 | K26: 6014.61 | L26: 735.18 | M26: 646.87
B27: 6 | C27: Gokul Agro | D27: 199.88 | E27: 29.51 | F27: =E27*D27 -> 5898.4588 | G27: 585.98 | H27: 396.14 | J27: =F27+G27-H27 -> 6088.2988 | K27: 23338.94 | L27: 562.21 | M27: 299.17
... B29: 21 | C29: HMA Agro Inds. | D29: 21.96 | E29: 50.08 | F29: =E29*D29 -> 1099.7568 | G29: 627.11 | H29: 94.29 | J29: =F29+G29-H29 -> 1632.5768 | K29: 6836.96 | L29: 186.49 | M29: 169.32

Sheet VAR>

Sheet Historical Approach
B3: =Comps_Val!B3 -> HINDUSTAN UNILEVER LTD
B4: =Comps_Val!B4 -> (HINDUNILVR | BSE Code: 500696)
B6: VAR - Historical Approach
A8: # | B8: Date | C8: Adj Close | D8: Returns | E8: Sorted Returns | G8: Calculation of Value at Risk - Hind. Uniliver(Historical)
B9: 2013-04-30 | C9: 468.73349 | D9: =(C9-C10)/C10 -> -0.78783557 | E9: 0.17382123
B10: 2020-04-07 | C10: 2209.2935 | D10: =(C10-C11)/C11 -> 14.884433 | E10: 0.1349983 | G10: Mean | L10: =AVERAGE(E8:E7606) -> 0.00070734082
B11: 2000-05-26 | C11: 139.08545 | D11: =(C11-C12)/C12 -> 0.24297472 | E11: 0.11928453 | G11: Std Deviation | L11: =_xlfn.STDEV.S(E9:E7606) -> 0.017939549
B12: 1999-03-01 | C12: 111.89725 | D12: =(C12-C13)/C13 -> -0.939645 | E12: 0.11773486 | G12: Min | L12: =MIN(E9:E7606) -> -0.1508303
B13: 2020-03-20 | C13: 1853.9846 | D13: =(C13-C14)/C14 -> 13.434088 | E13: 0.11608541 | G13: Max | L13: =MAX(E9:E7606) -> 0.17382123
B14: 2001-02-28 | C14: 128.44487 | D14: =(C14-C15)/C15 -> -0.040847291 | E14: 0.11423759 | G14: CMP | L14: 2166.1
B15: 2000-05-04 | C15: 133.91493 | D15: =(C15-C16)/C16 -> -0.75894509 | E15: 0.102473
B16: 2013-07-17 | C16: 555.53705 | D16: =(C16-C17)/C17 -> 3.4849097 | E16: 0.099421862 | G16: Percentile | H16: Confidence | I16: VAR % | J16: Stock Price | K16: VAR(INR)
B17: 2007-03-08 | C17: 123.86806 | D17: =(C17-C18)/C18 -> -0.18643317 | E17: 0.098625293 | G17: 0.05 | H17: =100%-G17 -> 0.95 | I17: =_xlfn.PERCENTILE.INC(E9:E7606,G17) -> -0.025817103 | J17: =$L$14*(1-(-I17)) -> 2110.1776 | K17: =$L$14-J17 -> 55.922427
B18: 2006-06-30 | C18: 152.25308 | D18: =(C18-C19)/C19 -> 0.16074679 | E18: 0.09305721 | G18: 0.01 | H18: =100%-G18 -> 0.99 | I18: =_xlfn.PERCENTILE.INC(E10:E7607,G18) -> -0.045274706 | J18: =$L$14*(1-(-I18)) -> 2068.0305 | K18: =$L$14-J18 -> 98.06954
B19: 2001-10-10 | C19: 131.16821 | D19: =(C19-C20)/C20 -> -0.92592415 | E19: 0.088089499 | G19: 0.005 | H19: =100%-G19 -> 0.995 | I19: =_xlfn.PERCENTILE.INC(E11:E7608,G19) -> -0.054593856 | J19: =$L$14*(1-(-I19)) -> 2047.8442 | K19: =$L$14-J19 -> 118.25575
B20: 2019-09-20 | C20: 1770.7285 | D20: =(C20-C21)/C21 -> -0.033673519 | E20: 0.086608796 | G20: 0.1 | H20: =100%-G20 -> 0.9 | I20: =_xlfn.PERCENTILE.INC(E12:E7609,G20) -> -0.018397836 | J20: =$L$14*(1-(-I20)) -> 2126.2484 | K20: =$L$14-J20 -> 39.851552
B21: 2020-03-24 | C21: 1832.433 | D21: =(C21-C22)/C22 -> 2.7115726 | E21: 0.084585557
B22: 2014-05-30 | C22: 493.70798 | D22: =(C22-C23)/C23 -> 3.2431945 | E22: 0.084284142
B23: 2001-09-18 | C23: 116.3529 | D23: =(C23-C24)/C24 -> -0.13281302 | E23: 0.083466281
B24: 2006-06-15 | C24: 134.17279 | D24: =(C24-C25)/C25 -> 0.83245328 | E24: 0.083176864
B25: 1997-10-29 | C25: 73.220306 | D25: =(C25-C26)/C26 -> -0.42504742 | E25: 0.080833693
B26: 2000-01-03 | C26: 127.35017 | D26: =(C26-C27)/C27 -> -0.21276279 | E26: 0.080010169
B27: 2000-02-22 | C27: 161.76848 | D27: =(C27-C28)/C28 -> 0.080009674 | E27: 0.080009674
B28: 2000-02-21 | C28: 149.78429 | D28: =(C28-C29)/C29 -> 0.034596503 | E28: 0.080003732
B29: 2000-04-03 | C29: 144.77556 | D29: =(C29-C30)/C30 -> 0.1267038 | E29: 0.080003365
B30: 1999-04-16 | C30: 128.49478 | D30: =(C30-C31)/C31 -> 0.16461805 | E30: 0.080002521
B31: 1999-02-10 | C31: 110.33212 | D31: =(C31-C32)/C32 -> -0.31095539 | E31: 0.080000108
B32: 2000-03-15 | C32: 160.12334 | D32: =(C32-C33)/C33 -> 0.15455236 | E32: 0.079999366
... B7606: 2004-05-17 | C7606: 75.007019 | D7606: =(C7606-C7607)/C7607 -> #DIV/0! | E7606: -0.1508303

Sheet Monte Carlo Simulation
B3: ='Historical Approach'!B3 -> HINDUSTAN UNILEVER LTD
B4: ='Historical Approach'!B4 -> (HINDUNILVR | BSE Code: 500696)
B6: VAR - Monte Carlo Simulation
A8: # | B8: Date | C8: Adj Close | D8: Returns | E8: Sorted Returns | G8: Replications | H8: Simulated Returns | J8: Calculation of Value at Risk - Hind. Uniliver(Simulation)
B9: 2013-04-30 | C9: 468.73349 | D9: =(C9-C10)/C10 -> -0.78783557 | E9: 0.17382123 | G9: 1 | H9: =_xlfn.NORM.INV(RAND(),N$11,N$12) -> 0.028735846
B10: 2020-04-07 | C10: 2209.2935 | D10: =(C10-C11)/C11 -> 14.884433 | E10: 0.1349983 | G10: 2 | H10: =_xlfn.NORM.INV(RAND(),$N$11,$N$12) -> 0.010330976 | J10: Historical Approach
B11: 2000-05-26 | C11: 139.08545 | D11: =(C11-C12)/C12 -> 0.24297472 | E11: 0.11928453 | G11: 3 | H11: =_xlfn.NORM.INV(RAND(),$N$11,$N$12) -> 0.022559307 | J11: Mean | N11: =AVERAGE(E8:E7606) -> 0.00070734082
B12: 1999-03-01 | C12: 111.89725 | D12: =(C12-C13)/C13 -> -0.939645 | E12: 0.11773486 | G12: 4 | H12: =_xlfn.NORM.INV(RAND(),$N$11,$N$12) -> 0.0034676641 | J12: Std Deviation | N12: =_xlfn.STDEV.S(E9:E7606) -> 0.017939549
B13: 2020-03-20 | C13: 1853.9846 | D13: =(C13-C14)/C14 -> 13.434088 | E13: 0.11608541 | G13: 5 | H13: =_xlfn.NORM.INV(RAND(),$N$11,$N$12) -> 0.02165035 | J13: Min | N13: =MIN(E9:E7606) -> -0.1508303
B14: 2001-02-28 | C14: 128.44487 | D14: =(C14-C15)/C15 -> -0.040847291 | E14: 0.11423759 | G14: 6 | H14: =_xlfn.NORM.INV(RAND(),$N$11,$N$12) -> 0.030766589 | J14: Max | N14: =MAX(E9:E7606) -> 0.17382123
B15: 2000-05-04 | C15: 133.91493 | D15: =(C15-C16)/C16 -> -0.75894509 | E15: 0.102473 | G15: 7 | H15: =_xlfn.NORM.INV(RAND(),$N$11,$N$12) -> 0.0015979286 | J15: CMP | N15: 2166.1
B16: 2013-07-17 | C16: 555.53705 | D16: =(C16-C17)/C17 -> 3.4849097 | E16: 0.099421862 | G16: 8 | H16: =_xlfn.NORM.INV(RAND(),$N$11,$N$12) -> -0.0078964136
B17: 2007-03-08 | C17: 123.86806 | D17: =(C17-C18)/C18 -> -0.18643317 | E17: 0.098625293 | G17: 9 | H17: =_xlfn.NORM.INV(RAND(),$N$11,$N$12) -> 0.023766884 | J17: Monte Carlo Simulation
B18: 2006-06-30 | C18: 152.25308 | D18: =(C18-C19)/C19 -> 0.16074679 | E18: 0.09305721 | G18: 10 | H18: =_xlfn.NORM.INV(RAND(),$N$11,$N$12) -> 0.0024300416 | J18: Mean | N18: =AVERAGE(H9:H10008) -> 0.00065574858
B19: 2001-10-10 | C19: 131.16821 | D19: =(C19-C20)/C20 -> -0.92592415 | E19: 0.088089499 | G19: 11 | H19: =_xlfn.NORM.INV(RAND(),$N$11,$N$12) -> 0.0038652385 | J19: Std Deviation | N19: =_xlfn.STDEV.S(H9:H10008) -> 0.017722999
B20: 2019-09-20 | C20: 1770.7285 | D20: =(C20-C21)/C21 -> -0.033673519 | E20: 0.086608796 | G20: 12 | H20: =_xlfn.NORM.INV(RAND(),$N$11,$N$12) -> 0.023882406 | J20: Min | N20: =MIN(H9:H10008) -> -0.071924173
B21: 2020-03-24 | C21: 1832.433 | D21: =(C21-C22)/C22 -> 2.7115726 | E21: 0.084585557 | G21: 13 | H21: =_xlfn.NORM.INV(RAND(),$N$11,$N$12) -> 0.028184994 | J21: Max | N21: =MAX(H9:H10008) -> 0.069320541
B22: 2014-05-30 | C22: 493.70798 | D22: =(C22-C23)/C23 -> 3.2431945 | E22: 0.084284142 | G22: 14 | H22: =_xlfn.NORM.INV(RAND(),$N$11,$N$12) -> 0.0082134736 | J22: CMP | N22: 2166.1
B23: 2001-09-18 | C23: 116.3529 | D23: =(C23-C24)/C24 -> -0.13281302 | E23: 0.083466281 | G23: 15 | H23: =_xlfn.NORM.INV(RAND(),$N$11,$N$12) -> 0.0014815941
B24: 2006-06-15 | C24: 134.17279 | D24: =(C24-C25)/C25 -> 0.83245328 | E24: 0.083176864 | G24: 16 | H24: =_xlfn.NORM.INV(RAND(),$N$11,$N$12) -> 0.014311007 | J24: Percentile | K24: Confidence | L24: VAR % | M24: Stock Price | N24: VAR(INR)
B25: 1997-10-29 | C25: 73.220306 | D25: =(C25-C26)/C26 -> -0.42504742 | E25: 0.080833693 | G25: 17 | H25: =_xlfn.NORM.INV(RAND(),$N$11,$N$12) -> 0.0095138349 | J25: 0.05 | K25: =100%-J25 -> 0.95 | L25: =_xlfn.PERCENTILE.INC(H9:H10008,J25) -> -0.028154474 | M25: =$N$15*(1-(-L25)) -> 2105.1146 | N25: =$N$15-M25 -> 60.985406
B26: 2000-01-03 | C26: 127.35017 | D26: =(C26-C27)/C27 -> -0.21276279 | E26: 0.080010169 | G26: 18 | H26: =_xlfn.NORM.INV(RAND(),$N$11,$N$12) -> -0.0029940948 | J26: 0.01 | K26: =100%-J26 -> 0.99 | L26: =_xlfn.PERCENTILE.INC(H10:H10009,J26) -> -0.040794158 | M26: =$N$15*(1-(-L26)) -> 2077.7358 | N26: =$N$15-M26 -> 88.364225
B27: 2000-02-22 | C27: 161.76848 | D27: =(C27-C28)/C28 -> 0.080009674 | E27: 0.080009674 | G27: 19 | H27: =_xlfn.NORM.INV(RAND(),$N$11,$N$12) -> 0.0070396956 | J27: 0.005 | K27: =100%-J27 -> 0.995 | L27: =_xlfn.PERCENTILE.INC(H11:H10010,J27) -> -0.044757638 | M27: =$N$15*(1-(-L27)) -> 2069.1505 | N27: =$N$15-M27 -> 96.94952
B28: 2000-02-21 | C28: 149.78429 | D28: =(C28-C29)/C29 -> 0.034596503 | E28: 0.080003732 | G28: 20 | H28: =_xlfn.NORM.INV(RAND(),$N$11,$N$12) -> -0.025899215 | J28: 0.1 | K28: =100%-J28 -> 0.9 | L28: =_xlfn.PERCENTILE.INC(H12:H10011,J28) -> -0.021842483 | M28: =$N$15*(1-(-L28)) -> 2118.787 | N28: =$N$15-M28 -> 47.313002
B29: 2000-04-03 | C29: 144.77556 | D29: =(C29-C30)/C30 -> 0.1267038 | E29: 0.080003365 | G29: 21 | H29: =_xlfn.NORM.INV(RAND(),$N$11,$N$12) -> -0.039645165
B30: 1999-04-16 | C30: 128.49478 | D30: =(C30-C31)/C31 -> 0.16461805 | E30: 0.080002521 | G30: 22 | H30: =_xlfn.NORM.INV(RAND(),$N$11,$N$12) -> 0.010735927
B31: 1999-02-10 | C31: 110.33212 | D31: =(C31-C32)/C32 -> -0.31095539 | E31: 0.080000108 | G31: 23 | H31: =_xlfn.NORM.INV(RAND(),$N$11,$N$12) -> -0.023329363
B32: 2000-03-15 | C32: 160.12334 | D32: =(C32-C33)/C33 -> 0.15455236 | E32: 0.079999366 | G32: 24 | H32: =_xlfn.NORM.INV(RAND(),$N$11,$N$12) -> -0.0078879191
B33: 2000-02-18 | C33: 138.68867 | D33: =(C33-C34)/C34 -> 0.029749914 | E33: 0.079908157 | G33: 25 | H33: =_xlfn.NORM.INV(RAND(),$N$11,$N$12) -> 0.028520504
B34: 1999-10-27 | C34: 134.6819 | D34: =(C34-C35)/C35 -> 0.66535515 | E34: 0.079894454 | G34: 26 | H34: =_xlfn.NORM.INV(RAND(),$N$11,$N$12) -> 0.0069440826
B35: 2004-05-18 | C35: 80.87278 | D35: =(C35-C36)/C36 -> -0.077014028 | E35: 0.078202825 | G35: 27 | H35: =_xlfn.NORM.INV(RAND(),$N$11,$N$12) -> 0.011676402
B36: 1998-07-01 | C36: 87.620811 | D36: =(C36-C37)/C37 -> -0.45530153 | E36: 0.075950968 | G36: 28 | H36: =_xlfn.NORM.INV(RAND(),$N$11,$N$12) -> 0.0056775845
B37: 2006-06-02 | C37: 160.86113 | D37: =(C37-C38)/C38 -> 1.9361168 | E37: 0.07555529 | G37: 29 | H37: =_xlfn.NORM.INV(RAND(),$N$11,$N$12) -> 0.014496028
B38: 1997-03-03 | C38: 54.787033 | D38: =(C38-C39)/C39 -> -0.61175837 | E38: 0.075211708 | G38: 30 | H38: =_xlfn.NORM.INV(RAND(),$N$11,$N$12) -> -0.0096937552
B39: 2008-01-25 | C39: 141.11581 | D39: =(C39-C40)/C40 -> 0.761692 | E39: 0.075208109 | G39: 31 | H39: =_xlfn.NORM.INV(RAND(),$N$11,$N$12) -> 0.01734201
B40: 1998-02-13 | C40: 80.102432 | D40: =(C40-C41)/C41 -> -0.78559173 | E40: 0.075089454 | G40: 32 | H40: =_xlfn.NORM.INV(RAND(),$N$11,$N$12) -> 0.0066036794
... B7606: 2004-05-17 | C7606: 75.007019 | D7606: =(C7606-C7607)/C7607 -> #DIV/0! | E7606: -0.1508303 | G7606: 7598 | H7606: =_xlfn.NORM.INV(RAND(),$N$11,$N$12) -> 0.028820794
G7607: 7599 | H7607: =_xlfn.NORM.INV(RAND(),$N$11,$N$12) -> -0.00058220756
G7608: 7600 | H7608: =_xlfn.NORM.INV(RAND(),$N$11,$N$12) -> -0.012773179
G7609: 7601 | H7609: =_xlfn.NORM.INV(RAND(),$N$11,$N$12) -> 0.012335346
G7610: 7602 | H7610: =_xlfn.NORM.INV(RAND(),$N$11,$N$12) -> 0.0046743186
G7611: 7603 | H7611: =_xlfn.NORM.INV(RAND(),$N$11,$N$12) -> 0.01877956
G7612: 7604 | H7612: =_xlfn.NORM.INV(RAND(),$N$11,$N$12) -> 0.0072335302
G7613: 7605 | H7613: =_xlfn.NORM.INV(RAND(),$N$11,$N$12) -> 0.0060421106
G7614: 7606 | H7614: =_xlfn.NORM.INV(RAND(),$N$11,$N$12) -> 0.020084091
G7615: 7607 | H7615: =_xlfn.NORM.INV(RAND(),$N$11,$N$12) -> -0.0055218196
G7616: 7608 | H7616: =_xlfn.NORM.INV(RAND(),$N$11,$N$12) -> -0.0072545158
G7617: 7609 | H7617: =_xlfn.NORM.INV(RAND(),$N$11,$N$12) -> 0.011006177
G7618: 7610 | H7618: =_xlfn.NORM.INV(RAND(),$N$11,$N$12) -> -0.0050112659
... G10008: 10000 | H10008: =_xlfn.NORM.INV(RAND(),$N$11,$N$12) -> 0.019566021

Sheet Altman's Z Score
B3: ='Data Sheet'!B1 -> HINDUSTAN UNILEVER LTD
B4: =CONCATENATE("","(",VLOOKUP(B3,'List of Stocks'!A2:D5442,3,FALSE)," | ", "BSE Code: ",VLOOKUP('Altman''s Z Score'!B3,'List of Stocks'!A2:D5442,2,FALSE),")") -> (HINDUNILVR | BSE Code: 500696)
B5: =CONCATENATE("","INR "&'Data Sheet'!B8) -> INR 2082.5
B6: 52 Week High - INR 2,750.00 & Low - 2,022.50
B9: Altman Z's Score Analysis
B15: Working Capital / Total Asset
C16: =HistoricalFS!F9 -> 43555 | D16: =HistoricalFS!G9 -> 43921 | E16: =HistoricalFS!H9 -> 44286 | F16: =HistoricalFS!I9 -> 44651 | G16: =HistoricalFS!J9 -> 45016 | H16: =HistoricalFS!K9 -> 45382 | I16: =HistoricalFS!L9 -> 45747
B17: Working Capital | C17: ='Data Sheet'!E65-'Data Sheet'!E60 -> 129 | D17: ='Data Sheet'!F65-'Data Sheet'!F60 -> 898 | E17: ='Data Sheet'!G65-'Data Sheet'!G60 -> -7223 | F17: ='Data Sheet'!H65-'Data Sheet'!H60 -> -6203 | G17: ='Data Sheet'!I65-'Data Sheet'!I60 -> -5169 | H17: ='Data Sheet'!J65-'Data Sheet'!J60 -> -6692 | I17: ='Data Sheet'!K65-'Data Sheet'!K60 -> -8104
B18: Total Assets | C18: ='Data Sheet'!E61 -> 18629 | D18: ='Data Sheet'!F61 -> 20153 | E18: ='Data Sheet'!G61 -> 68740 | F18: ='Data Sheet'!H61 -> 70506 | G18: ='Data Sheet'!I61 -> 73077 | H18: ='Data Sheet'!J61 -> 78489 | I18: ='Data Sheet'!K61 -> 79863
B19: Working Capital / Total Assets (A) | C19: =C17/C18 -> 0.0069246873 | D19: =D17/D18 -> 0.044559123 | E19: =E17/E18 -> -0.1050771 | F19: =F17/F18 -> -0.087978328 | G19: =G17/G18 -> -0.07073361 | H19: =H17/H18 -> -0.085260355 | I19: =I17/I18 -> -0.10147377
B21: Retained Earnings / Total Asset
C22: =C16 -> 43555 | D22: =D16 -> 43921 | E22: =E16 -> 44286 | F22: =F16 -> 44651 | G22: =G16 -> 45016 | H22: =H16 -> 45382 | I22: =I16 -> 45747
B23: Retained Earnings | C23: ='Data Sheet'!E58 -> 7651 | D23: ='Data Sheet'!F58 -> 8013 | E23: ='Data Sheet'!G58 -> 47439 | F23: ='Data Sheet'!H58 -> 48826 | G23: ='Data Sheet'!I58 -> 50069 | H23: ='Data Sheet'!J58 -> 50983 | I23: ='Data Sheet'!K58 -> 49167
B24: Total Assets | C24: =C18 -> 18629 | D24: =D18 -> 20153 | E24: =E18 -> 68740 | F24: =F18 -> 70506 | G24: =G18 -> 73077 | H24: =H18 -> 78489 | I24: =I18 -> 79863
B25: Retained Earnings / Total Asset (B) | C25: =C23/C24 -> 0.41070374 | D25: =D23/D24 -> 0.3976083 | E25: =E23/E24 -> 0.6901222 | F25: =F23/F24 -> 0.69250844 | G25: =G23/G24 -> 0.68515402 | H25: =H23/H24 -> 0.64955599 | I25: =I23/I24 -> 0.61564179
B27: EBIT / Total Asset
B28: EBIT | C28: =HistoricalFS!F24-HistoricalFS!F30 -> 8315 | D28: =HistoricalFS!G24-HistoricalFS!G30 -> 8859 | E28: =HistoricalFS!H24-HistoricalFS!H30 -> 10552 | F28: =HistoricalFS!I24-HistoricalFS!I30 -> 11766 | G28: =HistoricalFS!J24-HistoricalFS!J30 -> 13010 | H28: =HistoricalFS!K24-HistoricalFS!K30 -> 13443 | I28: =HistoricalFS!L24-HistoricalFS!L30 -> 13488
B29: Total Asset | C29: =C24 -> 18629 | D29: =D24 -> 20153 | E29: =E24 -> 68740 | F29: =F24 -> 70506 | G29: =G24 -> 73077 | H29: =H24 -> 78489 | I29: =I24 -> 79863
B30: EBIT / Total Asset (C) | C30: =C28/C29 -> 0.44634709 | D30: =D28/D29 -> 0.43958716 | E30: =E28/E29 -> 0.15350596 | F30: =F28/F29 -> 0.16687941 | G30: =G28/G29 -> 0.17803139 | H30: =H28/H29 -> 0.17127241 | I30: =I28/I29 -> 0.16888922
B32: Market Cap / Long Term Liabilities
B33: Market Cap | C33: =('Data Sheet'!E90*'Data Sheet'!E70)/10000000 -> 353610.96 | D33: =('Data Sheet'!F90*'Data Sheet'!F70)/10000000 -> 476198.17 | E33: =('Data Sheet'!G90*'Data Sheet'!G70)/10000000 -> 546772.63 | F33: =('Data Sheet'!H90*'Data Sheet'!H70)/10000000 -> 460684.36 | G33: =('Data Sheet'!I90*'Data Sheet'!I70)/10000000 -> 575753.24 | H33: =('Data Sheet'!J90*'Data Sheet'!J70)/10000000 -> 509189.32 | I33: =('Data Sheet'!K90*'Data Sheet'!K70)/10000000 -> 507953.44
B34: Long Term Liabilities | C34: =SUM('Data Sheet'!E59:E60) -> 10762 | D34: =SUM('Data Sheet'!F59:F60) -> 11924 | E34: =SUM('Data Sheet'!G59:G60) -> 21066 | F34: =SUM('Data Sheet'!H59:H60) -> 21445 | G34: =SUM('Data Sheet'!I59:I60) -> 22773 | H34: =SUM('Data Sheet'!J59:J60) -> 27271 | I34: =SUM('Data Sheet'!K59:K60) -> 30461
B35: Market Cap/ Long Term Liabilities (D) | C35: =IFERROR(C33/C34,0) -> 32.857365 | D35: =IFERROR(D33/D34,0) -> 39.936109 | E35: =IFERROR(E33/E34,0) -> 25.955218 | F35: =IFERROR(F33/F34,0) -> 21.482134 | G35: =IFERROR(G33/G34,0) -> 25.282275 | H35: =IFERROR(H33/H34,0) -> 18.671458 | I35: =IFERROR(I33/I34,0) -> 16.675534
B38: Sales / Total Assets
C39: =C22 -> 43555 | D39: =D22 -> 43921 | E39: =E22 -> 44286 | F39: =F22 -> 44651 | G39: =G22 -> 45016 | H39: =H22 -> 45382 | I39: =I22 -> 45747
B40: Sales | C40: ='Data Sheet'!E17 -> 39310 | D40: ='Data Sheet'!F17 -> 39783 | E40: ='Data Sheet'!G17 -> 47028 | F40: ='Data Sheet'!H17 -> 52446 | G40: ='Data Sheet'!I17 -> 60580 | H40: ='Data Sheet'!J17 -> 61896 | I40: ='Data Sheet'!K17 -> 63121
B41: =B29 -> Total Asset | C41: =C29 -> 18629 | D41: =D29 -> 20153 | E41: =E29 -> 68740 | F41: =F29 -> 70506 | G41: =G29 -> 73077 | H41: =H29 -> 78489 | I41: =I29 -> 79863
B42: Sales / Total Assets (E) | C42: =C40/C41 -> 2.1101508 | D42: =D40/D41 -> 1.9740485 | E42: =E40/E41 -> 0.68414315 | F42: =F40/F41 -> 0.74385159 | G42: =G40/G41 -> 0.8289886 | H42: =H40/H41 -> 0.78859458 | I42: =I40/I41 -> 0.790366
B44: Altman's Z Score
C45: =C39 -> 43555 | D45: =D39 -> 43921 | E45: =E39 -> 44286 | F45: =F39 -> 44651 | G45: =G39 -> 45016 | H45: =H39 -> 45382 | I45: =I39 -> 45747
B46: Final Score | C46: =(C19*1.2)+(C25*1.4)+(C30*3.3)+(C35*0.6)+(C42*1) -> 23.88081 | D46: =(D19*1.2)+(D25*1.4)+(D30*3.3)+(D35*0.6)+(D42*1) -> 27.996474 | E46: =(E19*1.2)+(E25*1.4)+(E30*3.3)+(E35*0.6)+(E42*1) -> 17.603922 | F46: =(F19*1.2)+(F25*1.4)+(F30*3.3)+(F35*0.6)+(F42*1) -> 15.047772 | G46: =(G19*1.2)+(G25*1.4)+(G30*3.3)+(G35*0.6)+(G42*1) -> 17.460192 | H46: =(H19*1.2)+(H25*1.4)+(H30*3.3)+(H35*0.6)+(H42*1) -> 13.363734 | I46: =(I19*1.2)+(I25*1.4)+(I30*3.3)+(I35*0.6)+(I42*1) -> 12.093151
B47: Financial Stability | C47: =IF(C46<1.81,"Distressed",IF(C46>3,"Strong","Grey Zone")) -> Strong | D47: =IF(D46<1.81,"Distressed",IF(D46>3,"Strong","Grey Zone")) -> Strong | E47: =IF(E46<1.81,"Distressed",IF(E46>3,"Strong","Grey Zone")) -> Strong | F47: =IF(F46<1.81,"Distressed",IF(F46>3,"Strong","Grey Zone")) -> Strong | G47: =IF(G46<1.81,"Distressed",IF(G46>3,"Strong","Grey Zone")) -> Strong | H47: =IF(H46<1.81,"Distressed",IF(H46>3,"Strong","Grey Zone")) -> Strong | I47: =IF(I46<1.81,"Distressed",IF(I46>3,"Strong","Grey Zone")) -> Strong

Sheet List of Stocks
A2: COMPANY_NAME | B2: BSE | C2: NSE | D2: Industry
A3: 20 MICRONS LTD | B3: 533022 | C3: 20MICRONS | D3: Mining
A4: 21ST CENTURY MANAGEMENT SERVICES LTD | B4: 526921 | C4: 21STCENMGM | D4: Other Financial Services
A5: 3I INFOTECH LTD | B5: 532628 | C5: 3IINFOTECH | D5: IT Consulting & Software
A6: 3M (INDIA) LTD | B6: 523395 | C6: 3M(INDIA) | D6: Diversified
A7: 3M INDIA LTD | B7: 523395 | C7: 3MINDIA | D7: Diversified
A8: 3P LAND HOLDINGS LTD | B8: 516092 | C8: 3PLAND | D8: Paper & Paper Products
A9: 5PAISA CAPITAL LTD | B9: 540776 | C9: 5PAISA | D9: Other Financial Services
A10: 63 MOONS TECHNOLOGIES LTD | B10: 526881 | C10: 63MOONS | D10: IT Consulting & Software
A11: 7NR RETAIL LTD | B11: 540615 | C11: Not Listed | D11: Specialty Retail
A12: 7SEAS ENTERTAINMENT LTD | B12: 540874 | C12: Not Listed | D12: Movies & Entertainment
A13: 8K MILES SOFTWARE SERVICES LTD | B13: 512161 | C13: 8KMILES | D13: Internet Software & Services
A14: A & M FEBCON LTD | B14: 540697 | C14: Not Listed | D14: Industrial Machinery
A15: A AND M JUMBO BAGS LTD | B15: Not Listed | C15: AMJUMBO | D15: SME
A16: A INFRASTRUCTURE LTD | B16: 539620 | C16: Not Listed | D16: Cement & Cement Products
A17: A K SPINTEX LTD | B17: 539300 | C17: Not Listed | D17: Textiles
A18: A K CAPITAL SERVICES LTD | B18: 530499 | C18: Not Listed | D18: Finance (including NBFCs)
A19: A.F. Enterprises Ltd | B19: 538351 | C19: AFEL | D19: Investment Companies
A20: A-1 ACID LTD | B20: 542012 | C20: Not Listed | D20: Comm.Trading & Distribution
A21: A2Z INFRA ENGINEERING LTD | B21: 533292 | C21: A2ZINFRA | D21: Utilities:Non-Elec.
A22: AADHAAR VENTURES (INDIA) LTD | B22: 531611 | C22: Not Listed | D22: Finance (including NBFCs)
A23: AADHAAR VENTURES INDIA LTD | B23: 531611 | C23: Not Listed | D23: Finance (including NBFCs)
A24: AAKASH EXPLORATION SERVICES LTD | B24: Not Listed | C24: AAKASH | D24: SME
A25: AANANDA LAKSHMI SPINNING MILLS LTD | B25: 539096 | C25: Not Listed | D25: Textiles
A26: AANCHAL ISPAT LTD | B26: 538812 | C26: Not Listed | D26: Iron & Steel/Interm.Products
A27: AAR COMMERCIAL COMPANY LTD | B27: 539632 | C27: Not Listed | D27: Distributors
A28: Aar Shyam India Investment Company Ltd | B28: 542377 | C28: AARSHYAM | D28: Finance (including NBFCs)
A29: AAREY DRUGS & PHARMACEUTICALS LTD | B29: 524412 | C29: Not Listed | D29: Pharmaceuticals
A30: AARON INDUSTRIES LTD | B30: Not Listed | C30: AARON | D30: SME
A31: Aartech Solonics Ltd | B31: 542580 | C31: AARTECH | D31: Heavy Electrical Equipment
A32: AARTI DRUGS LTD | B32: 524348 | C32: AARTIDRUGS | D32: Pharmaceuticals
A33: AARTI INDUSTRIES LTD | B33: 524208 | C33: AARTIIND | D33: Commodity Chemicals
A34: AARV INFRATEL LTD | B34: 526488 | C34: Not Listed | D34: Textiles
A35: AARVEE DENIMS & EXPORTS LTD | B35: 514274 | C35: AARVEEDEN | D35: Textiles
A36: AARVI ENCON LTD | B36: Not Listed | C36: AARVI | D36: SME
A37: AASHEE INFOTECH LTD | B37: 519319 | C37: Not Listed | D37: Internet Software & Services
A38: AASWA TRADING & EXPORTS LTD | B38: 512038 | C38: Not Listed | D38: Comm.Trading & Distribution
A39: AAVAS FINANCIERS LTD | B39: 541988 | C39: AAVAS | D39: Housing Finance
A40: AAYUSH FOOD AND HERBS LTD | B40: 539528 | C40: Not Listed | D40: Packaged Foods
A41: ABAN OFFSHORE LTD | B41: 523204 | C41: ABAN | D41: Exploration & Production
A42: ABANS ENTERPRISES LTD | B42: 512165 | C42: Not Listed | D42: Comm.Trading & Distribution
A43: ABB INDIA LTD | B43: 500002 | C43: ABB | D43: Heavy Electrical Equipment
A44: ABBOTT (INDIA) LTD | B44: 500488 | C44: ABBOT(INDIA) | D44: Pharmaceuticals
A45: ABBOTT INDIA LTD | B45: 500488 | C45: ABBOTINDIA | D45: Pharmaceuticals
A46: ABC (INDIA) LTD | B46: 520123 | C46: Not Listed | D46: Surface Transportation
A47: ABC GAS INTERNATIONAL LTD | B47: 513119 | C47: Not Listed | D47: Copper
A48: ABC INDIA LTD | B48: 520123 | C48: Not Listed | D48: Surface Transportation
... A56: ABIRAMI FINANCIAL SERVICES INDIA LTD | B56: 511756 | C56: Not Listed | D56: Finance (including NBFCs)
A57: ABM INTERNATIONAL LTD | B57: Not Listed | C57: ABMINTLTD | D57: Others
A58: ABM KNOWLEDGEWARE LTD | B58: 531161 | C58: Not Listed | D58: IT Software Products
A59: ACC LTD | B59: 500410 | C59: ACC | D59: Cement & Cement Products
A60: ACCEL LTD | B60: 517494 | C60: Not Listed | D60: Storage Media & Peripherals
A61: ACCELYA KALE SOLUTIONS LTD | B61: 532268 | C61: ACCELYA | D61: IT Consulting & Software
A62: ACCORD SYNERGY LTD | B62: Not Listed | C62: ACCORD | D62: SME
A63: ACCURACY SHIPPING LTD | B63: Not Listed | C63: ACCURACY | D63: SME
A64: ACE EDUTREND LTD | B64: 530093 | C64: Not Listed | D64: Education
A65: ACE INTEGRATED SOLUTIONS LTD | B65: Not Listed | C65: ACEINTEG | D65: SME
A66: ACE MEN ENGG WORKS LTD | B66: 539661 | C66: Not Listed | D66: Distributors
A67: ACE SOFTWARE EXPORTS LTD | B67: 531525 | C67: Not Listed | D67: IT Software Products
A68: Achal Investments Ltd | B68: 538570 | C68: ACHAL | D68: Other Financial Services
A69: ACI INFOCOM LTD | B69: 517356 | C69: Not Listed | D69: Storage Media & Peripherals
A70: ACKNIT INDUSTRIES LTD | B70: 530043 | C70: Not Listed | D70: Other Apparels & Accessories
A71: ACME RESOURCES LTD | B71: 539391 | C71: Not Listed | D71: Finance (including NBFCs)
A72: ACROW INDIA LTD. | B72: 513149 | C72: ACROW | D72: Iron &amp; Steel Products
A73: ACRYSIL LTD | B73: 524091 | C73: Not Listed | D73: Plastic Products
A74: ACTION CONSTRUCTION EQUIPMENT LTD | B74: 532762 | C74: ACE | D74: Transport Related Services
A75: ACTION FINANCIAL SERVICES (INDIA) LTD | B75: 511706 | C75: Not Listed | D75: Other Financial Services
A76: ACTION FINANCIAL SERVICES INDIA LTD | B76: 511706 | C76: Not Listed | D76: Other Financial Services
A77: ACTIVE CLOTHING CO LTD | B77: 541144 | C77: Not Listed | D77: Other Apparels & Accessories
... A135: AGRI-TECH INDIA LTD | B135: 537292 | C135: AGRITECH | D135: Other Agricultural Products
A136: AGRO PHOS (INDIA) LTD | B136: Not Listed | C136: AGROPHOS | D136: SME
A137: AGRO PHOS INDIA LTD | B137: Not Listed | C137: AGROPHOS | D137: SME
A138: AGRO TECH FOODS LTD | B138: 500215 | C138: ATFL | D138: Other Agricultural Products
A139: AHIMSA INDUSTRIES LTD | B139: Not Listed | C139: AHIMSA | D139: SME
A140: AHLADA ENGINEERS LTD | B140: Not Listed | C140: AHLADA | D140: SME
A141: AHLUWALIA CONTRACTS (INDIA) LTD | B141: 532811 | C141: AHLUCONT | D141: Realty
A142: AHLUWALIA CONTRACTS INDIA LTD | B142: 532811 | C142: AHLUCONT | D142: Realty
A143: AHMEDABAD STEELCRAFT LTD | B143: 522273 | C143: Not Listed | D143: Iron & Steel/Interm.Products
A144: AI CHAMPDANY INDUSTRIES LTD | B144: 532806 | C144: Not Listed | D144: Jute & Jute Products
A145: AIA ENGINEERING LTD | B145: 532683 | C145: AIAENG | D145: Other Industrial Goods
A146: AIMCO PESTICIDES LTD | B146: 524288 | C146: Not Listed | D146: Agrochemicals
A147: AIRAN LTD | B147: Not Listed | C147: AIRAN | D147: SME
A148: AIRO LAM LTD | B148: Not Listed | C148: AIROLAM | D148: SME
A149: AISHWARYA TELECOM LTD | B149: 532975 | C149: Not Listed | D149: Telecom Equipment
A150: AJANTA PHARMA LTD | B150: 532331 | C150: AJANTPHARM | D150: Pharmaceuticals
A151: AJANTA SOYA LTD | B151: 519216 | C151: Not Listed | D151: Edible Oils
A152: AJCON GLOBAL SERVICES LTD | B152: 511692 | C152: Not Listed | D152: Other Financial Services
A153: AJEL LTD | B153: 530713 | C153: Not Listed | D153: IT Consulting & Software
A154: AJMERA REALTY & INFRA (INDIA) LTD | B154: 513349 | C154: AJMERA | D154: Realty
A155: AJMERA REALTY & INFRA INDIA LTD | B155: 513349 | C155: AJMERA | D155: Realty
A156: AJOONI BIOTECH LTD | B156: Not Listed | C156: AJOONI | D156: SME
A157: AJWA FUN WORLD & RESORT LTD | B157: 526628 | C157: Not Listed | D157: Other Leisure Facilities
A158: AKAR AUTO INDUSTRIES LTD | B158: 530621 | C158: Not Listed | D158: Industrial Machinery
A159: AKASH INFRA PROJECTS LTD | B159: Not Listed | C159: AKASH | D159: SME
A160: AKASHDEEP METAL INDUSTRIES LTD | B160: 538778 | C160: Not Listed | D160: Finance (including NBFCs)
A161: AKG EXIM LTD | B161: Not Listed | C161: AKG | D161: SME
A162: AKI (INDIA) LTD | B162: 542020 | C162: Not Listed | D162: Other Apparels & Accessories
A163: AKI INDIA LTD | B163: 542020 | C163: Not Listed | D163: Other Apparels & Accessories
A164: AKM LACE AND EMBROTEX LTD | B164: 540718 | C164: Not Listed | D164: Textiles
A165: AKME STAR HOUSING FINANCE LTD | B165: 539017 | C165: Not Listed | D165: Housing Finance
...
